Workbook
Name _Ref209109087: 'fig1-14'!$A$1
Name BoxPlot: "BoxPlot"
Name Bubble: "Bubble"
Name Candlestick: "Candlestick"
Name Chart: "Chart"
Name ChartImage: "ChartImage"
Name ColumnRange: "ColumnRange"
Name Dumbbell: "Dumbbell"
Name Heatmap: "Heatmap"
Name Histogram: "Histogram"
Name Map: "Map"
Name OHLC: "OHLC"
Name PieChart: "PieChart"
Name Scatter: "Scatter"
Name Series: "Series"
Name Stripe: "Stripe"
Name Table: "Table"
Name TreeMap: "TreeMap"
Name Waterfall: "Waterfall"

Sheet fig1-14
A1: Figure 1.14. Without fiscal adjustment, public debt would rise rapidly in coming decades
A28: Source: OECD Long-term Model, OECD calculations.
A30: A. Long-term spending pressures under unchanged policies and a stable debt ratio | J30: B. Gross public debt
C31: Health and long-term care expenditure | D31: Pension expenditure | E31: Other primary expenditure | F31: Net interest payments | G31: Other factors | H31: Total | L31: Current tax and spending structure with future ageing and health costs | M31: Path with fiscal adjustment
A32: Netherlands | B32: NLD | C32: 0.74062699 | D32: 0.19766243 | E32: -1.382176 | F32: 0.49646563 | G32: -0.70520415 | H32: -0.65262505 | J32: 2022 | L32: 55.047571 | M32: 55.047571
A33: Latvia | B33: LVA | C33: 1.4983708 | D33: 1.3919574 | E33: 0.26386613 | F33: 0.44216613 | G33: -2.8710465 | H33: 0.72531392 | J33: 2023 | L33: 55.708872 | M33: 55.708872
A34: Hungary | B34: HUN | C34: 1.6616089 | D34: 1.2924536 | E34: 0.22513327 | F34: -1.4441883 | G34: -0.054906841 | H34: 1.6801006 | J34: 2024 | L34: 57.083484 | M34: 57.083484
A35: Ireland | B35: IRL | C35: 1.6734319 | D35: 1.3084202 | E35: -0.26327999 | F35: 0.15895834 | G35: -0.935387 | H35: 1.9421435 | J35: 2025 | L35: 59.940059 | M35: 59.940059
A36: Portugal | B36: PRT | C36: 2.4482982 | D36: -0.92347057 | E36: 1.1571901 | F36: 0.6402376 | G36: -0.81631293 | H36: 2.5059424 | J36: 2026 | L36: 62.50111 | M36: 62.50111
A37: Estonia | B37: EST | C37: 1.8687966 | D37: 1.1972189 | E37: -0.32586991 | F37: -0.15945985 | G37: 0.17351302 | H37: 2.7541988 | J37: 2027 | L37: 62.967842 | M37: 62.967842
A38: Greece | B38: GRC | C38: 1.8224936 | D38: -3.90984 | E38: 2.250804 | F38: 2.8934109 | G38: 0.10818989 | H38: 3.1650584 | J38: 2028 | L38: 63.623129 | M38: 63.123129
A39: Israel | B39: ISR | C39: 1.4730734 | D39: 1.7512456 | E39: -0.62143965 | F39: 0.39654417 | G39: 0.42376143 | H39: 3.4231849 | J39: 2029 | L39: 64.390122 | M39: 62.884266
A40: Lithuania | B40: LTU | C40: 1.839654 | D40: 2.162641 | E40: 0.87631152 | F40: 0.44021401 | G40: -1.6951716 | H40: 3.6236489 | J40: 2030 | L40: 65.286786 | M40: 62.260749
A41: Germany | B41: DEU | C41: 2.1344435 | D41: 1.7646239 | E41: 0.53797623 | F41: 0.4681321 | G41: -1.1112829 | H41: 3.7938928 | J41: 2031 | L41: 66.321513 | M41: 61.250342
A42: United Kingdom | B42: GBR | C42: 2.7608864 | D42: 1.6251628 | E42: 0.21917018 | F42: 0.37528375 | G42: 0.045072419 | H42: 5.0255755 | J42: 2032 | L42: 67.500605 | M42: 60.346826
A43: Denmark | B43: DNK | C43: 2.1727978 | D43: 2.416768 | E43: 1.5368546 | F43: -0.53986907 | G43: -0.16613078 | H43: 5.4204205 | J43: 2033 | L43: 68.824765 | M43: 59.545789
... A60: Luxembourg | B60: LUX | C60: 2.0582062 | D60: 6.5106372 | E60: 4.2079157 | F60: -1.3703873 | G60: 2.9692215 | H60: 14.375593 | J60: 2050 | L60: 113.22774 | M60: 57.282972
A61: Slovenia | B61: SVN | C61: 2.5543748 | D61: 4.4439576 | E61: 3.219083 | F61: 0.23938286 | G61: 4.1133115 | H61: 14.57011
A62: Slovak Republic | B62: SVK | C62: 2.8107808 | D62: 4.8315432 | E62: 2.889101 | F62: 0.80806957 | G62: 3.9163407 | H62: 15.255835
A63: Korea | B63: KOR | C63: 4.2845011 | D63: 6.5200724 | E63: 5.9909711 | F63: -0.11867803 | G63: -0.36337458 | H63: 16.313492

Sheet OECD_proj
A1: year | B1: OECD_proj | C1: OECD_adj_proj
A2: ='fig1-14'!J32 -> 2022 | B2: ='fig1-14'!L32 -> 55.047571 | C2: ='fig1-14'!M32 -> 55.047571
A3: ='fig1-14'!J33 -> 2023 | B3: ='fig1-14'!L33 -> 55.708872 | C3: ='fig1-14'!M33 -> 55.708872
A4: ='fig1-14'!J34 -> 2024 | B4: ='fig1-14'!L34 -> 57.083484 | C4: ='fig1-14'!M34 -> 57.083484
A5: ='fig1-14'!J35 -> 2025 | B5: ='fig1-14'!L35 -> 59.940059 | C5: ='fig1-14'!M35 -> 59.940059
A6: ='fig1-14'!J36 -> 2026 | B6: ='fig1-14'!L36 -> 62.50111 | C6: ='fig1-14'!M36 -> 62.50111
A7: ='fig1-14'!J37 -> 2027 | B7: ='fig1-14'!L37 -> 62.967842 | C7: ='fig1-14'!M37 -> 62.967842
A8: ='fig1-14'!J38 -> 2028 | B8: ='fig1-14'!L38 -> 63.623129 | C8: ='fig1-14'!M38 -> 63.123129
A9: ='fig1-14'!J39 -> 2029 | B9: ='fig1-14'!L39 -> 64.390122 | C9: ='fig1-14'!M39 -> 62.884266
A10: ='fig1-14'!J40 -> 2030 | B10: ='fig1-14'!L40 -> 65.286786 | C10: ='fig1-14'!M40 -> 62.260749
A11: ='fig1-14'!J41 -> 2031 | B11: ='fig1-14'!L41 -> 66.321513 | C11: ='fig1-14'!M41 -> 61.250342
A12: ='fig1-14'!J42 -> 2032 | B12: ='fig1-14'!L42 -> 67.500605 | C12: ='fig1-14'!M42 -> 60.346826
A13: ='fig1-14'!J43 -> 2033 | B13: ='fig1-14'!L43 -> 68.824765 | C13: ='fig1-14'!M43 -> 59.545789
... A30: ='fig1-14'!J60 -> 2050 | B30: ='fig1-14'!L60 -> 113.22774 | C30: ='fig1-14'!M60 -> 57.282972

Sheet PBO
A1: year | B1: PBO_proj
A2: 2024 | B2: 48.524
A3: 2025 | B3: 51.865
A4: 2026 | B4: 55.758
A5: 2027 | B5: 57.68
A6: 2028 | B6: 58.434
A7: 2029 | B7: 58.7
A8: 2030 | B8: 57.235
A9: 2031 | B9: 55.693
A10: 2032 | B10: 54.118
A11: 2033 | B11: 52.531
A12: 2034 | B12: 50.85
A13: 2035 | B13: 49.071
... A47: 2069 | B47: 3.425

Sheet About this file
B3: This Excel file contains the data for the following figure or table:
B5: OECD Economic Surveys: Australia 2026 - © OECD 2026
B6: Key policy insights - Figure 1.14. Without fiscal adjustment, public debt would rise rapidly in coming decades
B7: Version 1 - Last updated: 21-Jan-2026
B8: Disclaimer: http://oe.cd/disclaimer
B10: Permanent location of this file: https://stat.link/gdxr47
