Workbook

Sheet Display
A1: Key fiscal variable selected from drop-down list box ↓ | B1: 3 | C1: =OFFSET($A$1,$B$1,1) -> 78
A2: Total Crown OBEGAL | B2: 41
A3: Total Crown OBEGAL excluding ACC | B3: 45
A4: Net core Crown debt excl. NZSF & advances (excludes Crown entity debt) | B4: 78
A5: Core Crown residual cash | B5: 51
A6: Core Crown revenue | B6: 47
A7: Core Crown expenses | B7: 48
A8: Core Crown operating balance | B8: 49
A9: Core Crown primary balance | B9: 50
A10: Total Crown revenue | B10: 34
A11: Total Crown expenses | B11: 35
A12: Total Crown operating balance (excluding minority interests) | B12: 39
A13: Core Crown tax revenue | B13: 140
... A20: Core Crown borrowings | B20: 71

Sheet Guide
A1: Explanation of the worksheets in the 2025 Long-Term Fiscal Model (LTFM) and how they link to one another
A3: Name of worksheet | D3: Purpose | I3: Provides inputs to these worksheets | N3: Uses outputs from these worksheets
A5: Display | D5: This is a hidden worksheet. It provides | I5: Each of the main modelling worksheets. | N5: None.
D6: offsets to allow the chosen fiscal variable | I6: This model only contains one, which
D7: track to be displayed at the top of each | I7: is labelled Long-Term Fiscal Model.
D8: of the main modelling worksheets. | I8: Other worksheets can be copied from this
I9: and run off a different set of parameters
I10: from the Assumptions worksheet.
A12: Guide | D12: This is this worksheet. It provides some | I12: None. Purely for information purposes | N12: None.
D13: information to help users know how the | I13: and to help users of the model.
D14: various worksheets in the model interact.
A16: Sources | D16: This is also an information worksheet. | I16: None. Purely for information purposes | N16: None.
D17: It provides lists of data and exogenous | I17: and to help users of the model.
D18: tracks used in the model. Information is
D19: provided about the data, distribution or
D20: track, including from where it is sourced
D21: and when it was produced.
A23: Statistics NZ | D23: These are the most recent New Zealand | I23: Used extensively throughout the | N23: None.
D24: (NZ) resident population projections and | I24: Population Treasury and Labour Force
D25: Labour Force projections, by gender and | I25: Treasury worksheets in calculations to
D26: single year of age. They are produced by | I26: produce the Population and Labour Force
D27: Statistics New Zealand and are updated | I27: age and gender distributions that match
D28: when a new version becomes available. | I28: the aggregate values in forecast years.
D29: As well as population and labour force
D30: numbers the worksheet has participation
D31: rates (numbers in labour force divided by
D32: numbers in demographic group).
A34: Population Treasury | D34: These are age and gender distributions | I34: Used in numerous places in the main | N34: Statistics NZ
D35: of the NZ population that match the | I35: modelling worksheets, wherever | N35: Economic Forecasts
D36: aggregate forecasts in forecast years and | I36: demographic growth is required. Used
D37: are projected out into post-forecast years. | I37: in projecting some economic variables.
D38: They also adjust population projections | I38: Used as a driver of recipient numbers for
D39: for alternative net migration totals to the | I39: some expense types, especially New
D40: values used in Statistics NZ projections. | I40: Zealand Superannuation (NZS) and other
I41: welfare expenses. Used in projecting age
I42: and gender group Labour Force numbers
I43: in the Labour Force Treasury worksheet.
A45: Labour Force Treasury | D45: These are age and gender distributions | I45: Used in the economic projections of the | N45: Statistics NZ
D46: of the NZ labour force that match the | I46: main modelling worksheets to project the | N46: Population Treasury
D47: aggregate forecasts in forecast years and | I47: aggregate labour force. This variable is | N47: Economic Forecasts
D48: are projected out into post-forecast years. | I48: a key driver in the projections of both
D49: This worksheet uses labour force | I49: real and nominal GDP.
D50: participation rates, by single year of age
D51: and gender, multiplied by the equivalent
D52: population group in Population Treasury,
D53: to produce labour force numbers by
D54: single year of age and gender.
A56: Exogenous | D56: This worksheet contains a number of | I56: Used in many places throughout the main | N56: None.
D57: projected tracks and demographic | I57: modelling worksheets, often in regard to
D58: distributions. Some are produced by | I58: a particular asset, liability or expense
D59: Treasury, while others are sourced from | I59: type. Demographic distributions are used
D60: outside agencies. They all share the | I60: as inputs to the projected growth of
D61: characteristic of being produced outside | I61: recipient numbers in various welfare
D62: the model i.e. are exogenous inputs. | I62: expenses and Student Allowances.
D63: At the bottom of this worksheet are | I63: Bottom-up modelling of health and
D64: parameters related to the NZ personal | I64: education expenditure uses demographic
D65: tax regime that are used in fiscal drag | I65: distributions particular to these areas.
D66: modelling for both tax and NZS.
A68: Allocation | D68: This worksheet cakculates the division of | I68: In the main modelling worksheets this is | N68: None.
D69: forecast year operating allowances and | I69: used to allocate the operating allowances
D70: top-down expense adjustments into | I70: and the top-down expense adjustments to
D71: eleven different expense categories and | I71: individual expense categories. It is also
D72: five sub-categories of education expense. | I72: used to allocate the capital allowances
D73: It also calculates the division of forecast | I73: and the top-down capital expense
D74: forecast year capital allowances and | I74: adjustments to individual asset categories.
D75: top-down capital expense adjustments into
D76: four different asset categories.
D77: The percentages used in this worksheet
D78: should not be taken as definitive of
D79: future funding allocations. They are simply
D80: based on averages of growth in the past for
D81: these expense and asset types that are
D82: expected to have their future funding come
D83: from the operating and capital allowances.
A85: Fiscal Outturns | D85: This worksheet contains historical data | I85: None. Purely for information purposes | N85: None.
D86: relating to the main fiscal indicators that | I86: and to help users of the model.
D87: can be selected in the pull-down box at
D88: the top of the main modelling worksheets.
D89: There is more explanation at the top of
D90: this worksheet about why data prior to
D91: 2018/19 is given here and not in the main
D92: modelling worksheets themselves.
A94: Economic Forecasts | D94: The latest set of economic forecast | I94: Used as the base of economic projections | N94: None.
D95: variables, as well as historical outturns | I95: in the main modelling worksheets.
D96: of these variables, are stored in this | I96: Also used as the base of various inputs
D97: worksheet. It also contains parameters, | I97: into the projection of NZS and other
D98: derived from the economic forecasts by | I98: categories of welfare expenditure in the
D99: another Treasury model, that are used to | I99: main modelling worksheets.
D100: project New Zealand Superannuation
D101: (NZS) expenses. Historical outturns and
D102: forecasts of recipient numbers for NZS
D103: and the Jobseeker Support benefit are
D104: also provided in this worksheet.
A106: Fiscal Forecasts | D106: The fiscal equivalent of the Economic | I106: Used as the base of projections of asset, | N106: None.
D107: Forecasts worksheet, this contains the | I107: liability, revenue and expense categories
D108: most recent set of fiscal forecast | I108: in the main modelling worksheets.
D109: variables. For reasons explained in the | I109: Covers core Crown and total Crown
D110: Fiscal Outturns worksheet, there are only | I110: variables, and in some cases extends to
D111: historical outturns dating from 2018/19 | I111: Crown entity and State-owned enterprise
D112: in this worksheet. Because there is so | I112: (SOE) variables.
...

Sheet Sources
A1: LONG-TERM FISCAL MODEL (LTFM) - 2025 VERSION
A2: Unless otherwise stated, forecasts and projections are produced by the New Zealand Treasury
A3: Unless otherwise stated, all post-forecast projections are produced by the LTFM model
A4: The adjective "outturn", normally used before the word data, means it comes from a completed time period
A6: This version of the LTFM uses: | E6: Budget Economic and Fiscal Update (BEFU) 2025 data and forecasts
A8: Economic Data | C8: History | E8: Outturn data from Treasury databases | J8: Mainly Statistics New Zealand (Stats NZ) measures
C9: Forecasts | J9: BEFU 2025 version
A11: Fiscal Data | C11: History | E11: Outturn data from Treasury publications | J11: Mainly from Financial Statements published in past Budget EFU reports
C12: Forecasts | J12: BEFU 2025 version
A14: Demographic Data | C14: History | E14: Outturn data from Stats NZ | J14: Accessible from Stats NZ website
A15: (by gender and | C15: Forecasts | E15: Treasury forecasts aggregate population | J15: BEFU 2025 version
A16: single year of age) | C16: Projections | E16: Based on those of Stats NZ | J16: Uses National Population Projections, produced in 2025
A18: Labour Force | C18: History | E18: Outturn data from Stats NZ | J18: Based on Household Labour Force Survey (HLFS)
A19: (by gender and | C19: Forecasts | E19: Treasury forecasts aggregate labour force | J19: BEFU 2025 version
A20: single year of age) | C20: Projections | E20: Based on those of Stats NZ | J20: Uses National Labour Force Projections, produced in 2025
A22: Social welfare | C22: History | E22: Outturn data from Treasury publications | J22: Mainly from Financial Statements published in past Budget EFU reports
A23: transfers | C23: Forecasts | E23: Forecasts from Ministry of Social | J23: BEFU 2025 version
E24: Development (MSD) and Inland Revenue
E25: Department (IRD) for Working for Families
A27: New Zealand | C27: History | E27: Outturn data from Treasury publications | J27: Mainly from Financial Statements published in past Budget EFU reports
A28: Superannuation | C28: Forecasts | E28: Forecasts from the NZSF | J28: BEFU 2025 version
A29: Fund (NZSF) | C29: Projections | E29: Projection produced by Treasury | J29: 2025 update
A31: Accident Compen- | C31: History | E31: Outturn data from Treasury publications | J31: Mainly from Financial Statements published in past Budget EFU reports
A32: sation Corporation | C32: Forecasts | E32: Forecasts from ACC | J32: BEFU 2025 version
A33: (ACC) data | C33: Projections | E33: Projection produced by ACC | J33: Asset/liability track, 2025 update
A35: Student Loans | C35: History | E35: Outturn data from Treasury publications | J35: Mainly from Financial Statements published in past Budget EFU reports
A36: track | C36: Forecasts | E36: Forecasts from IRD and the | J36: BEFU 2025 version
E37: Ministry of Education (MoE)
C38: Projections | E38: Projection produced by the MoE | J38: 2025 updated track provided by the Ministry of Education
A40: KiwiSaver expenses | C40: History | E40: Outturn data from Treasury publications | J40: Mainly from Financial Statements published in past Budget EFU reports
A41: Inland Revenue | C41: Forecasts | E41: Forecasts from IRD | J41: BEFU 2025 version
A42: Department (IRD) | C42: Projections | E42: Projection from IRD | J42: BEFU 2025 version
A44: Government | C44: History | E44: Outturn data from Treasury publications | J44: Mainly from Financial Statements published in past Budget EFU reports
A45: Superannuation | C45: Forecasts | E45: Forecasts based on actuarial valuations | J45: BEFU 2025 version
A46: Fund (GSF) | C46: Projections | E46: Projection produced by actuaries for GSF | J46: 2012 version
A48: Tax Receivable write- | C48: History | E48: Outturn data from Treasury publications | J48: Mainly from Financial Statements published in past Budget EFU reports
A49: downs & impairments | C49: Forecasts | E49: Forecasts from IRD | J49: BEFU 2025 version
A51: Main benefit age & | E51: Based on administrative data from MSD | J51: 2025 update
A52: gender distribution
A54: Education age & | E54: Based on data from Minstry of Education | J54: 2025 update
A55: gender distribution | E55: Education Counts website
A57: Health age & | E57: Based on data provided by | J57: 2025 update
A58: gender distribution | E58: the Ministry of Health

Sheet Statistics NZ
A1: STATISTICS NEW ZEALAND OUTTURNS AND PROJECTIONS OF RESIDENT POPULATION OF NEW ZEALAND AND LABOUR FORCE, BY SINGLE YEAR OF AGE AND GENDER, AS AT 30 JUNE
A2: Population projections | B2: National population projections: 2024 (base) - 2078 50th percentile projection
A3: Labour Force projections | B3: National labour force projections: 2024 (base) - 2078 50th percentile projection
A4: Year ended 30 June | B4: 2005/06 | C4: 2006/07 | D4: 2007/08 | E4: 2008/09 | F4: 2009/10 | G4: 2010/11 | H4: 2011/12 | I4: 2012/13 | J4: 2013/14 | K4: 2014/15 | L4: 2015/16 | M4: 2016/17 | N4: 2017/18 | O4: 2018/19 | P4: 2019/20 | Q4: 2020/21 | R4: 2021/22 | S4: 2022/23 | T4: 2023/24 | U4: 2024/25 | V4: 2025/26 | W4: 2026/27 | X4: 2027/28 | Y4: 2028/29 | Z4: 2029/30 | AA4: 2030/31 | AB4: 2031/32 | AC4: 2032/33 | AD4: 2033/34 | AE4: 2034/35 | AF4: 2035/36 | AG4: 2036/37 | AH4: 2037/38 | AI4: 2038/39 | AJ4: 2039/40 | AK4: 2040/41 | AL4: 2041/42 | AM4: 2042/43 | AN4: 2043/44 | AO4: 2044/45 | AP4: 2045/46 | AQ4: 2046/47 | AR4: 2047/48 | AS4: 2048/49 | AT4: 2049/50 | AU4: 2050/51 | AV4: 2051/52 | AW4: 2052/53 | AX4: 2053/54 | AY4: 2054/55 | AZ4: 2055/56 | BA4: 2056/57 | BB4: 2057/58 | BC4: 2058/59 | BD4: 2059/60 | BE4: 2060/61 | BF4: 2061/62 | BG4: 2062/63 | BH4: 2063/64 | BI4: 2064/65
B5: 2006 | C5: 2007 | D5: 2008 | E5: 2009 | F5: 2010 | G5: 2011 | H5: 2012 | I5: 2013 | J5: 2014 | K5: 2015 | L5: 2016 | M5: 2017 | N5: 2018 | O5: 2019 | P5: 2020 | Q5: 2021 | R5: 2022 | S5: 2023 | T5: 2024 | U5: 2025 | V5: 2026 | W5: 2027 | X5: 2028 | Y5: 2029 | Z5: 2030 | AA5: 2031 | AB5: 2032 | AC5: 2033 | AD5: 2034 | AE5: 2035 | AF5: 2036 | AG5: 2037 | AH5: 2038 | AI5: 2039 | AJ5: 2040 | AK5: 2041 | AL5: 2042 | AM5: 2043 | AN5: 2044 | AO5: 2045 | AP5: 2046 | AQ5: 2047 | AR5: 2048 | AS5: 2049 | AT5: 2050 | AU5: 2051 | AV5: 2052 | AW5: 2053 | AX5: 2054 | AY5: 2055 | AZ5: 2056 | BA5: 2057 | BB5: 2058 | BC5: 2059 | BD5: 2060 | BE5: 2061 | BF5: 2062 | BG5: 2063 | BH5: 2064 | BI5: 2065
A6: Population (millions) | B6: =SUM(B$15:B$110,B$115:B$210)/1000000 -> 4.18463 | C6: =SUM(C$15:C$110,C$115:C$210)/1000000 -> 4.22386 | D6: =SUM(D$15:D$110,D$115:D$210)/1000000 -> 4.25975 | E6: =SUM(E$15:E$110,E$115:E$210)/1000000 -> 4.3026 | F6: =SUM(F$15:F$110,F$115:F$210)/1000000 -> 4.35065 | G6: =SUM(G$15:G$110,G$115:G$210)/1000000 -> 4.38397 | H6: =SUM(H$15:H$110,H$115:H$210)/1000000 -> 4.40798 | I6: =SUM(I$15:I$110,I$115:I$210)/1000000 -> 4.4421 | ... BI6: =SUM(BI$15:BI$110,BI$115:BI$210)/1000000 -> 7.28726
A7: Annual growth (%) | C7: =C$6/B$6-1 -> 0.0093747834 | D7: =D$6/C$6-1 -> 0.0084969672 | E7: =E$6/D$6-1 -> 0.010059276 | F7: =F$6/E$6-1 -> 0.011167666 | G7: =G$6/F$6-1 -> 0.0076586257 | H7: =H$6/G$6-1 -> 0.0054767711 | I7: =I$6/H$6-1 -> 0.007740507 | J7: =J$6/I$6-1 -> 0.016737579 | ... BI7: =BI$6/BH$6-1 -> 0.0059926696
A8: Working-age popn (15+, millions) | B8: =SUM(B$30:B$110,B$130:B$210)/1000000 -> 3.29632 | C8: =SUM(C$30:C$110,C$130:C$210)/1000000 -> 3.33256 | D8: =SUM(D$30:D$110,D$130:D$210)/1000000 -> 3.36424 | E8: =SUM(E$30:E$110,E$130:E$210)/1000000 -> 3.40144 | F8: =SUM(F$30:F$110,F$130:F$210)/1000000 -> 3.44251 | G8: =SUM(G$30:G$110,G$130:G$210)/1000000 -> 3.47326 | H8: =SUM(H$30:H$110,H$130:H$210)/1000000 -> 3.49817 | I8: =SUM(I$30:I$110,I$130:I$210)/1000000 -> 3.53331 | ... BI8: =SUM(BI$30:BI$110,BI$130:BI$210)/1000000 -> 6.2968
A9: =$A$7 -> Annual growth (%) | C9: =C$8/B$8-1 -> 0.010994078 | D9: =D$8/C$8-1 -> 0.0095062054 | E9: =E$8/D$8-1 -> 0.011057475 | F9: =F$8/E$8-1 -> 0.012074298 | G9: =G$8/F$8-1 -> 0.0089324359 | H9: =H$8/G$8-1 -> 0.0071719365 | I9: =I$8/H$8-1 -> 0.010045252 | J9: =J$8/I$8-1 -> 0.020216171 | ... BI9: =BI$8/BH$8-1 -> 0.0068677695
A10: Labour Force (LF, millions) | T10: =SUM(T$215:T$280,T$285:T$350)/1000000 -> 3.0711 | U10: =SUM(U$215:U$280,U$285:U$350)/1000000 -> 3.1062 | V10: =SUM(V$215:V$280,V$285:V$350)/1000000 -> 3.1441 | W10: =SUM(W$215:W$280,W$285:W$350)/1000000 -> 3.18293 | X10: =SUM(X$215:X$280,X$285:X$350)/1000000 -> 3.22259 | Y10: =SUM(Y$215:Y$280,Y$285:Y$350)/1000000 -> 3.2622 | Z10: =SUM(Z$215:Z$280,Z$285:Z$350)/1000000 -> 3.3017 | AA10: =SUM(AA$215:AA$280,AA$285:AA$350)/1000000 -> 3.34058 | ... BI10: =SUM(BI$215:BI$280,BI$285:BI$350)/1000000 -> 4.23825
A11: =$A$7 -> Annual growth (%) | U11: =U$10/T$10-1 -> 0.01142913 | V11: =V$10/U$10-1 -> 0.012201404 | W11: =W$10/V$10-1 -> 0.012350116 | X11: =X$10/W$10-1 -> 0.012460217 | Y11: =Y$10/X$10-1 -> 0.012291356 | Z11: =Z$10/Y$10-1 -> 0.012108393 | AA11: =AA$10/Z$10-1 -> 0.011775752 | AB11: =AB$10/AA$10-1 -> 0.011498003 | ... BI11: =BI$10/BH$10-1 -> 0.0042389749
A12: Total LF participation rate (%) | T12: =T$10/T$8 -> 0.7120153 | U12: =U$10/U$8 -> 0.71113451 | V12: =V$10/V$8 -> 0.71040264 | W12: =W$10/W$8 -> 0.70969447 | X12: =X$10/X$8 -> 0.70905474 | Y12: =Y$10/Y$8 -> 0.70853161 | Z12: =Z$10/Z$8 -> 0.70796479 | AA12: =AA$10/AA$8 -> 0.70744873 | ... BI12: =BI$10/BI$8 -> 0.67307998
A13: Age in years ↓
A14: FEMALE POPULATION
A15: 0 | B15: 28910 | C15: 30230 | D15: 31360 | E15: 30830 | F15: 31510 | G15: 30670 | H15: 29880 | I15: 29370 | J15: 28390 | K15: 28520 | L15: 28790 | M15: 29450 | N15: 29000 | O15: 28900 | P15: 29060 | Q15: 29540 | R15: 29820 | S15: 27560 | T15: 27820 | U15: 28280 | V15: 28290 | W15: 28280 | X15: 28270 | Y15: 28250 | Z15: 28240 | AA15: 28250 | AB15: 28270 | AC15: 28320 | AD15: 28400 | AE15: 28520 | AF15: 28680 | AG15: 28860 | AH15: 29070 | AI15: 29290 | AJ15: 29510 | AK15: 29730 | AL15: 29920 | AM15: 30080 | AN15: 30210 | AO15: 30300 | AP15: 30360 | AQ15: 30390 | AR15: 30390 | AS15: 30370 | AT15: 30330 | AU15: 30270 | AV15: 30200 | AW15: 30140 | AX15: 30080 | AY15: 30020 | AZ15: 29980 | BA15: 29950 | BB15: 29930 | BC15: 29940 | BD15: 29970 | BE15: 30020 | BF15: 30080 | BG15: 30160 | BH15: 30250 | BI15: 30360
A16: 1 | B16: 27990 | C16: 28850 | D16: 30110 | E16: 31260 | F16: 30820 | G16: 31460 | H16: 30640 | I16: 29950 | J16: 29510 | K16: 28670 | L16: 28900 | M16: 29040 | N16: 29620 | O16: 29110 | P16: 29080 | Q16: 29150 | R16: 29470 | S16: 30040 | T16: 27710 | U16: 27790 | V16: 28280 | W16: 28300 | X16: 28310 | Y16: 28300 | Z16: 28290 | AA16: 28290 | AB16: 28290 | AC16: 28320 | AD16: 28370 | AE16: 28450 | AF16: 28570 | AG16: 28730 | AH16: 28920 | AI16: 29130 | AJ16: 29350 | AK16: 29580 | AL16: 29790 | AM16: 29980 | AN16: 30140 | AO16: 30280 | AP16: 30370 | AQ16: 30430 | AR16: 30460 | AS16: 30460 | AT16: 30440 | AU16: 30400 | AV16: 30350 | AW16: 30290 | AX16: 30220 | AY16: 30160 | AZ16: 30110 | BA16: 30070 | BB16: 30040 | BC16: 30030 | BD16: 30030 | BE16: 30060 | BF16: 30110 | BG16: 30180 | BH16: 30260 | BI16: 30350
A17: 2 | B17: 28180 | C17: 28100 | D17: 28870 | E17: 30220 | F17: 31340 | G17: 30770 | H17: 31310 | I17: 30580 | J17: 30150 | K17: 29890 | L17: 29060 | M17: 29470 | N17: 29470 | O17: 29980 | P17: 29540 | Q17: 29260 | R17: 29240 | S17: 29840 | T17: 30450 | U17: 27780 | V17: 27890 | W17: 28390 | X17: 28430 | Y17: 28440 | Z17: 28440 | AA17: 28440 | AB17: 28430 | AC17: 28440 | AD17: 28470 | AE17: 28520 | AF17: 28610 | AG17: 28730 | AH17: 28890 | AI17: 29070 | AJ17: 29280 | AK17: 29510 | AL17: 29740 | AM17: 29950 | AN17: 30150 | AO17: 30310 | AP17: 30440 | AQ17: 30540 | AR17: 30600 | AS17: 30640 | AT17: 30640 | AU17: 30620 | AV17: 30580 | AW17: 30530 | AX17: 30470 | AY17: 30410 | AZ17: 30350 | BA17: 30300 | BB17: 30250 | BC17: 30230 | BD17: 30220 | BE17: 30230 | BF17: 30260 | BG17: 30310 | BH17: 30380 | BI17: 30460
A18: 3 | B18: 27310 | C18: 28260 | D18: 28090 | E18: 28910 | F18: 30280 | G18: 31290 | H18: 30670 | I18: 31320 | J18: 30730 | K18: 30430 | L18: 30460 | M18: 29610 | N18: 30030 | O18: 29920 | P18: 30490 | Q18: 29680 | R18: 29450 | S18: 29740 | T18: 30340 | U18: 30570 | V18: 27930 | W18: 28060 | X18: 28580 | Y18: 28620 | Z18: 28640 | AA18: 28650 | AB18: 28640 | AC18: 28640 | AD18: 28650 | AE18: 28680 | AF18: 28730 | AG18: 28820 | AH18: 28950 | AI18: 29110 | AJ18: 29300 | AK18: 29510 | AL18: 29730 | AM18: 29960 | AN18: 30180 | AO18: 30380 | AP18: 30540 | AQ18: 30680 | AR18: 30780 | AS18: 30840 | AT18: 30880 | AU18: 30880 | AV18: 30860 | AW18: 30830 | AX18: 30780 | AY18: 30720 | AZ18: 30660 | BA18: 30600 | BB18: 30550 | BC18: 30510 | BD18: 30480 | BE18: 30480 | BF18: 30490 | BG18: 30520 | BH18: 30570 | BI18: 30640
A19: 4 | B19: 27400 | C19: 27460 | D19: 28310 | E19: 28190 | F19: 29030 | G19: 30250 | H19: 31140 | I19: 30550 | J19: 31460 | K19: 31040 | L19: 30880 | M19: 30980 | N19: 30100 | O19: 30500 | P19: 30420 | Q19: 30610 | R19: 29800 | S19: 30210 | T19: 30430 | U19: 30500 | V19: 30770 | W19: 28150 | X19: 28290 | Y19: 28820 | Z19: 28870 | AA19: 28900 | AB19: 28910 | AC19: 28900 | AD19: 28900 | AE19: 28910 | AF19: 28940 | AG19: 29000 | AH19: 29090 | AI19: 29220 | AJ19: 29380 | AK19: 29570 | AL19: 29780 | AM19: 30010 | AN19: 30240 | AO19: 30460 | AP19: 30660 | AQ19: 30830 | AR19: 30970 | AS19: 31070 | AT19: 31130 | AU19: 31170 | AV19: 31180 | AW19: 31160 | AX19: 31130 | AY19: 31080 | AZ19: 31020 | BA19: 30960 | BB19: 30910 | BC19: 30860 | BD19: 30820 | BE19: 30800 | BF19: 30790 | BG19: 30810 | BH19: 30840 | BI19: 30890
A20: 5 | B20: 28370 | C20: 27650 | D20: 27610 | E20: 28410 | F20: 28320 | G20: 29050 | H20: 30120 | I20: 31090 | J20: 30700 | K20: 31720 | L20: 31400 | M20: 31390 | N20: 31470 | O20: 30590 | P20: 30990 | Q20: 30490 | R20: 30660 | S20: 30490 | T20: 31010 | U20: 30610 | V20: 30720 | W20: 31000 | X20: 28400 | Y20: 28560 | Z20: 29090 | AA20: 29150 | AB20: 29180 | AC20: 29180 | AD20: 29180 | AE20: 29180 | AF20: 29200 | AG20: 29230 | AH20: 29290 | AI20: 29380 | AJ20: 29510 | AK20: 29670 | AL20: 29870 | AM20: 30080 | AN20: 30310 | AO20: 30550 | AP20: 30770 | AQ20: 30970 | AR20: 31140 | AS20: 31280 | AT20: 31380 | AU20: 31450 | AV20: 31490 | AW20: 31490 | AX20: 31480 | AY20: 31450 | AZ20: 31400 | BA20: 31350 | BB20: 31290 | BC20: 31240 | BD20: 31190 | BE20: 31150 | BF20: 31130 | BG20: 31130 | BH20: 31140 | BI20: 31180
A21: 6 | B21: 28910 | C21: 28620 | D21: 27860 | E21: 27770 | F21: 28550 | G21: 28290 | H21: 28900 | I21: 30050 | J21: 31180 | K21: 30870 | L21: 31990 | M21: 31750 | N21: 31830 | O21: 31890 | P21: 31080 | Q21: 31090 | R21: 30550 | S21: 31420 | T21: 31240 | U21: 31200 | V21: 30840 | W21: 30970 | X21: 31270 | Y21: 28680 | Z21: 28840 | AA21: 29380 | AB21: 29440 | AC21: 29470 | AD21: 29480 | AE21: 29480 | AF21: 29490 | AG21: 29500 | AH21: 29530 | AI21: 29600 | AJ21: 29690 | AK21: 29820 | AL21: 29990 | AM21: 30180 | AN21: 30400 | AO21: 30630 | AP21: 30870 | AQ21: 31090 | AR21: 31290 | AS21: 31470 | AT21: 31610 | AU21: 31710 | AV21: 31780 | AW21: 31820 | AX21: 31830 | AY21: 31820 | AZ21: 31790 | BA21: 31750 | BB21: 31690 | BC21: 31640 | BD21: 31590 | BE21: 31540 | BF21: 31510 | BG21: 31490 | BH21: 31490 | BI21: 31510
A22: 7 | B22: 27980 | C22: 29160 | D22: 28760 | E22: 27990 | F22: 27850 | G22: 28600 | H22: 28200 | I22: 28790 | J22: 30150 | K22: 31310 | L22: 31080 | M22: 32270 | N22: 32050 | O22: 32190 | P22: 32370 | Q22: 31220 | R22: 31170 | S22: 31190 | T22: 32120 | U22: 31440 | V22: 31440 | W22: 31100 | X22: 31250 | Y22: 31560 | Z22: 28980 | AA22: 29140 | AB22: 29690 | AC22: 29750 | AD22: 29780 | AE22: 29790 | AF22: 29790 | AG22: 29800 | AH22: 29820 | AI22: 29850 | AJ22: 29920 | AK22: 30010 | AL22: 30150 | AM22: 30310 | AN22: 30510 | AO22: 30730 | AP22: 30970 | AQ22: 31200 | AR22: 31430 | AS22: 31630 | AT22: 31810 | AU22: 31950 | AV22: 32060 | AW22: 32130 | AX22: 32170 | AY22: 32180 | AZ22: 32170 | BA22: 32150 | BB22: 32100 | BC22: 32050 | BD22: 32000 | BE22: 31950 | BF22: 31910 | BG22: 31880 | BH22: 31860 | BI22: 31860
A23: 8 | B23: 28620 | C23: 28230 | D23: 29340 | E23: 28950 | F23: 28120 | G23: 27910 | H23: 28490 | I23: 28140 | J23: 28910 | K23: 30320 | L23: 31560 | M23: 31380 | N23: 32500 | O23: 32460 | P23: 32650 | Q23: 32520 | R23: 31310 | S23: 31870 | T23: 31910 | U23: 32320 | V23: 31680 | W23: 31700 | X23: 31380 | Y23: 31540 | Z23: 31860 | AA23: 29280 | AB23: 29450 | AC23: 29990 | AD23: 30050 | AE23: 30090 | AF23: 30100 | AG23: 30110 | AH23: 30110 | AI23: 30130 | AJ23: 30170 | AK23: 30240 | AL23: 30330 | AM23: 30470 | AN23: 30640 | AO23: 30840 | AP23: 31060 | AQ23: 31300 | AR23: 31540 | AS23: 31770 | AT23: 31970 | AU23: 32150 | AV23: 32290 | AW23: 32400 | AX23: 32480 | AY23: 32520 | AZ23: 32540 | BA23: 32530 | BB23: 32500 | BC23: 32460 | BD23: 32410 | BE23: 32360 | BF23: 32310 | BG23: 32270 | BH23: 32240 | BI23: 32230
A24: 9 | B24: 28770 | C24: 28910 | D24: 28390 | E24: 29550 | F24: 29150 | G24: 28210 | H24: 27850 | I24: 28430 | J24: 28290 | K24: 29120 | L24: 30590 | M24: 31900 | N24: 31640 | O24: 32820 | P24: 32920 | Q24: 32770 | R24: 32570 | S24: 32040 | T24: 32620 | U24: 32110 | V24: 32570 | W24: 31940 | X24: 31980 | Y24: 31660 | Z24: 31830 | AA24: 32160 | AB24: 29580 | AC24: 29750 | AD24: 30300 | AE24: 30360 | AF24: 30400 | AG24: 30410 | AH24: 30420 | AI24: 30430 | AJ24: 30450 | AK24: 30490 | AL24: 30560 | AM24: 30660 | AN24: 30800 | AO24: 30970 | AP24: 31170 | AQ24: 31390 | AR24: 31630 | AS24: 31870 | AT24: 32100 | AU24: 32310 | AV24: 32490 | AW24: 32640 | AX24: 32750 | AY24: 32820 | AZ24: 32870 | BA24: 32890 | BB24: 32880 | BC24: 32860 | BD24: 32820 | BE24: 32770 | BF24: 32720 | BG24: 32680 | BH24: 32640 | BI24: 32610
A25: 10 | B25: 29250 | C25: 28990 | D25: 29090 | E25: 28550 | F25: 29770 | G25: 29310 | H25: 28210 | I25: 27900 | J25: 28540 | K25: 28530 | L25: 29430 | M25: 30950 | N25: 32130 | O25: 31950 | P25: 33220 | Q25: 33040 | R25: 32810 | S25: 33270 | T25: 32820 | U25: 32830 | V25: 32370 | W25: 32840 | X25: 32230 | Y25: 32280 | Z25: 31970 | AA25: 32140 | AB25: 32470 | AC25: 29900 | AD25: 30070 | AE25: 30620 | AF25: 30680 | AG25: 30720 | AH25: 30740 | AI25: 30750 | AJ25: 30760 | AK25: 30780 | AL25: 30820 | AM25: 30890 | AN25: 31000 | AO25: 31130 | AP25: 31310 | AQ25: 31510 | AR25: 31740 | AS25: 31980 | AT25: 32220 | AU25: 32450 | AV25: 32660 | AW25: 32840 | AX25: 32990 | AY25: 33100 | AZ25: 33180 | BA25: 33230 | BB25: 33250 | BC25: 33250 | BD25: 33220 | BE25: 33190 | BF25: 33140 | BG25: 33100 | BH25: 33050 | BI25: 33010
A26: 11 | B26: 29970 | C26: 29430 | D26: 29180 | E26: 29270 | F26: 28700 | G26: 29880 | H26: 29380 | I26: 28280 | J26: 28040 | K26: 28740 | L26: 28830 | M26: 29750 | N26: 31280 | O26: 32550 | P26: 32410 | Q26: 33350 | R26: 33060 | S26: 33500 | T26: 33950 | U26: 33030 | V26: 33080 | W26: 32640 | X26: 33120 | Y26: 32530 | Z26: 32580 | AA26: 32280 | AB26: 32460 | AC26: 32780 | AD26: 30210 | AE26: 30390 | AF26: 30940 | AG26: 31000 | AH26: 31040 | AI26: 31060 | AJ26: 31080 | AK26: 31090 | AL26: 31110 | AM26: 31160 | AN26: 31230 | AO26: 31330 | AP26: 31470 | AQ26: 31650 | AR26: 31860 | AS26: 32080 | AT26: 32330 | AU26: 32570 | AV26: 32800 | AW26: 33020 | AX26: 33200 | AY26: 33350 | AZ26: 33460 | BA26: 33540 | BB26: 33590 | BC26: 33610 | BD26: 33610 | BE26: 33590 | BF26: 33560 | BG26: 33510 | BH26: 33470 | BI26: 33430
... A109: 94 | B109: 1310 | C109: 1370 | D109: 1330 | E109: 1450 | F109: 1480 | G109: 1480 | H109: 1480 | I109: 1400 | J109: 1740 | K109: 1830 | L109: 1920 | M109: 1940 | N109: 2000 | O109: 2070 | P109: 2050 | Q109: 2070 | R109: 1990 | S109: 2120 | T109: 2190 | U109: 2110 | V109: 2080 | W109: 2130 | X109: 2140 | Y109: 2170 | Z109: 2320 | AA109: 2420 | AB109: 2580 | AC109: 2750 | AD109: 3020 | AE109: 3300 | AF109: 3410 | AG109: 3120 | AH109: 3480 | AI109: 3730 | AJ109: 4010 | AK109: 4830 | AL109: 4900 | AM109: 4890 | AN109: 5170 | AO109: 5170 | AP109: 5420 | AQ109: 5610 | AR109: 5910 | AS109: 6150 | AT109: 6450 | AU109: 6700 | AV109: 6990 | AW109: 7320 | AX109: 7530 | AY109: 7970 | AZ109: 8340 | BA109: 8540 | BB109: 8490 | BC109: 8390 | BD109: 8410 | BE109: 8740 | BF109: 8980 | BG109: 9320 | BH109: 9460 | BI109: 9990
A110: 95 & over | B110: 2960 | C110: 3090 | D110: 3260 | E110: 3310 | F110: 3590 | G110: 3710 | H110: 3780 | I110: 3810 | J110: 3860 | K110: 4120 | L110: 4390 | M110: 4710 | N110: 4980 | O110: 5180 | P110: 5330 | Q110: 5510 | R110: 5380 | S110: 5140 | T110: 5280 | U110: 5600 | V110: 5800 | W110: 5920 | X110: 6040 | Y110: 6140 | Z110: 6230 | AA110: 6430 | AB110: 6660 | AC110: 6950 | AD110: 7320 | AE110: 7810 | AF110: 8410 | AG110: 8960 | AH110: 9140 | AI110: 9560 | AJ110: 10080 | AK110: 10690 | AL110: 11830 | AM110: 12760 | AN110: 13460 | AO110: 14210 | AP110: 14780 | AQ110: 15420 | AR110: 16050 | AS110: 16780 | AT110: 17550 | AU110: 18370 | AV110: 19220 | AW110: 20110 | AX110: 21070 | AY110: 21990 | AZ110: 23060 | BA110: 24200 | BB110: 25240 | BC110: 26030 | BD110: 26540 | BE110: 26970 | BF110: 27570 | BG110: 28250 | BH110: 29070 | BI110: 29840
A111: Female total | B111: =SUM(B$15:B$110) -> 2136250 | C111: =SUM(C$15:C$110) -> 2157380 | D111: =SUM(D$15:D$110) -> 2176330 | E111: =SUM(E$15:E$110) -> 2197940 | F111: =SUM(F$15:F$110) -> 2222910 | G111: =SUM(G$15:G$110) -> 2240420 | H111: =SUM(H$15:H$110) -> 2252990 | I111: =SUM(I$15:I$110) -> 2269940 | ... AI111: =SUM(AI$15:AI$110) -> 3047710
A114: MALE POPULATION
A115: =$A$15 -> 0 | B115: 30150 | C115: 31900 | D115: 33050 | E115: 33060 | F115: 33020 | G115: 32130 | H115: 31320 | I115: 30890 | J115: 30140 | K115: 30350 | L115: 30610 | M115: 30690 | N115: 30530 | O115: 30740 | P115: 30270 | Q115: 31310 | R115: 30520 | S115: 29280 | T115: 29270 | U115: 29840 | V115: 29850 | W115: 29850 | X115: 29830 | Y115: 29820 | Z115: 29810 | AA115: 29810 | AB115: 29830 | AC115: 29890 | AD115: 29980 | AE115: 30100 | AF115: 30270 | AG115: 30460 | AH115: 30680 | AI115: 30910 | AJ115: 31150 | AK115: 31380 | AL115: 31580 | AM115: 31750 | AN115: 31880 | AO115: 31980 | AP115: 32050 | AQ115: 32080 | AR115: 32080 | AS115: 32050 | AT115: 32010 | AU115: 31950 | AV115: 31880 | AW115: 31810 | AX115: 31750 | AY115: 31690 | AZ115: 31640 | BA115: 31610 | BB115: 31600 | BC115: 31610 | BD115: 31640 | BE115: 31690 | BF115: 31750 | BG115: 31840 | BH115: 31940 | BI115: 32050
A116: =$A$16 -> 1 | B116: 29380 | C116: 30170 | D116: 31780 | E116: 32980 | F116: 33130 | G116: 33060 | H116: 32050 | I116: 31410 | J116: 31010 | K116: 30350 | L116: 30650 | M116: 30930 | N116: 30900 | O116: 30640 | P116: 31000 | Q116: 30370 | R116: 31240 | S116: 30750 | T116: 29490 | U116: 29240 | V116: 29840 | W116: 29860 | X116: 29870 | Y116: 29860 | Z116: 29850 | AA116: 29840 | AB116: 29850 | AC116: 29880 | AD116: 29930 | AE116: 30020 | AF116: 30150 | AG116: 30310 | AH116: 30510 | AI116: 30730 | AJ116: 30970 | AK116: 31200 | AL116: 31430 | AM116: 31630 | AN116: 31810 | AO116: 31940 | AP116: 32040 | AQ116: 32110 | AR116: 32140 | AS116: 32140 | AT116: 32120 | AU116: 32080 | AV116: 32020 | AW116: 31960 | AX116: 31890 | AY116: 31830 | AZ116: 31770 | BA116: 31720 | BB116: 31690 | BC116: 31680 | BD116: 31690 | BE116: 31720 | BF116: 31770 | BG116: 31840 | BH116: 31930 | BI116: 32030
A117: =$A$17 -> 2 | B117: 29510 | C117: 29490 | D117: 30170 | E117: 31800 | F117: 33070 | G117: 33070 | H117: 32930 | I117: 31970 | J117: 31670 | K117: 31400 | L117: 30920 | M117: 31290 | N117: 31420 | O117: 31310 | P117: 31070 | Q117: 31160 | R117: 30440 | S117: 31660 | T117: 31270 | U117: 29590 | V117: 29370 | W117: 29980 | X117: 30020 | Y117: 30030 | Z117: 30030 | AA117: 30030 | AB117: 30020 | AC117: 30030 | AD117: 30060 | AE117: 30110 | AF117: 30200 | AG117: 30340 | AH117: 30500 | AI117: 30700 | AJ117: 30920 | AK117: 31160 | AL117: 31400 | AM117: 31630 | AN117: 31830 | AO117: 32010 | AP117: 32150 | AQ117: 32250 | AR117: 32310 | AS117: 32350 | AT117: 32350 | AU117: 32330 | AV117: 32290 | AW117: 32240 | AX117: 32170 | AY117: 32110 | AZ117: 32040 | BA117: 31990 | BB117: 31940 | BC117: 31920 | BD117: 31910 | BE117: 31920 | BF117: 31950 | BG117: 32000 | BH117: 32070 | BI117: 32160
A118: =$A$18 -> 3 | B118: 28800 | C118: 29680 | D118: 29550 | E118: 30280 | F118: 31860 | G118: 32950 | H118: 32970 | I118: 32960 | J118: 32220 | K118: 32020 | L118: 31970 | M118: 31570 | N118: 31850 | O118: 31860 | P118: 31920 | Q118: 31240 | R118: 31390 | S118: 31090 | T118: 32200 | U118: 31410 | V118: 29770 | W118: 29560 | X118: 30190 | Y118: 30240 | Z118: 30260 | AA118: 30260 | AB118: 30260 | AC118: 30250 | AD118: 30260 | AE118: 30290 | AF118: 30350 | AG118: 30450 | AH118: 30580 | AI118: 30750 | AJ118: 30950 | AK118: 31170 | AL118: 31410 | AM118: 31650 | AN118: 31880 | AO118: 32090 | AP118: 32260 | AQ118: 32400 | AR118: 32510 | AS118: 32580 | AT118: 32610 | AU118: 32620 | AV118: 32600 | AW118: 32560 | AX118: 32510 | AY118: 32440 | AZ118: 32380 | BA118: 32320 | BB118: 32270 | BC118: 32230 | BD118: 32200 | BE118: 32190 | BF118: 32200 | BG118: 32240 | BH118: 32290 | BI118: 32360
A119: =$A$19 -> 4 | B119: 28370 | C119: 28970 | D119: 29740 | E119: 29670 | F119: 30290 | G119: 31810 | H119: 32820 | I119: 32930 | J119: 33110 | K119: 32540 | L119: 32460 | M119: 32480 | N119: 32120 | O119: 32360 | P119: 32360 | Q119: 32020 | R119: 31360 | S119: 32140 | T119: 31840 | U119: 32380 | V119: 31630 | W119: 30010 | X119: 29820 | Y119: 30460 | Z119: 30510 | AA119: 30540 | AB119: 30550 | AC119: 30540 | AD119: 30540 | AE119: 30550 | AF119: 30580 | AG119: 30640 | AH119: 30740 | AI119: 30870 | AJ119: 31050 | AK119: 31250 | AL119: 31470 | AM119: 31710 | AN119: 31960 | AO119: 32190 | AP119: 32400 | AQ119: 32570 | AR119: 32720 | AS119: 32820 | AT119: 32890 | AU119: 32930 | AV119: 32940 | AW119: 32920 | AX119: 32890 | AY119: 32830 | AZ119: 32770 | BA119: 32710 | BB119: 32650 | BC119: 32600 | BD119: 32560 | BE119: 32540 | BF119: 32530 | BG119: 32550 | BH119: 32580 | BI119: 32640
A120: =$A$20 -> 5 | B120: 29670 | C120: 28590 | D120: 29100 | E120: 29870 | F120: 29760 | G120: 30240 | H120: 31670 | I120: 32730 | J120: 33050 | K120: 33360 | L120: 32990 | M120: 32950 | N120: 32960 | O120: 32680 | P120: 32910 | Q120: 32500 | R120: 32050 | S120: 32120 | T120: 32920 | U120: 32030 | V120: 32610 | W120: 31880 | X120: 30280 | Y120: 30100 | Z120: 30750 | AA120: 30800 | AB120: 30830 | AC120: 30840 | AD120: 30840 | AE120: 30840 | AF120: 30850 | AG120: 30890 | AH120: 30950 | AI120: 31050 | AJ120: 31180 | AK120: 31360 | AL120: 31560 | AM120: 31790 | AN120: 32030 | AO120: 32280 | AP120: 32510 | AQ120: 32720 | AR120: 32900 | AS120: 33050 | AT120: 33150 | AU120: 33230 | AV120: 33270 | AW120: 33280 | AX120: 33260 | AY120: 33230 | AZ120: 33180 | BA120: 33120 | BB120: 33060 | BC120: 33000 | BD120: 32950 | BE120: 32920 | BF120: 32890 | BG120: 32890 | BH120: 32910 | BI120: 32940
A121: =$A$21 -> 6 | B121: 30280 | C121: 29980 | D121: 28760 | E121: 29210 | F121: 29950 | G121: 29730 | H121: 30080 | I121: 31520 | J121: 32870 | K121: 33280 | L121: 33630 | M121: 33450 | N121: 33340 | O121: 33330 | P121: 33180 | Q121: 32980 | R121: 32530 | S121: 32760 | T121: 32910 | U121: 33130 | V121: 32280 | W121: 32880 | X121: 32170 | Y121: 30580 | Z121: 30410 | AA121: 31060 | AB121: 31120 | AC121: 31150 | AD121: 31160 | AE121: 31160 | AF121: 31160 | AG121: 31180 | AH121: 31210 | AI121: 31280 | AJ121: 31380 | AK121: 31520 | AL121: 31690 | AM121: 31900 | AN121: 32130 | AO121: 32370 | AP121: 32620 | AQ121: 32860 | AR121: 33070 | AS121: 33250 | AT121: 33400 | AU121: 33510 | AV121: 33580 | AW121: 33620 | AX121: 33640 | AY121: 33620 | AZ121: 33590 | BA121: 33540 | BB121: 33490 | BC121: 33430 | BD121: 33380 | BE121: 33330 | BF121: 33290 | BG121: 33270 | BH121: 33270 | BI121: 33290
A122: =$A$22 -> 7 | B122: 29500 | C122: 30570 | D122: 30180 | E122: 28890 | F122: 29340 | G122: 29910 | H122: 29610 | I122: 29960 | J122: 31670 | K122: 33060 | L122: 33510 | M122: 33970 | N122: 33780 | O122: 33750 | P122: 33740 | Q122: 33350 | R122: 33010 | S122: 33250 | T122: 33470 | U122: 33130 | V122: 33390 | W122: 32560 | X122: 33180 | Y122: 32480 | Z122: 30900 | AA122: 30730 | AB122: 31390 | AC122: 31450 | AD122: 31480 | AE122: 31490 | AF122: 31500 | AG122: 31500 | AH122: 31520 | AI122: 31560 | AJ122: 31620 | AK122: 31720 | AL122: 31870 | AM122: 32040 | AN122: 32250 | AO122: 32480 | AP122: 32730 | AQ122: 32980 | AR122: 33220 | AS122: 33430 | AT122: 33620 | AU122: 33770 | AV122: 33880 | AW122: 33960 | AX122: 34000 | AY122: 34010 | AZ122: 34000 | BA122: 33970 | BB122: 33930 | BC122: 33870 | BD122: 33820 | BE122: 33770 | BF122: 33720 | BG122: 33690 | BH122: 33670 | BI122: 33670
A123: =$A$23 -> 8 | B123: 29960 | C123: 29810 | D123: 30860 | E123: 30370 | F123: 29120 | G123: 29410 | H123: 29840 | I123: 29550 | J123: 30110 | K123: 31880 | L123: 33360 | M123: 33860 | N123: 34200 | O123: 34170 | P123: 34210 | Q123: 33870 | R123: 33350 | S123: 33740 | T123: 34050 | U123: 33700 | V123: 33400 | W123: 33680 | X123: 32870 | Y123: 33500 | Z123: 32810 | AA123: 31230 | AB123: 31060 | AC123: 31720 | AD123: 31790 | AE123: 31820 | AF123: 31840 | AG123: 31840 | AH123: 31850 | AI123: 31870 | AJ123: 31910 | AK123: 31980 | AL123: 32080 | AM123: 32220 | AN123: 32400 | AO123: 32610 | AP123: 32850 | AQ123: 33100 | AR123: 33350 | AS123: 33590 | AT123: 33810 | AU123: 33990 | AV123: 34140 | AW123: 34260 | AX123: 34340 | AY123: 34380 | AZ123: 34400 | BA123: 34390 | BB123: 34360 | BC123: 34320 | BD123: 34270 | BE123: 34220 | BF123: 34160 | BG123: 34120 | BH123: 34090 | BI123: 34080
A124: =$A$24 -> 9 | B124: 29820 | C124: 30270 | D124: 30090 | E124: 31080 | F124: 30610 | G124: 29220 | H124: 29330 | I124: 29810 | J124: 29700 | K124: 30340 | L124: 32240 | M124: 33630 | N124: 34150 | O124: 34610 | P124: 34590 | Q124: 34310 | R124: 33920 | S124: 34030 | T124: 34600 | U124: 34290 | V124: 33970 | W124: 33690 | X124: 33990 | Y124: 33190 | Z124: 33830 | AA124: 33140 | AB124: 31570 | AC124: 31400 | AD124: 32060 | AE124: 32130 | AF124: 32170 | AG124: 32180 | AH124: 32190 | AI124: 32200 | AJ124: 32220 | AK124: 32260 | AL124: 32340 | AM124: 32440 | AN124: 32590 | AO124: 32770 | AP124: 32980 | AQ124: 33220 | AR124: 33470 | AS124: 33720 | AT124: 33970 | AU124: 34180 | AV124: 34370 | AW124: 34530 | AX124: 34640 | AY124: 34720 | AZ124: 34770 | BA124: 34790 | BB124: 34780 | BC124: 34760 | BD124: 34720 | BE124: 34670 | BF124: 34620 | BG124: 34570 | BH124: 34530 | BI124: 34500
A125: =$A$25 -> 10 | B125: 31100 | C125: 30190 | D125: 30480 | E125: 30320 | F125: 31360 | G125: 30720 | H125: 29220 | I125: 29330 | J125: 29960 | K125: 29980 | L125: 30710 | M125: 32680 | N125: 33930 | O125: 34530 | P125: 35100 | Q125: 34700 | R125: 34360 | S125: 34700 | T125: 34830 | U125: 34830 | V125: 34560 | W125: 34270 | X125: 34000 | Y125: 34310 | Z125: 33530 | AA125: 34170 | AB125: 33480 | AC125: 31910 | AD125: 31750 | AE125: 32410 | AF125: 32480 | AG125: 32520 | AH125: 32540 | AI125: 32550 | AJ125: 32560 | AK125: 32580 | AL125: 32630 | AM125: 32700 | AN125: 32810 | AO125: 32960 | AP125: 33140 | AQ125: 33350 | AR125: 33590 | AS125: 33850 | AT125: 34100 | AU125: 34350 | AV125: 34570 | AW125: 34760 | AX125: 34910 | AY125: 35030 | AZ125: 35120 | BA125: 35170 | BB125: 35190 | BC125: 35180 | BD125: 35160 | BE125: 35120 | BF125: 35070 | BG125: 35020 | BH125: 34980 | BI125: 34940
A126: =$A$26 -> 11 | B126: 31570 | C126: 31310 | D126: 30420 | E126: 30690 | F126: 30620 | G126: 31500 | H126: 30790 | I126: 29240 | J126: 29600 | K126: 30160 | L126: 30300 | M126: 31150 | N126: 33010 | O126: 34340 | P126: 34870 | Q126: 35210 | R126: 34760 | S126: 35040 | T126: 35460 | U126: 35070 | V126: 35110 | W126: 34860 | X126: 34590 | Y126: 34330 | Z126: 34650 | AA126: 33870 | AB126: 34520 | AC126: 33830 | AD126: 32260 | AE126: 32100 | AF126: 32770 | AG126: 32840 | AH126: 32880 | AI126: 32900 | AJ126: 32910 | AK126: 32920 | AL126: 32950 | AM126: 33000 | AN126: 33070 | AO126: 33180 | AP126: 33330 | AQ126: 33520 | AR126: 33730 | AS126: 33970 | AT126: 34230 | AU126: 34490 | AV126: 34730 | AW126: 34960 | AX126: 35150 | AY126: 35310 | AZ126: 35430 | BA126: 35510 | BB126: 35570 | BC126: 35590 | BD126: 35590 | BE126: 35560 | BF126: 35530 | BG126: 35480 | BH126: 35430 | BI126: 35390
A127: =$A$27 -> 12 | B127: 31640 | C127: 31640 | D127: 31450 | E127: 30620 | F127: 30980 | G127: 30730 | H127: 31640 | I127: 30870 | J127: 29490 | K127: 29980 | L127: 30450 | M127: 30710 | N127: 31540 | O127: 33560 | P127: 34840 | Q127: 35020 | R127: 35240 | S127: 35440 | T127: 35780 | U127: 35700 | V127: 35350 | W127: 35420 | X127: 35180 | Y127: 34920 | Z127: 34670 | AA127: 35000 | AB127: 34210 | AC127: 34860 | AD127: 34180 | AE127: 32610 | AF127: 32460 | AG127: 33120 | AH127: 33190 | AI127: 33240 | AJ127: 33260 | AK127: 33270 | AL127: 33290 | AM127: 33320 | AN127: 33360 | AO127: 33440 | AP127: 33550 | AQ127: 33700 | AR127: 33890 | AS127: 34110 | AT127: 34350 | AU127: 34610 | AV127: 34870 | AW127: 35120 | AX127: 35340 | AY127: 35540 | AZ127: 35700 | BA127: 35820 | BB127: 35910 | BC127: 35960 | BD127: 35990 | BE127: 35990 | BF127: 35970 | BG127: 35930 | BH127: 35890 | BI127: 35840
A128: =$A$28 -> 13 | B128: 32400 | C128: 31620 | D128: 31620 | E128: 31610 | F128: 30840 | G128: 31190 | H128: 30830 | I128: 31780 | J128: 31050 | K128: 29880 | L128: 30500 | M128: 30750 | N128: 31040 | O128: 32050 | P128: 34110 | Q128: 35090 | R128: 35090 | S128: 35950 | T128: 36220 | U128: 36050 | V128: 36010 | W128: 35680 | X128: 35760 | Y128: 35540 | Z128: 35280 | AA128: 35040 | AB128: 35360 | AC128: 34580 | AD128: 35230 | AE128: 34550 | AF128: 32990 | AG128: 32830 | AH128: 33500 | AI128: 33570 | AJ128: 33620 | AK128: 33640 | AL128: 33660 | AM128: 33670 | AN128: 33700 | AO128: 33760 | AP128: 33830 | AQ128: 33950 | AR128: 34100 | AS128: 34290 | AT128: 34510 | AU128: 34750 | AV128: 35010 | AW128: 35280 | AX128: 35530 | AY128: 35750 | AZ128: 35950 | BA128: 36110 | BB128: 36240 | BC128: 36330 | BD128: 36380 | BE128: 36410 | BF128: 36410 | BG128: 36390 | BH128: 36360 | BI128: 36320
A129: =$A$29 -> 14 | B129: 32800 | C129: 32260 | D129: 31550 | E129: 31640 | F129: 31810 | G129: 31060 | H129: 31400 | I129: 30980 | J129: 31850 | K129: 31360 | L129: 30430 | M129: 31080 | N129: 31160 | O129: 31570 | P129: 32560 | Q129: 34280 | R129: 35220 | S129: 35800 | T129: 36680 | U129: 36540 | V129: 36400 | W129: 36380 | X129: 36060 | Y129: 36150 | Z129: 35940 | AA129: 35680 | AB129: 35440 | AC129: 35770 | AD129: 34990 | AE129: 35640 | AF129: 34960 | AG129: 33400 | AH129: 33250 | AI129: 33920 | AJ129: 33990 | AK129: 34040 | AL129: 34070 | AM129: 34080 | AN129: 34100 | AO129: 34130 | AP129: 34190 | AQ129: 34270 | AR129: 34380 | AS129: 34540 | AT129: 34730 | AU129: 34950 | AV129: 35200 | AW129: 35460 | AX129: 35720 | AY129: 35980 | AZ129: 36200 | BA129: 36400 | BB129: 36570 | BC129: 36690 | BD129: 36780 | BE129: 36840 | BF129: 36870 | BG129: 36870 | BH129: 36860 | BI129: 36830
A130: =$A$30 -> 15 | B130: 33590 | C130: 32590 | D130: 32100 | E130: 31480 | F130: 31790 | G130: 31950 | H130: 31310 | I130: 31620 | J130: 31200 | K130: 32200 | L130: 31970 | M130: 31110 | N130: 31730 | O130: 31760 | P130: 32140 | Q130: 32720 | R130: 34490 | S130: 36160 | T130: 36610 | U130: 37050 | V130: 36940 | W130: 36820 | X130: 36810 | Y130: 36510 | Z130: 36600 | AA130: 36390 | AB130: 36140 | AC130: 35900 | AD130: 36230 | AE130: 35450 | AF130: 36110 | AG130: 35430 | AH130: 33870 | AI130: 33720 | AJ130: 34390 | AK130: 34470 | AL130: 34520 | AM130: 34540 | AN130: 34560 | AO130: 34580 | AP130: 34620 | AQ130: 34670 | AR130: 34750 | AS130: 34870 | AT130: 35030 | AU130: 35220 | AV130: 35450 | AW130: 35690 | AX130: 35960 | AY130: 36220 | AZ130: 36480 | BA130: 36710 | BB130: 36910 | BC130: 37070 | BD130: 37200 | BE130: 37290 | BF130: 37350 | BG130: 37380 | BH130: 37390 | BI130: 37380
A131: =$A$31 -> 16 | B131: 32610 | C131: 33310 | D131: 32300 | E131: 32050 | F131: 31680 | G131: 31980 | H131: 32180 | I131: 31650 | J131: 31920 | K131: 31620 | L131: 32770 | M131: 32690 | N131: 31800 | O131: 32190 | P131: 32350 | Q131: 32320 | R131: 32920 | S131: 35350 | T131: 37080 | U131: 37080 | V131: 37560 | W131: 37460 | X131: 37360 | Y131: 37370 | Z131: 37070 | AA131: 37170 | AB131: 36960 | AC131: 36710 | AD131: 36480 | AE131: 36810 | AF131: 36030 | AG131: 36690 | AH131: 36010 | AI131: 34450 | AJ131: 34310 | AK131: 34980 | AL131: 35060 | AM131: 35110 | AN131: 35140 | AO131: 35160 | AP131: 35180 | AQ131: 35220 | AR131: 35280 | AS131: 35360 | AT131: 35480 | AU131: 35640 | AV131: 35840 | AW131: 36060 | AX131: 36310 | AY131: 36580 | AZ131: 36850 | BA131: 37100 | BB131: 37330 | BC131: 37540 | BD131: 37700 | BE131: 37830 | BF131: 37930 | BG131: 37990 | BH131: 38020 | BI131: 38030
A132: =$A$32 -> 17 | B132: 31820 | C132: 32260 | D132: 33160 | E132: 32180 | F132: 32210 | G132: 31800 | H132: 32120 | I132: 32430 | J132: 31970 | K132: 32340 | L132: 32150 | M132: 33240 | N132: 33240 | O132: 32050 | P132: 32410 | Q132: 32410 | R132: 32480 | S132: 33660 | T132: 36040 | U132: 37630 | V132: 37680 | W132: 38190 | X132: 38120 | Y132: 38030 | Z132: 38050 | AA132: 37760 | AB132: 37860 | AC132: 37660 | AD132: 37410 | AE132: 37180 | AF132: 37510 | AG132: 36740 | AH132: 37400 | AI132: 36730 | AJ132: 35170 | AK132: 35030 | AL132: 35700 | AM132: 35780 | AN132: 35840 | AO132: 35870 | AP132: 35900 | AQ132: 35920 | AR132: 35960 | AS132: 36020 | AT132: 36110 | AU132: 36230 | AV132: 36390 | AW132: 36590 | AX132: 36820 | AY132: 37070 | AZ132: 37340 | BA132: 37610 | BB132: 37870 | BC132: 38110 | BD132: 38310 | BE132: 38480 | BF132: 38620 | BG132: 38710 | BH132: 38780 | BI132: 38810
A133: =$A$33 -> 18 | B133: 31140 | C133: 31370 | D133: 31770 | E133: 32780 | F133: 32130 | G133: 32140 | H133: 31760 | I133: 32160 | J133: 32870 | K133: 32580 | L133: 32900 | M133: 32440 | N133: 33440 | O133: 33280 | P133: 32230 | Q133: 32100 | R133: 32260 | S133: 32990 | T133: 34000 | U133: 36600 | V133: 38250 | W133: 38330 | X133: 38870 | Y133: 38820 | Z133: 38750 | AA133: 38770 | AB133: 38480 | AC133: 38590 | AD133: 38390 | AE133: 38140 | AF133: 37910 | AG133: 38250 | AH133: 37480 | AI133: 38150 | AJ133: 37480 | AK133: 35930 | AL133: 35790 | AM133: 36460 | AN133: 36550 | AO133: 36610 | AP133: 36640 | AQ133: 36670 | AR133: 36700 | AS133: 36740 | AT133: 36810 | AU133: 36900 | AV133: 37020 | AW133: 37190 | AX133: 37390 | AY133: 37620 | AZ133: 37880 | BA133: 38150 | BB133: 38420 | BC133: 38690 | BD133: 38930 | BE133: 39130 | BF133: 39310 | BG133: 39440 | BH133: 39550 | BI133: 39610
A134: =$A$34 -> 19 | B134: 30250 | C134: 30770 | D134: 31170 | E134: 31800 | F134: 33050 | G134: 32460 | H134: 32470 | I134: 32290 | J134: 33320 | K134: 34130 | L134: 33640 | M134: 33610 | N134: 32890 | O134: 33760 | P134: 33740 | Q134: 31810 | R134: 31740 | S134: 33010 | T134: 33790 | U134: 34500 | V134: 37170 | W134: 38850 | X134: 38960 | Y134: 39520 | Z134: 39480 | AA134: 39420 | AB134: 39450 | AC134: 39160 | AD134: 39270 | AE134: 39080 | AF134: 38840 | AG134: 38610 | AH134: 38950 | AI134: 38190 | AJ134: 38860 | AK134: 38190 | AL134: 36640 | AM134: 36510 | AN134: 37190 | AO134: 37280 | AP134: 37340 | AQ134: 37380 | AR134: 37410 | AS134: 37440 | AT134: 37490 | AU134: 37560 | AV134: 37650 | AW134: 37780 | AX134: 37950 | AY134: 38160 | AZ134: 38390 | BA134: 38650 | BB134: 38930 | BC134: 39200 | BD134: 39470 | BE134: 39710 | BF134: 39920 | BG134: 40100 | BH134: 40240 | BI134: 40350
A135: =$A$35 -> 20 | B135: 29830 | C135: 29900 | D135: 30470 | E135: 31180 | F135: 32100 | G135: 33380 | H135: 32580 | I135: 32810 | J135: 33360 | K135: 34710 | L135: 35250 | M135: 34280 | N135: 34130 | O135: 33130 | P135: 34400 | Q135: 33190 | R135: 31430 | S135: 32620 | T135: 34030 | U135: 34210 | V135: 35000 | W135: 37700 | X135: 39420 | Y135: 39550 | Z135: 40120 | AA135: 40100 | AB135: 40040 | AC135: 40070 | AD135: 39790 | AE135: 39900 | AF135: 39710 | AG135: 39470 | AH135: 39250 | AI135: 39600 | AJ135: 38840 | AK135: 39510 | AL135: 38850 | AM135: 37310 | AN135: 37170 | AO135: 37860 | AP135: 37950 | AQ135: 38020 | AR135: 38060 | AS135: 38100 | AT135: 38140 | AU135: 38190 | AV135: 38260 | AW135: 38360 | AX135: 38490 | AY135: 38660 | AZ135: 38870 | BA135: 39110 | BB135: 39380 | BC135: 39660 | BD135: 39940 | BE135: 40210 | BF135: 40450 | BG135: 40670 | BH135: 40850 | BI135: 41000
A136: =$A$36 -> 21 | B136: 29560 | C136: 29170 | D136: 29450 | E136: 30280 | F136: 31170 | G136: 32090 | H136: 33060 | I136: 32490 | J136: 33640 | K136: 34560 | L136: 35630 | M136: 35580 | N136: 34500 | O136: 34400 | P136: 33810 | Q136: 33920 | R136: 32710 | S136: 32360 | T136: 33420 | U136: 34220 | V136: 34470 | W136: 35290 | X136: 38030 | Y136: 39760 | Z136: 39910 | AA136: 40490 | AB136: 40470 | AC136: 40410 | AD136: 40450 | AE136: 40170 | AF136: 40290 | AG136: 40100 | AH136: 39870 | AI136: 39660 | AJ136: 40000 | AK136: 39250 | AL136: 39920 | AM136: 39270 | AN136: 37730 | AO136: 37600 | AP136: 38290 | AQ136: 38390 | AR136: 38460 | AS136: 38510 | AT136: 38550 | AU136: 38590 | AV136: 38640 | AW136: 38710 | AX136: 38820 | AY136: 38950 | AZ136: 39130 | BA136: 39350 | BB136: 39590 | BC136: 39860 | BD136: 40140 | BE136: 40420 | BF136: 40700 | BG136: 40950 | BH136: 41170 | BI136: 41350
A137: =$A$37 -> 22 | B137: 29400 | C137: 28750 | D137: 28560 | E137: 29170 | F137: 30130 | G137: 30860 | H137: 31510 | I137: 32760 | J137: 33500 | K137: 35130 | L137: 35470 | M137: 35840 | N137: 35600 | O137: 34550 | P137: 34890 | Q137: 33310 | R137: 33450 | S137: 33470 | T137: 33000 | U137: 33510 | V137: 34380 | W137: 34670 | X137: 35520 | Y137: 38280 | Z137: 40030 | AA137: 40190 | AB137: 40770 | AC137: 40750 | AD137: 40700 | AE137: 40740 | AF137: 40470 | AG137: 40590 | AH137: 40410 | AI137: 40180 | AJ137: 39970 | AK137: 40320 | AL137: 39570 | AM137: 40250 | AN137: 39600 | AO137: 38060 | AP137: 37940 | AQ137: 38630 | AR137: 38730 | AS137: 38810 | AT137: 38860 | AU137: 38900 | AV137: 38950 | AW137: 39010 | AX137: 39090 | AY137: 39190 | AZ137: 39330 | BA137: 39510 | BB137: 39730 | BC137: 39980 | BD137: 40250 | BE137: 40540 | BF137: 40830 | BG137: 41100 | BH137: 41360 | BI137: 41580
A138: =$A$38 -> 23 | B138: 29090 | C138: 28510 | D138: 28050 | E138: 28280 | F138: 28950 | G138: 29690 | H138: 30250 | I138: 31220 | J138: 33600 | K138: 35270 | L138: 36570 | M138: 36110 | N138: 36120 | O138: 35810 | P138: 35380 | Q138: 34290 | R138: 32750 | S138: 34240 | T138: 34000 | U138: 33050 | V138: 33640 | W138: 34560 | X138: 34880 | Y138: 35750 | Z138: 38530 | AA138: 40280 | AB138: 40450 | AC138: 41030 | AD138: 41020 | AE138: 40970 | AF138: 41010 | AG138: 40750 | AH138: 40880 | AI138: 40690 | AJ138: 40470 | AK138: 40260 | AL138: 40620 | AM138: 39880 | AN138: 40560 | AO138: 39910 | AP138: 38380 | AQ138: 38260 | AR138: 38960 | AS138: 39060 | AT138: 39140 | AU138: 39200 | AV138: 39250 | AW138: 39300 | AX138: 39360 | AY138: 39440 | AZ138: 39550 | BA138: 39700 | BB138: 39880 | BC138: 40100 | BD138: 40360 | BE138: 40630 | BF138: 40920 | BG138: 41220 | BH138: 41500 | BI138: 41760
A139: =$A$39 -> 24 | B139: 27970 | C139: 28320 | D139: 27860 | E139: 27710 | F139: 28100 | G139: 28460 | H139: 28950 | I139: 29910 | J139: 32200 | K139: 35200 | L139: 36820 | M139: 37470 | N139: 36450 | O139: 36340 | P139: 36870 | Q139: 34730 | R139: 33700 | S139: 33590 | T139: 34620 | U139: 34050 | V139: 33180 | W139: 33810 | X139: 34750 | Y139: 35100 | Z139: 35990 | AA139: 38770 | AB139: 40530 | AC139: 40700 | AD139: 41290 | AE139: 41280 | AF139: 41230 | AG139: 41280 | AH139: 41020 | AI139: 41150 | AJ139: 40980 | AK139: 40760 | AL139: 40550 | AM139: 40910 | AN139: 40170 | AO139: 40860 | AP139: 40220 | AQ139: 38690 | AR139: 38580 | AS139: 39280 | AT139: 39390 | AU139: 39470 | AV139: 39530 | AW139: 39580 | AX139: 39640 | AY139: 39700 | AZ139: 39790 | BA139: 39910 | BB139: 40050 | BC139: 40240 | BD139: 40470 | BE139: 40720 | BF139: 41000 | BG139: 41300 | BH139: 41600 | BI139: 41880
A140: =$A$40 -> 25 | B140: 26850 | C140: 27330 | D140: 27690 | E140: 27550 | F140: 27400 | G140: 27490 | H140: 27780 | I140: 28550 | J140: 30780 | K140: 33840 | L140: 36740 | M140: 37940 | N140: 37990 | O140: 36610 | P140: 37410 | Q140: 36230 | R140: 34050 | S140: 34530 | T140: 33850 | U140: 34660 | V140: 34170 | W140: 33330 | X140: 33990 | Y140: 34960 | Z140: 35320 | AA140: 36220 | AB140: 39000 | AC140: 40760 | AD140: 40930 | AE140: 41530 | AF140: 41520 | AG140: 41480 | AH140: 41540 | AI140: 41280 | AJ140: 41410 | AK140: 41240 | AL140: 41030 | AM140: 40830 | AN140: 41190 | AO140: 40460 | AP140: 41150 | AQ140: 40510 | AR140: 38990 | AS140: 38880 | AT140: 39580 | AU140: 39700 | AV140: 39780 | AW140: 39850 | AX140: 39900 | AY140: 39960 | AZ140: 40030 | BA140: 40120 | BB140: 40240 | BC140: 40390 | BD140: 40590 | BE140: 40820 | BF140: 41080 | BG140: 41360 | BH140: 41660 | BI140: 41960
A141: =$A$41 -> 26 | B141: 25810 | C141: 26520 | D141: 26680 | E141: 27300 | F141: 27360 | G141: 26870 | H141: 26900 | I141: 27500 | J141: 29490 | K141: 32170 | L141: 35490 | M141: 37790 | N141: 38730 | O141: 38220 | P141: 37780 | Q141: 36690 | R141: 35310 | S141: 35000 | T141: 34780 | U141: 33920 | V141: 34790 | W141: 34330 | X141: 33530 | Y141: 34210 | Z141: 35190 | AA141: 35560 | AB141: 36460 | AC141: 39240 | AD141: 41010 | AE141: 41190 | AF141: 41780 | AG141: 41780 | AH141: 41750 | AI141: 41800 | AJ141: 41550 | AK141: 41690 | AL141: 41520 | AM141: 41310 | AN141: 41120 | AO141: 41480 | AP141: 40750 | AQ141: 41440 | AR141: 40810 | AS141: 39300 | AT141: 39190 | AU141: 39900 | AV141: 40010 | AW141: 40100 | AX141: 40170 | AY141: 40230 | AZ141: 40290 | BA141: 40370 | BB141: 40460 | BC141: 40580 | BD141: 40740 | BE141: 40940 | BF141: 41170 | BG141: 41430 | BH141: 41720 | BI141: 42020
A142: =$A$42 -> 27 | B142: 24950 | C142: 25500 | D142: 26180 | E142: 26500 | F142: 27160 | G142: 26830 | H142: 26330 | I142: 26710 | J142: 28440 | K142: 31000 | L142: 33600 | M142: 36760 | N142: 38680 | O142: 39030 | P142: 39300 | Q142: 37130 | R142: 35860 | S142: 36560 | T142: 35260 | U142: 34910 | V142: 34110 | W142: 35020 | X142: 34590 | Y142: 33800 | Z142: 34500 | AA142: 35480 | AB142: 35850 | AC142: 36760 | AD142: 39550 | AE142: 41310 | AF142: 41490 | AG142: 42090 | AH142: 42100 | AI142: 42060 | AJ142: 42120 | AK142: 41880 | AL142: 42020 | AM142: 41850 | AN142: 41650 | AO142: 41460 | AP142: 41830 | AQ142: 41100 | AR142: 41790 | AS142: 41160 | AT142: 39660 | AU142: 39550 | AV142: 40260 | AW142: 40380 | AX142: 40470 | AY142: 40550 | AZ142: 40610 | BA142: 40670 | BB142: 40750 | BC142: 40850 | BD142: 40980 | BE142: 41140 | BF142: 41340 | BG142: 41570 | BH142: 41840 | BI142: 42130
A143: =$A$43 -> 28 | B143: 24310 | C143: 25050 | D143: 25420 | E143: 26210 | F143: 26400 | G143: 26740 | H143: 26420 | I143: 26240 | J143: 27720 | K143: 29900 | L143: 32600 | M143: 34940 | N143: 37910 | O143: 39120 | P143: 40080 | Q143: 38540 | R143: 36380 | S143: 37510 | T143: 37090 | U143: 35470 | V143: 35180 | W143: 34420 | X143: 35350 | Y143: 34940 | Z143: 34170 | AA143: 34870 | AB143: 35860 | AC143: 36240 | AD143: 37150 | AE143: 39930 | AF143: 41700 | AG143: 41890 | AH143: 42490 | AI143: 42500 | AJ143: 42470 | AK143: 42530 | AL143: 42290 | AM143: 42430 | AN143: 42270 | AO143: 42070 | AP143: 41880 | AQ143: 42250 | AR143: 41530 | AS143: 42230 | AT143: 41600 | AU143: 40100 | AV143: 40000 | AW143: 40710 | AX143: 40840 | AY143: 40930 | AZ143: 41010 | BA143: 41070 | BB143: 41140 | BC143: 41220 | BD143: 41320 | BE143: 41450 | BF143: 41620 | BG143: 41820 | BH143: 42060 | BI143: 42330
A144: =$A$44 -> 29 | B144: 24860 | C144: 24580 | D144: 25170 | E144: 25650 | F144: 26170 | G144: 26150 | H144: 26520 | I144: 26330 | J144: 27110 | K144: 29070 | L144: 31620 | M144: 34150 | N144: 36030 | O144: 38510 | P144: 40340 | Q144: 39410 | R144: 37670 | S144: 38060 | T144: 38040 | U144: 37380 | V144: 35820 | W144: 35560 | X144: 34820 | Y144: 35780 | Z144: 35380 | AA144: 34610 | AB144: 35320 | AC144: 36310 | AD144: 36690 | AE144: 37600 | AF144: 40390 | AG144: 42160 | AH144: 42350 | AI144: 42960 | AJ144: 42970 | AK144: 42940 | AL144: 43010 | AM144: 42770 | AN144: 42920 | AO144: 42760 | AP144: 42560 | AQ144: 42370 | AR144: 42750 | AS144: 42030 | AT144: 42730 | AU144: 42110 | AV144: 40610 | AW144: 40510 | AX144: 41230 | AY144: 41360 | AZ144: 41460 | BA144: 41530 | BB144: 41600 | BC144: 41680 | BD144: 41760 | BE144: 41860 | BF144: 42000 | BG144: 42160 | BH144: 42370 | BI144: 42610
A145: =$A$45 -> 30 | B145: 25180 | C145: 25160 | D145: 24780 | E145: 25430 | F145: 25770 | G145: 26150 | H145: 26000 | I145: 26530 | J145: 27330 | K145: 28470 | L145: 30500 | M145: 33140 | N145: 35420 | O145: 36740 | P145: 39650 | Q145: 39820 | R145: 38760 | S145: 39660 | T145: 38920 | U145: 38380 | V145: 37780 | W145: 36250 | X145: 36020 | Y145: 35300 | Z145: 36270 | AA145: 35870 | AB145: 35110 | AC145: 35820 | AD145: 36810 | AE145: 37200 | AF145: 38110 | AG145: 40900 | AH145: 42680 | AI145: 42870 | AJ145: 43480 | AK145: 43490 | AL145: 43470 | AM145: 43540 | AN145: 43300 | AO145: 43450 | AP145: 43300 | AQ145: 43100 | AR145: 42920 | AS145: 43300 | AT145: 42590 | AU145: 43290 | AV145: 42670 | AW145: 41170 | AX145: 41080 | AY145: 41800 | AZ145: 41930 | BA145: 42030 | BB145: 42110 | BC145: 42190 | BD145: 42260 | BE145: 42350 | BF145: 42460 | BG145: 42590 | BH145: 42760 | BI145: 42970
A146: =$A$46 -> 31 | B146: 26120 | C146: 25420 | D146: 25480 | E146: 25060 | F146: 25520 | G146: 25770 | H146: 26110 | I146: 26060 | J146: 27460 | K146: 28560 | L146: 29760 | M146: 31930 | N146: 34380 | O146: 36180 | P146: 38030 | Q146: 39100 | R146: 39310 | S146: 40880 | T146: 40550 | U146: 39270 | V146: 38780 | W146: 38210 | X146: 36700 | Y146: 36490 | Z146: 35780 | AA146: 36750 | AB146: 36360 | AC146: 35600 | AD146: 36310 | AE146: 37310 | AF146: 37690 | AG146: 38610 | AH146: 41410 | AI146: 43180 | AJ146: 43370 | AK146: 43990 | AL146: 44000 | AM146: 43990 | AN146: 44060 | AO146: 43820 | AP146: 43980 | AQ146: 43830 | AR146: 43630 | AS146: 43460 | AT146: 43840 | AU146: 43130 | AV146: 43830 | AW146: 43220 | AX146: 41720 | AY146: 41630 | AZ146: 42360 | BA146: 42490 | BB146: 42590 | BC146: 42680 | BD146: 42760 | BE146: 42830 | BF146: 42920 | BG146: 43030 | BH146: 43170 | BI146: 43350
A147: =$A$47 -> 32 | B147: 27080 | C147: 26350 | D147: 25550 | E147: 25630 | F147: 25140 | G147: 25470 | H147: 25610 | I147: 26030 | J147: 26910 | K147: 28440 | L147: 29910 | M147: 31030 | N147: 33060 | O147: 35140 | P147: 37340 | Q147: 37690 | R147: 38630 | S147: 41530 | T147: 41920 | U147: 40890 | V147: 39660 | W147: 39200 | X147: 38640 | Y147: 37150 | Z147: 36950 | AA147: 36250 | AB147: 37220 | AC147: 36840 | AD147: 36080 | AE147: 36790 | AF147: 37790 | AG147: 38180 | AH147: 39100 | AI147: 41900 | AJ147: 43670 | AK147: 43870 | AL147: 44480 | AM147: 44500 | AN147: 44490 | AO147: 44560 | AP147: 44330 | AQ147: 44490 | AR147: 44340 | AS147: 44150 | AT147: 43980 | AU147: 44360 | AV147: 43650 | AW147: 44360 | AX147: 43750 | AY147: 42260 | AZ147: 42170 | BA147: 42900 | BB147: 43030 | BC147: 43140 | BD147: 43230 | BE147: 43310 | BF147: 43390 | BG147: 43480 | BH147: 43590 | BI147: 43730
A148: =$A$48 -> 33 | B148: 28270 | C148: 27360 | D148: 26460 | E148: 25700 | F148: 25670 | G148: 25030 | H148: 25340 | I148: 25570 | J148: 26780 | K148: 27870 | L148: 29590 | M148: 31100 | N148: 32140 | O148: 33860 | P148: 36230 | Q148: 37180 | R148: 37370 | S148: 40990 | T148: 42440 | U148: 42270 | V148: 41290 | W148: 40090 | X148: 39640 | Y148: 39110 | Z148: 37630 | AA148: 37440 | AB148: 36730 | AC148: 37710 | AD148: 37330 | AE148: 36580 | AF148: 37290 | AG148: 38290 | AH148: 38680 | AI148: 39610 | AJ148: 42400 | AK148: 44180 | AL148: 44380 | AM148: 45000 | AN148: 45020 | AO148: 45010 | AP148: 45090 | AQ148: 44860 | AR148: 45020 | AS148: 44870 | AT148: 44680 | AU148: 44510 | AV148: 44900 | AW148: 44190 | AX148: 44910 | AY148: 44300 | AZ148: 42810 | BA148: 42720 | BB148: 43450 | BC148: 43590 | BD148: 43700 | BE148: 43790 | BF148: 43870 | BG148: 43960 | BH148: 44050 | BI148: 44170
A149: =$A$49 -> 34 | B149: 29670 | C149: 28570 | D149: 27580 | E149: 26650 | F149: 25770 | G149: 25700 | H149: 24980 | I149: 25320 | J149: 26290 | K149: 27700 | L149: 28960 | M149: 30720 | N149: 32190 | O149: 32930 | P149: 34780 | Q149: 36150 | R149: 37020 | S149: 39800 | T149: 42130 | U149: 42790 | V149: 42660 | W149: 41710 | X149: 40530 | Y149: 40110 | Z149: 39590 | AA149: 38110 | AB149: 37920 | AC149: 37220 | AD149: 38200 | AE149: 37820 | AF149: 37070 | AG149: 37790 | AH149: 38800 | AI149: 39190 | AJ149: 40110 | AK149: 42910 | AL149: 44690 | AM149: 44890 | AN149: 45510 | AO149: 45540 | AP149: 45530 | AQ149: 45610 | AR149: 45390 | AS149: 45550 | AT149: 45410 | AU149: 45220 | AV149: 45050 | AW149: 45450 | AX149: 44740 | AY149: 45460 | AZ149: 44850 | BA149: 43370 | BB149: 43280 | BC149: 44020 | BD149: 44160 | BE149: 44270 | BF149: 44360 | BG149: 44450 | BH149: 44530 | BI149: 44630
A150: =$A$50 -> 35 | B150: 30140 | C150: 29910 | D150: 28640 | E150: 27750 | F150: 26780 | G150: 25730 | H150: 25670 | I150: 24970 | J150: 25980 | K150: 27190 | L150: 28680 | M150: 30040 | N150: 31710 | O150: 32960 | P150: 34060 | Q150: 34860 | R150: 36130 | S150: 39320 | T150: 40830 | U150: 42480 | V150: 43190 | W150: 43100 | X150: 42170 | Y150: 41010 | Z150: 40600 | AA150: 40080 | AB150: 38610 | AC150: 38420 | AD150: 37730 | AE150: 38710 | AF150: 38330 | AG150: 37590 | AH150: 38310 | AI150: 39320 | AJ150: 39710 | AK150: 40640 | AL150: 43440 | AM150: 45220 | AN150: 45420 | AO150: 46050 | AP150: 46070 | AQ150: 46070 | AR150: 46150 | AS150: 45930 | AT150: 46100 | AU150: 45960 | AV150: 45780 | AW150: 45610 | AX150: 46010 | AY150: 45310 | AZ150: 46020 | BA150: 45420 | BB150: 43940 | BC150: 43860 | BD150: 44590 | BE150: 44740 | BF150: 44860 | BG150: 44950 | BH150: 45040 | BI150: 45130
A151: =$A$51 -> 36 | B151: 29680 | C151: 30320 | D151: 30070 | E151: 28790 | F151: 27890 | G151: 26800 | H151: 25710 | I151: 25740 | J151: 25570 | K151: 26830 | L151: 28100 | M151: 29670 | N151: 31090 | O151: 32550 | P151: 33910 | Q151: 34040 | R151: 34850 | S151: 38490 | T151: 40500 | U151: 41180 | V151: 42880 | W151: 43630 | X151: 43550 | Y151: 42650 | Z151: 41500 | AA151: 41090 | AB151: 40570 | AC151: 39110 | AD151: 38930 | AE151: 38240 | AF151: 39220 | AG151: 38850 | AH151: 38110 | AI151: 38830 | AJ151: 39840 | AK151: 40240 | AL151: 41170 | AM151: 43970 | AN151: 45750 | AO151: 45960 | AP151: 46580 | AQ151: 46620 | AR151: 46610 | AS151: 46700 | AT151: 46480 | AU151: 46650 | AV151: 46520 | AW151: 46340 | AX151: 46180 | AY151: 46570 | AZ151: 45880 | BA151: 46600 | BB151: 46000 | BC151: 44520 | BD151: 44440 | BE151: 45180 | BF151: 45330 | BG151: 45450 | BH151: 45550 | BI151: 45640
A152: =$A$52 -> 37 | B152: 30040 | C152: 29860 | D152: 30480 | E152: 30200 | F152: 28920 | G152: 27960 | H152: 26770 | I152: 25830 | J152: 26230 | K152: 26280 | L152: 27720 | M152: 29140 | N152: 30600 | O152: 31900 | P152: 33520 | Q152: 33930 | R152: 34010 | S152: 37020 | T152: 39680 | U152: 40830 | V152: 41560 | W152: 43290 | X152: 44060 | Y152: 44000 | Z152: 43110 | AA152: 41960 | AB152: 41560 | AC152: 41050 | AD152: 39590 | AE152: 39410 | AF152: 38720 | AG152: 39710 | AH152: 39340 | AI152: 38600 | AJ152: 39330 | AK152: 40340 | AL152: 40740 | AM152: 41670 | AN152: 44470 | AO152: 46260 | AP152: 46470 | AQ152: 47100 | AR152: 47130 | AS152: 47130 | AT152: 47220 | AU152: 47010 | AV152: 47180 | AW152: 47050 | AX152: 46870 | AY152: 46710 | AZ152: 47110 | BA152: 46420 | BB152: 47140 | BC152: 46550 | BD152: 45080 | BE152: 45000 | BF152: 45740 | BG152: 45890 | BH152: 46010 | BI152: 46120
A153: =$A$53 -> 38 | B153: 29710 | C153: 30220 | D153: 29910 | E153: 30610 | F153: 30300 | G153: 28910 | H153: 27940 | I153: 26840 | J153: 26360 | K153: 26880 | L153: 27080 | M153: 28640 | N153: 30040 | O153: 31220 | P153: 32640 | Q153: 33520 | R153: 33910 | S153: 36150 | T153: 37960 | U153: 39990 | V153: 41200 | W153: 41960 | X153: 43710 | Y153: 44490 | Z153: 44440 | AA153: 43550 | AB153: 42410 | AC153: 42020 | AD153: 41510 | AE153: 40050 | AF153: 39880 | AG153: 39190 | AH153: 40180 | AI153: 39810 | AJ153: 39080 | AK153: 39810 | AL153: 40820 | AM153: 41230 | AN153: 42160 | AO153: 44960 | AP153: 46750 | AQ153: 46970 | AR153: 47600 | AS153: 47640 | AT153: 47640 | AU153: 47730 | AV153: 47520 | AW153: 47700 | AX153: 47570 | AY153: 47400 | AZ153: 47240 | BA153: 47640 | BB153: 46950 | BC153: 47680 | BD153: 47080 | BE153: 45620 | BF153: 45550 | BG153: 46290 | BH153: 46440 | BI153: 46570
A154: =$A$54 -> 39 | B154: 29570 | C154: 29890 | D154: 30260 | E154: 30030 | F154: 30640 | G154: 30250 | H154: 28910 | I154: 28120 | J154: 27310 | K154: 27010 | L154: 27580 | M154: 27870 | N154: 29500 | O154: 30730 | P154: 32010 | Q154: 32580 | R154: 33360 | S154: 35930 | T154: 37120 | U154: 38240 | V154: 40330 | W154: 41560 | X154: 42340 | Y154: 44100 | Z154: 44890 | AA154: 44850 | AB154: 43970 | AC154: 42830 | AD154: 42440 | AE154: 41930 | AF154: 40490 | AG154: 40310 | AH154: 39630 | AI154: 40620 | AJ154: 40260 | AK154: 39530 | AL154: 40260 | AM154: 41280 | AN154: 41680 | AO154: 42620 | AP154: 45420 | AQ154: 47210 | AR154: 47430 | AS154: 48060 | AT154: 48100 | AU154: 48110 | AV154: 48210 | AW154: 48000 | AX154: 48180 | AY154: 48050 | AZ154: 47880 | BA154: 47730 | BB154: 48130 | BC154: 47450 | BD154: 48180 | BE154: 47590 | BF154: 46120 | BG154: 46060 | BH154: 46800 | BI154: 46960
A155: =$A$55 -> 40 | B155: 29920 | C155: 29750 | D155: 29950 | E155: 30360 | F155: 30050 | G155: 30610 | H155: 30210 | I155: 29000 | J155: 28540 | K155: 27880 | L155: 27730 | M155: 28340 | N155: 28670 | O155: 30090 | P155: 31440 | Q155: 32070 | R155: 32430 | S155: 35210 | T155: 36830 | U155: 37360 | V155: 38530 | W155: 40640 | X155: 41890 | Y155: 42680 | Z155: 44450 | AA155: 45250 | AB155: 45210 | AC155: 44330 | AD155: 43200 | AE155: 42810 | AF155: 42310 | AG155: 40860 | AH155: 40690 | AI155: 40010 | AJ155: 41010 | AK155: 40650 | AL155: 39920 | AM155: 40650 | AN155: 41670 | AO155: 42080 | AP155: 43020 | AQ155: 45820 | AR155: 47620 | AS155: 47840 | AT155: 48470 | AU155: 48520 | AV155: 48530 | AW155: 48630 | AX155: 48420 | AY155: 48600 | AZ155: 48480 | BA155: 48310 | BB155: 48160 | BC155: 48570 | BD155: 47890 | BE155: 48620 | BF155: 48030 | BG155: 46570 | BH155: 46510 | BI155: 47250
A156: =$A$56 -> 41 | B156: 30380 | C156: 30040 | D156: 29780 | E156: 30010 | F156: 30420 | G156: 30010 | H156: 30580 | I156: 30270 | J156: 29570 | K156: 29050 | L156: 28500 | M156: 28400 | N156: 29020 | O156: 29160 | P156: 30680 | Q156: 31450 | R156: 31950 | S156: 34140 | T156: 36090 | U156: 37050 | V156: 37620 | W156: 38810 | X156: 40940 | Y156: 42200 | Z156: 43000 | AA156: 44780 | AB156: 45570 | AC156: 45540 | AD156: 44670 | AE156: 43540 | AF156: 43150 | AG156: 42650 | AH156: 41210 | AI156: 41040 | AJ156: 40370 | AK156: 41360 | AL156: 41010 | AM156: 40290 | AN156: 41020 | AO156: 42040 | AP156: 42450 | AQ156: 43400 | AR156: 46200 | AS156: 47990 | AT156: 48220 | AU156: 48850 | AV156: 48900 | AW156: 48910 | AX156: 49020 | AY156: 48810 | AZ156: 49000 | BA156: 48880 | BB156: 48710 | BC156: 48570 | BD156: 48980 | BE156: 48300 | BF156: 49030 | BG156: 48450 | BH156: 46990 | BI156: 46930
A157: =$A$57 -> 42 | B157: 31600 | C157: 30480 | D157: 30040 | E157: 29810 | F157: 30060 | G157: 30400 | H157: 29940 | I157: 30650 | J157: 30730 | K157: 30140 | L157: 29640 | M157: 29160 | N157: 29050 | O157: 29590 | P157: 29730 | Q157: 30660 | R157: 31300 | S157: 33460 | T157: 34890 | U157: 36270 | V157: 37260 | W157: 37860 | X157: 39070 | Y157: 41200 | Z157: 42470 | AA157: 43280 | AB157: 45050 | AC157: 45850 | AD157: 45820 | AE157: 44950 | AF157: 43830 | AG157: 43440 | AH157: 42950 | AI157: 41510 | AJ157: 41350 | AK157: 40680 | AL157: 41670 | AM157: 41320 | AN157: 40600 | AO157: 41340 | AP157: 42360 | AQ157: 42780 | AR157: 43720 | AS157: 46520 | AT157: 48320 | AU157: 48540 | AV157: 49180 | AW157: 49230 | AX157: 49250 | AY157: 49350 | AZ157: 49150 | BA157: 49340 | BB157: 49220 | BC157: 49060 | BD157: 48920 | BE157: 49330 | BF157: 48660 | BG157: 49390 | BH157: 48810 | BI157: 47360
A158: =$A$58 -> 43 | B158: 31940 | C158: 31630 | D158: 30470 | E158: 30040 | F158: 29760 | G158: 30010 | H158: 30300 | I158: 29990 | J158: 31110 | K158: 31310 | L158: 30820 | M158: 30240 | N158: 29770 | O158: 29500 | P158: 30100 | Q158: 29670 | R158: 30480 | S158: 32720 | T158: 34120 | U158: 35030 | V158: 36440 | W158: 37460 | X158: 38070 | Y158: 39290 | Z158: 41430 | AA158: 42700 | AB158: 43510 | AC158: 45290 | AD158: 46090 | AE158: 46060 | AF158: 45190 | AG158: 44070 | AH158: 43690 | AI158: 43200 | AJ158: 41770 | AK158: 41600 | AL158: 40940 | AM158: 41940 | AN158: 41590 | AO158: 40870 | AP158: 41610 | AQ158: 42630 | AR158: 43050 | AS158: 43990 | AT158: 46800 | AU158: 48600 | AV158: 48820 | AW158: 49470 | AX158: 49520 | AY158: 49540 | AZ158: 49640 | BA158: 49440 | BB158: 49630 | BC158: 49520 | BD158: 49360 | BE158: 49220 | BF158: 49640 | BG158: 48960 | BH158: 49700 | BI158: 49120
A159: =$A$59 -> 44 | B159: 32110 | C159: 31970 | D159: 31540 | E159: 30420 | F159: 30060 | G159: 29670 | H159: 29920 | I159: 30260 | J159: 30470 | K159: 31570 | L159: 31930 | M159: 31430 | N159: 30790 | O159: 30130 | P159: 29960 | Q159: 30130 | R159: 29490 | S159: 31720 | T159: 33250 | U159: 34210 | V159: 35150 | W159: 36580 | X159: 37610 | Y159: 38230 | Z159: 39450 | AA159: 41600 | AB159: 42870 | AC159: 43680 | AD159: 45460 | AE159: 46260 | AF159: 46240 | AG159: 45370 | AH159: 44260 | AI159: 43880 | AJ159: 43390 | AK159: 41960 | AL159: 41800 | AM159: 41140 | AN159: 42140 | AO159: 41790 | AP159: 41080 | AQ159: 41820 | AR159: 42850 | AS159: 43260 | AT159: 44210 | AU159: 47010 | AV159: 48810 | AW159: 49040 | AX159: 49690 | AY159: 49740 | AZ159: 49760 | BA159: 49870 | BB159: 49670 | BC159: 49870 | BD159: 49750 | BE159: 49600 | BF159: 49460 | BG159: 49880 | BH159: 49210 | BI159: 49950
A160: =$A$60 -> 45 | B160: 31490 | C160: 32140 | D160: 31920 | E160: 31530 | F160: 30400 | G160: 29970 | H160: 29530 | I160: 29930 | J160: 30650 | K160: 30940 | L160: 32060 | M160: 32500 | N160: 32030 | O160: 31110 | P160: 30480 | Q160: 29940 | R160: 29970 | S160: 30510 | T160: 32190 | U160: 33300 | V160: 34290 | W160: 35240 | X160: 36690 | Y160: 37720 | Z160: 38350 | AA160: 39580 | AB160: 41720 | AC160: 42990 | AD160: 43810 | AE160: 45580 | AF160: 46390 | AG160: 46370 | AH160: 45500 | AI160: 44390 | AJ160: 44020 | AK160: 43530 | AL160: 42110 | AM160: 41950 | AN160: 41290 | AO160: 42290 | AP160: 41950 | AQ160: 41240 | AR160: 41980 | AS160: 43010 | AT160: 43430 | AU160: 44380 | AV160: 47180 | AW160: 48980 | AX160: 49210 | AY160: 49850 | AZ160: 49910 | BA160: 49930 | BB160: 50050 | BC160: 49850 | BD160: 50050 | BE160: 49940 | BF160: 49780 | BG160: 49650 | BH160: 50070 | BI160: 49400
A161: =$A$61 -> 46 | B161: 30540 | C161: 31420 | D161: 32070 | E161: 31870 | F161: 31460 | G161: 30290 | H161: 29820 | I161: 29520 | J161: 30230 | K161: 31090 | L161: 31460 | M161: 32560 | N161: 33000 | O161: 32250 | P161: 31470 | Q161: 30400 | R161: 29730 | S161: 30820 | T161: 30860 | U161: 32200 | V161: 33330 | W161: 34330 | X161: 35300 | Y161: 36750 | Z161: 37790 | AA161: 38420 | AB161: 39650 | AC161: 41790 | AD161: 43060 | AE161: 43880 | AF161: 45660 | AG161: 46460 | AH161: 46440 | AI161: 45580 | AJ161: 44480 | AK161: 44100 | AL161: 43620 | AM161: 42200 | AN161: 42050 | AO161: 41390 | AP161: 42390 | AQ161: 42050 | AR161: 41350 | AS161: 42090 | AT161: 43120 | AU161: 43540 | AV161: 44490 | AW161: 47290 | AX161: 49090 | AY161: 49320 | AZ161: 49970 | BA161: 50030 | BB161: 50050 | BC161: 50170 | BD161: 49980 | BE161: 50170 | BF161: 50070 | BG161: 49920 | BH161: 49780 | BI161: 50200
A162: =$A$62 -> 47 | B162: 30080 | C162: 30470 | D162: 31270 | E162: 31960 | F162: 31720 | G162: 31300 | H162: 30150 | I162: 29680 | J162: 29780 | K162: 30590 | L162: 31490 | M162: 31920 | N162: 33000 | O162: 33200 | P162: 32490 | Q162: 31370 | R162: 30170 | S162: 30450 | T162: 31110 | U162: 30830 | V162: 32200 | W162: 33340 | X162: 34350 | Y162: 35330 | Z162: 36780 | AA162: 37820 | AB162: 38450 | AC162: 39680 | AD162: 41820 | AE162: 43100 | AF162: 43910 | AG162: 45690 | AH162: 46500 | AI162: 46480 | AJ162: 45630 | AK162: 44520 | AL162: 44150 | AM162: 43680 | AN162: 42260 | AO162: 42110 | AP162: 41460 | AQ162: 42460 | AR162: 42120 | AS162: 41420 | AT162: 42160 | AU162: 43190 | AV162: 43610 | AW162: 44560 | AX162: 47360 | AY162: 49160 | AZ162: 49400 | BA162: 50050 | BB162: 50110 | BC162: 50140 | BD162: 50250 | BE162: 50060 | BF162: 50260 | BG162: 50160 | BH162: 50010 | BI162: 49880
A163: =$A$63 -> 48 | B163: 28610 | C163: 30010 | D163: 30340 | E163: 31240 | F163: 31890 | G163: 31530 | H163: 31110 | I163: 30000 | J163: 29900 | K163: 30080 | L163: 31030 | M163: 31900 | N163: 32290 | O163: 33190 | P163: 33360 | Q163: 32400 | R163: 31200 | S163: 30640 | T163: 30670 | U163: 31040 | V163: 30790 | W163: 32170 | X163: 33320 | Y163: 34340 | Z163: 35320 | AA163: 36770 | AB163: 37820 | AC163: 38450 | AD163: 39680 | AE163: 41810 | AF163: 43090 | AG163: 43910 | AH163: 45680 | AI163: 46490 | AJ163: 46480 | AK163: 45630 | AL163: 44530 | AM163: 44160 | AN163: 43690 | AO163: 42280 | AP163: 42130 | AQ163: 41480 | AR163: 42480 | AS163: 42140 | AT163: 41440 | AU163: 42190 | AV163: 43220 | AW163: 43650 | AX163: 44600 | AY163: 47400 | AZ163: 49200 | BA163: 49430 | BB163: 50080 | BC163: 50150 | BD163: 50180 | BE163: 50290 | BF163: 50110 | BG163: 50310 | BH163: 50210 | BI163: 50060
A164: =$A$64 -> 49 | B164: 28400 | C164: 28490 | D164: 29860 | E164: 30220 | F164: 31130 | G164: 31760 | H164: 31330 | I164: 30960 | J164: 30200 | K164: 30140 | L164: 30360 | M164: 31360 | N164: 32290 | O164: 32420 | P164: 33360 | Q164: 33200 | R164: 32130 | S164: 31570 | T164: 30730 | U164: 30570 | V164: 30970 | W164: 30730 | X164: 32110 | Y164: 33270 | Z164: 34300 | AA164: 35270 | AB164: 36730 | AC164: 37770 | AD164: 38400 | AE164: 39630 | AF164: 41770 | AG164: 43050 | AH164: 43860 | AI164: 45640 | AJ164: 46450 | AK164: 46440 | AL164: 45590 | AM164: 44500 | AN164: 44130 | AO164: 43660 | AP164: 42260 | AQ164: 42110 | AR164: 41460 | AS164: 42470 | AT164: 42130 | AU164: 41440 | AV164: 42180 | AW164: 43210 | AX164: 43640 | AY164: 44590 | AZ164: 47390 | BA164: 49190 | BB164: 49430 | BC164: 50080 | BD164: 50150 | BE164: 50180 | BF164: 50300 | BG164: 50120 | BH164: 50320 | BI164: 50220
A165: =$A$65 -> 50 | B165: 27750 | C165: 28300 | D165: 28330 | E165: 29730 | F165: 30080 | G165: 30940 | H165: 31520 | I165: 31200 | J165: 31150 | K165: 30470 | L165: 30440 | M165: 30640 | N165: 31660 | O165: 32300 | P165: 32540 | Q165: 33310 | R165: 32920 | S165: 32370 | T165: 31620 | U165: 30610 | V165: 30470 | W165: 30880 | X165: 30650 | Y165: 32040 | Z165: 33200 | AA165: 34230 | AB165: 35200 | AC165: 36660 | AD165: 37700 | AE165: 38340 | AF165: 39570 | AG165: 41700 | AH165: 42980 | AI165: 43800 | AJ165: 45570 | AK165: 46380 | AL165: 46370 | AM165: 45530 | AN165: 44440 | AO165: 44080 | AP165: 43610 | AQ165: 42210 | AR165: 42060 | AS165: 41420 | AT165: 42430 | AU165: 42100 | AV165: 41400 | AW165: 42150 | AX165: 43180 | AY165: 43610 | AZ165: 44560 | BA165: 47360 | BB165: 49160 | BC165: 49400 | BD165: 50050 | BE165: 50120 | BF165: 50150 | BG165: 50280 | BH165: 50090 | BI165: 50300
A166: =$A$66 -> 51 | B166: 26550 | C166: 27630 | D166: 28160 | E166: 28190 | F166: 29630 | G166: 29880 | H166: 30740 | I166: 31370 | J166: 31370 | K166: 31310 | L166: 30700 | M166: 30660 | N166: 30900 | O166: 31600 | P166: 32400 | Q166: 32350 | R166: 33040 | S166: 33030 | T166: 32270 | U166: 31480 | V166: 30490 | W166: 30360 | X166: 30780 | Y166: 30560 | Z166: 31950 | AA166: 33110 | AB166: 34140 | AC166: 35110 | AD166: 36570 | AE166: 37610 | AF166: 38250 | AG166: 39480 | AH166: 41610 | AI166: 42880 | AJ166: 43700 | AK166: 45480 | AL166: 46290 | AM166: 46280 | AN166: 45450 | AO166: 44360 | AP166: 44000 | AQ166: 43540 | AR166: 42140 | AS166: 42000 | AT166: 41360 | AU166: 42360 | AV166: 42040 | AW166: 41350 | AX166: 42100 | AY166: 43130 | AZ166: 43560 | BA166: 44510 | BB166: 47300 | BC166: 49100 | BD166: 49340 | BE166: 50000 | BF166: 50070 | BG166: 50110 | BH166: 50230 | BI166: 50050
A167: =$A$67 -> 52 | B167: 25810 | C167: 26450 | D167: 27420 | E167: 27980 | F167: 28050 | G167: 29430 | H167: 29630 | I167: 30570 | J167: 31440 | K167: 31620 | L167: 31560 | M167: 30960 | N167: 30800 | O167: 30820 | P167: 31600 | Q167: 32220 | R167: 32060 | S167: 33110 | T167: 32980 | U167: 32110 | V167: 31350 | W167: 30370 | X167: 30250 | Y167: 30680 | Z167: 30460 | AA167: 31850 | AB167: 33010 | AC167: 34030 | AD167: 35010 | AE167: 36470 | AF167: 37510 | AG167: 38140 | AH167: 39370 | AI167: 41500 | AJ167: 42780 | AK167: 43600 | AL167: 45370 | AM167: 46180 | AN167: 46180 | AO167: 45350 | AP167: 44270 | AQ167: 43910 | AR167: 43450 | AS167: 42060 | AT167: 41920 | AU167: 41280 | AV167: 42290 | AW167: 41960 | AX167: 41280 | AY167: 42030 | AZ167: 43060 | BA167: 43490 | BB167: 44440 | BC167: 47240 | BD167: 49030 | BE167: 49280 | BF167: 49930 | BG167: 50010 | BH167: 50040 | BI167: 50170
A168: =$A$68 -> 53 | B168: 25070 | C168: 25680 | D168: 26270 | E168: 27290 | F168: 27870 | G168: 27840 | H168: 29190 | I168: 29500 | J168: 30590 | K168: 31550 | L168: 31810 | M168: 31740 | N168: 31150 | O168: 30770 | P168: 30920 | Q168: 31440 | R168: 31950 | S168: 32010 | T168: 33070 | U168: 32820 | V168: 31970 | W168: 31220 | X168: 30260 | Y168: 30140 | Z168: 30570 | AA168: 30360 | AB168: 31740 | AC168: 32910 | AD168: 33930 | AE168: 34910 | AF168: 36360 | AG168: 37400 | AH168: 38040 | AI168: 39270 | AJ168: 41400 | AK168: 42670 | AL168: 43490 | AM168: 45260 | AN168: 46080 | AO168: 46080 | AP168: 45250 | AQ168: 44170 | AR168: 43820 | AS168: 43360 | AT168: 41980 | AU168: 41840 | AV168: 41210 | AW168: 42210 | AX168: 41890 | AY168: 41210 | AZ168: 41960 | BA168: 42990 | BB168: 43420 | BC168: 44380 | BD168: 47170 | BE168: 48960 | BF168: 49210 | BG168: 49870 | BH168: 49940 | BI168: 49980
A169: =$A$69 -> 54 | B169: 24750 | C169: 24910 | D169: 25610 | E169: 26170 | F169: 27170 | G169: 27700 | H169: 27670 | I169: 29030 | J169: 29500 | K169: 30660 | L169: 31700 | M169: 31980 | N169: 31840 | O169: 31080 | P169: 30850 | Q169: 30730 | R169: 31150 | S169: 31830 | T169: 31770 | U169: 32910 | V169: 32680 | W169: 31850 | X169: 31110 | Y169: 30150 | Z169: 30040 | AA169: 30470 | AB169: 30260 | AC169: 31650 | AD169: 32810 | AE169: 33830 | AF169: 34810 | AG169: 36260 | AH169: 37310 | AI169: 37940 | AJ169: 39170 | AK169: 41300 | AL169: 42570 | AM169: 43390 | AN169: 45160 | AO169: 45980 | AP169: 45980 | AQ169: 45160 | AR169: 44090 | AS169: 43740 | AT169: 43280 | AU169: 41900 | AV169: 41770 | AW169: 41140 | AX169: 42140 | AY169: 41830 | AZ169: 41150 | BA169: 41900 | BB169: 42930 | BC169: 43360 | BD169: 44320 | BE169: 47100 | BF169: 48900 | BG169: 49150 | BH169: 49810 | BI169: 49880
A170: =$A$70 -> 55 | B170: 24160 | C170: 24590 | D170: 24710 | E170: 25530 | F170: 26030 | G170: 26960 | H170: 27520 | I170: 27530 | J170: 29070 | K170: 29640 | L170: 30710 | M170: 31770 | N170: 32110 | O170: 31730 | P170: 31160 | Q170: 30680 | R170: 30450 | S170: 31030 | T170: 31630 | U170: 31630 | V170: 32780 | W170: 32560 | X170: 31740 | Y170: 31000 | Z170: 30060 | AA170: 29950 | AB170: 30390 | AC170: 30180 | AD170: 31560 | AE170: 32730 | AF170: 33750 | AG170: 34730 | AH170: 36180 | AI170: 37220 | AJ170: 37860 | AK170: 39080 | AL170: 41210 | AM170: 42480 | AN170: 43300 | AO170: 45070 | AP170: 45880 | AQ170: 45890 | AR170: 45070 | AS170: 44010 | AT170: 43660 | AU170: 43210 | AV170: 41840 | AW170: 41700 | AX170: 41080 | AY170: 42080 | AZ170: 41770 | BA170: 41090 | BB170: 41840 | BC170: 42880 | BD170: 43310 | BE170: 44270 | BF170: 47050 | BG170: 48850 | BH170: 49100 | BI170: 49760
A171: =$A$71 -> 56 | B171: 24180 | C171: 24100 | D171: 24450 | E171: 24570 | F171: 25410 | G171: 25870 | H171: 26760 | I171: 27380 | J171: 27590 | K171: 29150 | L171: 29730 | M171: 30730 | N171: 31810 | O171: 31970 | P171: 31770 | Q171: 30940 | R171: 30350 | S171: 30240 | T171: 30790 | U171: 31490 | V171: 31500 | W171: 32660 | X171: 32450 | Y171: 31640 | Z171: 30910 | AA171: 29970 | AB171: 29870 | AC171: 30310 | AD171: 30100 | AE171: 31480 | AF171: 32650 | AG171: 33670 | AH171: 34650 | AI171: 36090 | AJ171: 37130 | AK171: 37770 | AL171: 39000 | AM171: 41120 | AN171: 42390 | AO171: 43220 | AP171: 44980 | AQ171: 45800 | AR171: 45810 | AS171: 44990 | AT171: 43930 | AU171: 43590 | AV171: 43150 | AW171: 41780 | AX171: 41650 | AY171: 41030 | AZ171: 42030 | BA171: 41720 | BB171: 41050 | BC171: 41800 | BD171: 42830 | BE171: 43270 | BF171: 44220 | BG171: 47000 | BH171: 48800 | BI171: 49050
A172: =$A$72 -> 57 | B172: 23830 | C172: 24030 | D172: 23970 | E172: 24310 | F172: 24480 | G172: 25290 | H172: 25730 | I172: 26620 | J172: 27330 | K172: 27690 | L172: 29250 | M172: 29850 | N172: 30770 | O172: 31640 | P172: 32040 | Q172: 31570 | R172: 30630 | S172: 30150 | T172: 30020 | U172: 30660 | V172: 31370 | W172: 31390 | X172: 32550 | Y172: 32340 | Z172: 31540 | AA172: 30830 | AB172: 29890 | AC172: 29800 | AD172: 30230 | AE172: 30030 | AF172: 31410 | AG172: 32570 | AH172: 33590 | AI172: 34570 | AJ172: 36020 | AK172: 37060 | AL172: 37700 | AM172: 38930 | AN172: 41040 | AO172: 42310 | AP172: 43140 | AQ172: 44900 | AR172: 45720 | AS172: 45730 | AT172: 44920 | AU172: 43870 | AV172: 43530 | AW172: 43090 | AX172: 41720 | AY172: 41600 | AZ172: 40980 | BA172: 41990 | BB172: 41680 | BC172: 41010 | BD172: 41760 | BE172: 42790 | BF172: 43230 | BG172: 44190 | BH172: 46970 | BI172: 48760
A173: =$A$73 -> 58 | B173: 23890 | C173: 23710 | D173: 23900 | E173: 23870 | F173: 24240 | G173: 24350 | H173: 25160 | I173: 25610 | J173: 26590 | K173: 27240 | L173: 27750 | M173: 29280 | N173: 29880 | O173: 30660 | P173: 31700 | Q173: 31840 | R173: 31250 | S173: 30370 | T173: 29900 | U173: 29890 | V173: 30540 | W173: 31260 | X173: 31290 | Y173: 32450 | Z173: 32250 | AA173: 31460 | AB173: 30750 | AC173: 29820 | AD173: 29730 | AE173: 30160 | AF173: 29970 | AG173: 31350 | AH173: 32510 | AI173: 33530 | AJ173: 34500 | AK173: 35950 | AL173: 36990 | AM173: 37630 | AN173: 38860 | AO173: 40970 | AP173: 42240 | AQ173: 43070 | AR173: 44830 | AS173: 45640 | AT173: 45660 | AU173: 44860 | AV173: 43810 | AW173: 43470 | AX173: 43040 | AY173: 41680 | AZ173: 41560 | BA173: 40940 | BB173: 41950 | BC173: 41640 | BD173: 40980 | BE173: 41730 | BF173: 42760 | BG173: 43200 | BH173: 44160 | BI173: 46930
A174: =$A$74 -> 59 | B174: 24020 | C174: 23810 | D174: 23610 | E174: 23740 | F174: 23780 | G174: 24060 | H174: 24210 | I174: 25030 | J174: 25570 | K174: 26540 | L174: 27260 | M174: 27800 | N174: 29260 | O174: 29720 | P174: 30710 | Q174: 31470 | R174: 31510 | S174: 30970 | T174: 30130 | U174: 29780 | V174: 29780 | W174: 30440 | X174: 31160 | Y174: 31200 | Z174: 32360 | AA174: 32160 | AB174: 31380 | AC174: 30670 | AD174: 29760 | AE174: 29670 | AF174: 30110 | AG174: 29920 | AH174: 31290 | AI174: 32450 | AJ174: 33470 | AK174: 34450 | AL174: 35890 | AM174: 36930 | AN174: 37570 | AO174: 38800 | AP174: 40900 | AQ174: 42180 | AR174: 43000 | AS174: 44760 | AT174: 45580 | AU174: 45600 | AV174: 44800 | AW174: 43760 | AX174: 43430 | AY174: 42990 | AZ174: 41640 | BA174: 41520 | BB174: 40910 | BC174: 41920 | BD174: 41620 | BE174: 40960 | BF174: 41710 | BG174: 42740 | BH174: 43180 | BI174: 44140
A175: =$A$75 -> 60 | B175: 20160 | C175: 23860 | D175: 23690 | E175: 23510 | F175: 23680 | G175: 23700 | H175: 23950 | I175: 24120 | J175: 24970 | K175: 25620 | L175: 26540 | M175: 27210 | N175: 27840 | O175: 29140 | P175: 29740 | Q175: 30510 | R175: 31170 | S175: 31200 | T175: 30730 | U175: 30000 | V175: 29660 | W175: 29680 | X175: 30340 | Y175: 31070 | Z175: 31110 | AA175: 32270 | AB175: 32080 | AC175: 31300 | AD175: 30600 | AE175: 29690 | AF175: 29610 | AG175: 30050 | AH175: 29860 | AI175: 31240 | AJ175: 32390 | AK175: 33410 | AL175: 34390 | AM175: 35830 | AN175: 36870 | AO175: 37510 | AP175: 38740 | AQ175: 40840 | AR175: 42110 | AS175: 42940 | AT175: 44690 | AU175: 45510 | AV175: 45530 | AW175: 44740 | AX175: 43710 | AY175: 43380 | AZ175: 42950 | BA175: 41610 | BB175: 41490 | BC175: 40890 | BD175: 41890 | BE175: 41590 | BF175: 40940 | BG175: 41690 | BH175: 42730 | BI175: 43170
A176: =$A$76 -> 61 | B176: 19140 | C176: 20030 | D176: 23700 | E176: 23550 | F176: 23420 | G176: 23540 | H176: 23580 | I176: 23850 | J176: 24110 | K176: 24960 | L176: 25640 | M176: 26510 | N176: 27110 | O176: 27720 | P176: 29200 | Q176: 29490 | R176: 30290 | S176: 30880 | T176: 30950 | U176: 30590 | V176: 29880 | W176: 29560 | X176: 29580 | Y176: 30240 | Z176: 30970 | AA176: 31020 | AB176: 32180 | AC176: 31990 | AD176: 31230 | AE176: 30540 | AF176: 29640 | AG176: 29560 | AH176: 30000 | AI176: 29820 | AJ176: 31180 | AK176: 32340 | AL176: 33360 | AM176: 34330 | AN176: 35770 | AO176: 36810 | AP176: 37460 | AQ176: 38680 | AR176: 40780 | AS176: 42050 | AT176: 42870 | AU176: 44630 | AV176: 45450 | AW176: 45470 | AX176: 44690 | AY176: 43660 | AZ176: 43340 | BA176: 42910 | BB176: 41580 | BC176: 41460 | BD176: 40870 | BE176: 41870 | BF176: 41580 | BG176: 40920 | BH176: 41680 | BI176: 42710
A177: =$A$77 -> 62 | B177: 18400 | C177: 19020 | D177: 19890 | E177: 23560 | F177: 23450 | G177: 23330 | H177: 23410 | I177: 23520 | J177: 23840 | K177: 24130 | L177: 24930 | M177: 25610 | N177: 26400 | O177: 27010 | P177: 27840 | Q177: 28820 | R177: 29080 | S177: 30090 | T177: 30610 | U177: 30800 | V177: 30460 | W177: 29770 | X177: 29450 | Y177: 29480 | Z177: 30150 | AA177: 30880 | AB177: 30930 | AC177: 32090 | AD177: 31910 | AE177: 31150 | AF177: 30470 | AG177: 29580 | AH177: 29500 | AI177: 29940 | AJ177: 29770 | AK177: 31130 | AL177: 32290 | AM177: 33300 | AN177: 34280 | AO177: 35710 | AP177: 36750 | AQ177: 37400 | AR177: 38620 | AS177: 40720 | AT177: 41980 | AU177: 42810 | AV177: 44560 | AW177: 45380 | AX177: 45410 | AY177: 44640 | AZ177: 43610 | BA177: 43300 | BB177: 42880 | BC177: 41550 | BD177: 41440 | BE177: 40840 | BF177: 41850 | BG177: 41560 | BH177: 40910 | BI177: 41670
A178: =$A$78 -> 63 | B178: 16270 | C178: 18230 | D178: 18890 | E178: 19760 | F178: 23410 | G178: 23320 | H178: 23240 | I178: 23270 | J178: 23440 | K178: 23800 | L178: 24090 | M178: 24890 | N178: 25430 | O178: 26250 | P178: 27090 | Q178: 27570 | R178: 28500 | S178: 28780 | T178: 29840 | U178: 30450 | V178: 30660 | W178: 30330 | X178: 29650 | Y178: 29340 | Z178: 29380 | AA178: 30050 | AB178: 30780 | AC178: 30840 | AD178: 31990 | AE178: 31820 | AF178: 31070 | AG178: 30390 | AH178: 29510 | AI178: 29440 | AJ178: 29880 | AK178: 29710 | AL178: 31080 | AM178: 32230 | AN178: 33240 | AO178: 34220 | AP178: 35650 | AQ178: 36690 | AR178: 37340 | AS178: 38560 | AT178: 40650 | AU178: 41910 | AV178: 42740 | AW178: 44490 | AX178: 45310 | AY178: 45350 | AZ178: 44580 | BA178: 43560 | BB178: 43250 | BC178: 42830 | BD178: 41510 | BE178: 41410 | BF178: 40820 | BG178: 41820 | BH178: 41540 | BI178: 40900
A179: =$A$79 -> 64 | B179: 17930 | C179: 16110 | D179: 18080 | E179: 18740 | F179: 19670 | G179: 23280 | H179: 23190 | I179: 23140 | J179: 23170 | K179: 23360 | L179: 23780 | M179: 24050 | N179: 24810 | O179: 25410 | P179: 26340 | Q179: 26810 | R179: 27210 | S179: 28200 | T179: 28500 | U179: 29660 | V179: 30280 | W179: 30500 | X179: 30180 | Y179: 29520 | Z179: 29220 | AA179: 29260 | AB179: 29930 | AC179: 30670 | AD179: 30720 | AE179: 31880 | AF179: 31710 | AG179: 30970 | AH179: 30310 | AI179: 29430 | AJ179: 29370 | AK179: 29810 | AL179: 29640 | AM179: 31000 | AN179: 32150 | AO179: 33170 | AP179: 34140 | AQ179: 35570 | AR179: 36610 | AS179: 37260 | AT179: 38480 | AU179: 40560 | AV179: 41830 | AW179: 42660 | AX179: 44400 | AY179: 45230 | AZ179: 45260 | BA179: 44500 | BB179: 43490 | BC179: 43190 | BD179: 42780 | BE179: 41470 | BF179: 41360 | BG179: 40780 | BH179: 41780 | BI179: 41500
A180: =$A$80 -> 65 | B180: 17660 | C180: 17780 | D180: 15980 | E180: 17930 | F180: 18590 | G180: 19590 | H180: 23200 | I180: 23070 | J180: 23060 | K180: 23100 | L180: 23280 | M180: 23710 | N180: 24020 | O180: 24660 | P180: 25540 | Q180: 26000 | R180: 26450 | S180: 26960 | T180: 27950 | U180: 28310 | V180: 29480 | W180: 30110 | X180: 30330 | Y180: 30020 | Z180: 29370 | AA180: 29080 | AB180: 29130 | AC180: 29800 | AD180: 30530 | AE180: 30600 | AF180: 31750 | AG180: 31590 | AH180: 30860 | AI180: 30200 | AJ180: 29340 | AK180: 29270 | AL180: 29720 | AM180: 29560 | AN180: 30920 | AO180: 32060 | AP180: 33080 | AQ180: 34050 | AR180: 35480 | AS180: 36510 | AT180: 37160 | AU180: 38380 | AV180: 40460 | AW180: 41730 | AX180: 42560 | AY180: 44300 | AZ180: 45120 | BA180: 45160 | BB180: 44410 | BC180: 43410 | BD180: 43110 | BE180: 42700 | BF180: 41400 | BG180: 41300 | BH180: 40720 | BI180: 41730
A181: =$A$81 -> 66 | B181: 16280 | C181: 17430 | D181: 17580 | E181: 15830 | F181: 17790 | G181: 18420 | H181: 19390 | I181: 23050 | J181: 22850 | K181: 22840 | L181: 22960 | M181: 23100 | N181: 23520 | O181: 23790 | P181: 24690 | Q181: 25160 | R181: 25550 | S181: 26120 | T181: 26680 | U181: 27740 | V181: 28110 | W181: 29280 | X181: 29910 | Y181: 30140 | Z181: 29850 | AA181: 29200 | AB181: 28930 | AC181: 28980 | AD181: 29650 | AE181: 30380 | AF181: 30450 | AG181: 31600 | AH181: 31450 | AI181: 30720 | AJ181: 30080 | AK181: 29220 | AL181: 29170 | AM181: 29620 | AN181: 29460 | AO181: 30810 | AP181: 31960 | AQ181: 32970 | AR181: 33940 | AS181: 35370 | AT181: 36400 | AU181: 37050 | AV181: 38270 | AW181: 40340 | AX181: 41600 | AY181: 42440 | AZ181: 44170 | BA181: 45000 | BB181: 45050 | BC181: 44300 | BD181: 43310 | BE181: 43010 | BF181: 42610 | BG181: 41320 | BH181: 41230 | BI181: 40650
A182: =$A$82 -> 67 | B182: 14490 | C182: 16080 | D182: 17200 | E182: 17370 | F182: 15630 | G182: 17630 | H182: 18190 | I182: 19250 | J182: 22790 | K182: 22630 | L182: 22650 | M182: 22790 | N182: 22870 | O182: 23280 | P182: 23690 | Q182: 24320 | R182: 24630 | S182: 25230 | T182: 25770 | U182: 26450 | V182: 27520 | W182: 27890 | X182: 29060 | Y182: 29690 | Z182: 29930 | AA182: 29640 | AB182: 29010 | AC182: 28740 | AD182: 28800 | AE182: 29470 | AF182: 30200 | AG182: 30280 | AH182: 31420 | AI182: 31270 | AJ182: 30570 | AK182: 29930 | AL182: 29090 | AM182: 29030 | AN182: 29480 | AO182: 29330 | AP182: 30680 | AQ182: 31820 | AR182: 32840 | AS182: 33810 | AT182: 35230 | AU182: 36260 | AV182: 36910 | AW182: 38130 | AX182: 40190 | AY182: 41450 | AZ182: 42280 | BA182: 44020 | BB182: 44850 | BC182: 44900 | BD182: 44160 | BE182: 43180 | BF182: 42890 | BG182: 42490 | BH182: 41210 | BI182: 41120
A183: =$A$83 -> 68 | B183: 13990 | C183: 14260 | D183: 15840 | E183: 16980 | F183: 17180 | G183: 15460 | H183: 17420 | I183: 18010 | J183: 19040 | K183: 22450 | L183: 22440 | M183: 22410 | N183: 22540 | O183: 22590 | P183: 23180 | Q183: 23260 | R183: 23900 | S183: 24330 | T183: 24920 | U183: 25520 | V183: 26200 | W183: 27260 | X183: 27640 | Y183: 28800 | Z183: 29440 | AA183: 29680 | AB183: 29410 | AC183: 28790 | AD183: 28530 | AE183: 28590 | AF183: 29260 | AG183: 29990 | AH183: 30070 | AI183: 31220 | AJ183: 31070 | AK183: 30380 | AL183: 29750 | AM183: 28920 | AN183: 28870 | AO183: 29320 | AP183: 29180 | AQ183: 30520 | AR183: 31660 | AS183: 32670 | AT183: 33640 | AU183: 35060 | AV183: 36090 | AW183: 36740 | AX183: 37950 | AY183: 40010 | AZ183: 41270 | BA183: 42100 | BB183: 43830 | BC183: 44660 | BD183: 44720 | BE183: 43990 | BF183: 43020 | BG183: 42730 | BH183: 42350 | BI183: 41070
A184: =$A$84 -> 69 | B184: 13200 | C184: 13760 | D184: 14020 | E184: 15590 | F184: 16690 | G184: 16960 | H184: 15240 | I184: 17190 | J184: 17730 | K184: 18770 | L184: 22160 | M184: 22100 | N184: 22140 | O184: 22240 | P184: 22510 | Q184: 22710 | R184: 22730 | S184: 23480 | T184: 23950 | U184: 24640 | V184: 25240 | W184: 25930 | X184: 26980 | Y184: 27370 | Z184: 28520 | AA184: 29160 | AB184: 29410 | AC184: 29140 | AD184: 28540 | AE184: 28290 | AF184: 28360 | AG184: 29030 | AH184: 29760 | AI184: 29840 | AJ184: 30980 | AK184: 30850 | AL184: 30160 | AM184: 29540 | AN184: 28730 | AO184: 28690 | AP184: 29140 | AQ184: 29000 | AR184: 30340 | AS184: 31470 | AT184: 32480 | AU184: 33450 | AV184: 34860 | AW184: 35890 | AX184: 36540 | AY184: 37750 | AZ184: 39800 | BA184: 41060 | BB184: 41890 | BC184: 43620 | BD184: 44450 | BE184: 44510 | BF184: 43790 | BG184: 42830 | BH184: 42550 | BI184: 42170
...

Sheet Population Treasury
A1: RESIDENT POPULATION OF NEW ZEALAND, BY SINGLE YEAR OF AGE AND GENDER, AS AT 30 JUNE, THAT MATCHES HOUSEHOLD LABOUR FORCE SURVEY (HLFS) HISTORY AND TREASURY"S HLFS-BASED FORECASTS
A2: Year ended 30 June | B2: 2005/06 | C2: 2006/07 | D2: 2007/08 | E2: 2008/09 | F2: 2009/10 | G2: 2010/11 | H2: 2011/12 | I2: 2012/13 | J2: 2013/14 | K2: 2014/15 | L2: 2015/16 | M2: 2016/17 | N2: 2017/18 | O2: 2018/19 | P2: 2019/20 | Q2: 2020/21 | R2: 2021/22 | S2: 2022/23 | T2: 2023/24 | U2: 2024/25 | V2: 2025/26 | W2: 2026/27 | X2: 2027/28 | Y2: 2028/29 | Z2: 2029/30 | AA2: 2030/31 | AB2: 2031/32 | AC2: 2032/33 | AD2: 2033/34 | AE2: 2034/35 | AF2: 2035/36 | AG2: 2036/37 | AH2: 2037/38 | AI2: 2038/39 | AJ2: 2039/40 | AK2: 2040/41 | AL2: 2041/42 | AM2: 2042/43 | AN2: 2043/44 | AO2: 2044/45 | AP2: 2045/46 | AQ2: 2046/47 | AR2: 2047/48 | AS2: 2048/49 | AT2: 2049/50 | AU2: 2050/51 | AV2: 2051/52 | AW2: 2052/53 | AX2: 2053/54 | AY2: 2054/55 | AZ2: 2055/56 | BA2: 2056/57 | BB2: 2057/58 | BC2: 2058/59 | BD2: 2059/60 | BE2: 2060/61 | BF2: 2061/62 | BG2: 2062/63 | BH2: 2063/64 | BI2: 2064/65
B3: 2006 | C3: 2007 | D3: 2008 | E3: 2009 | F3: 2010 | G3: 2011 | H3: 2012 | I3: 2013 | J3: 2014 | K3: 2015 | L3: 2016 | M3: 2017 | N3: 2018 | O3: 2019 | P3: 2020 | Q3: 2021 | R3: 2022 | S3: 2023 | T3: 2024 | U3: 2025 | V3: 2026 | W3: 2027 | X3: 2028 | Y3: 2029 | Z3: 2030 | AA3: 2031 | AB3: 2032 | AC3: 2033 | AD3: 2034 | AE3: 2035 | AF3: 2036 | AG3: 2037 | AH3: 2038 | AI3: 2039 | AJ3: 2040 | AK3: 2041 | AL3: 2042 | AM3: 2043 | AN3: 2044 | AO3: 2045 | AP3: 2046 | AQ3: 2047 | AR3: 2048 | AS3: 2049 | AT3: 2050 | AU3: 2051 | AV3: 2052 | AW3: 2053 | AX3: 2054 | AY3: 2055 | AZ3: 2056 | BA3: 2057 | BB3: 2058 | BC3: 2059 | BD3: 2060 | BE3: 2061 | BF3: 2062 | BG3: 2063 | BH3: 2064 | BI3: 2065
A4: Population (millions) | B4: =SUM(B$15:B$110,B$115:B$210)/1000000 -> 4.1669 | C4: =SUM(C$15:C$110,C$115:C$210)/1000000 -> 4.212 | D4: =SUM(D$15:D$110,D$115:D$210)/1000000 -> 4.2489 | E4: =SUM(E$15:E$110,E$115:E$210)/1000000 -> 4.2865 | F4: =SUM(F$15:F$110,F$115:F$210)/1000000 -> 4.3365 | G4: =SUM(G$15:G$110,G$115:G$210)/1000000 -> 4.3758 | H4: =SUM(H$15:H$110,H$115:H$210)/1000000 -> 4.4015 | I4: =SUM(I$15:I$110,I$115:I$210)/1000000 -> 4.4299 | ... BI4: =SUM(BI$15:BI$110,BI$115:BI$210)/1000000 -> 7.36473
A5: Annual growth (%) | C5: =C$4/B$4-1 -> 0.010823394 | D5: =D$4/C$4-1 -> 0.0087606838 | E5: =E$4/D$4-1 -> 0.0088493492 | F5: =F$4/E$4-1 -> 0.011664528 | G5: =G$4/F$4-1 -> 0.0090626081 | H5: =H$4/G$4-1 -> 0.0058732118 | I5: =I$4/H$4-1 -> 0.0064523458 | J5: =J$4/I$4-1 -> 0.013160568 | ... BI5: =BI$4/BH$4-1 -> 0.0059292586
A6: Working-age popn (15+, millions) | B6: =SUM(B$30:B$110,B$130:B$210)/1000000 -> 3.2251 | C6: =SUM(C$30:C$110,C$130:C$210)/1000000 -> 3.2726 | D6: =SUM(D$30:D$110,D$130:D$210)/1000000 -> 3.3046 | E6: =SUM(E$30:E$110,E$130:E$210)/1000000 -> 3.3358 | F6: =SUM(F$30:F$110,F$130:F$210)/1000000 -> 3.3767 | G6: =SUM(G$30:G$110,G$130:G$210)/1000000 -> 3.4116 | H6: =SUM(H$30:H$110,H$130:H$210)/1000000 -> 3.437 | I6: =SUM(I$30:I$110,I$130:I$210)/1000000 -> 3.4639 | ... BI6: =SUM(BI$30:BI$110,BI$130:BI$210)/1000000 -> 6.2615748
A7: Minors' popn (0-14, millions) | B7: =SUM(B$15:B$29,B$115:B$129)/1000000 -> 0.9418 | C7: =SUM(C$15:C$29,C$115:C$129)/1000000 -> 0.9394 | D7: =SUM(D$15:D$29,D$115:D$129)/1000000 -> 0.9443 | E7: =SUM(E$15:E$29,E$115:E$129)/1000000 -> 0.9507 | F7: =SUM(F$15:F$29,F$115:F$129)/1000000 -> 0.9598 | G7: =SUM(G$15:G$29,G$115:G$129)/1000000 -> 0.9642 | H7: =SUM(H$15:H$29,H$115:H$129)/1000000 -> 0.9645 | I7: =SUM(I$15:I$29,I$115:I$129)/1000000 -> 0.966 | ... BI7: =SUM(BI$15:BI$29,BI$115:BI$129)/1000000 -> 1.1031552
A8: Net Migration (thousands) - Treasury | U8: ='Economic Forecasts'!W$17 -> 32.9 | V8: ='Economic Forecasts'!X$17 -> 38.2 | W8: ='Economic Forecasts'!Y$17 -> 39.5 | X8: ='Economic Forecasts'!Z$17 -> 39.9 | Y8: ='Economic Forecasts'!AA$17 -> 40 | Z8: =MAX(Y$8-0.5,Z$9) -> 39.5 | AA8: =MAX(Z$8-0.5,AA$9) -> 39 | AB8: =MAX(AA$8-0.5,AB$9) -> 38.5 | AC8: =MAX(AB$8-0.5,AC$9) -> 38 | AD8: =MAX(AC$8-0.5,AD$9) -> 38.3 | AE8: =MAX(AD$8-0.5,AE$9) -> 38.5 | AF8: =MAX(AE$8-0.5,AF$9) -> 38.8 | AG8: =MAX(AF$8-0.5,AG$9) -> 39 | ... BI8: =MAX(BH$8-0.5,BI$9) -> 46
A9: Net Migration (thousands) - Statistics NZ | U9: 25 | V9: 30 | W9: 32.5 | X9: 34.5 | Y9: 36 | Z9: 37 | AA9: =Z9+0.5 -> 37.5 | AB9: =AA9+0.3 -> 37.8 | AC9: =AB9+0.2 -> 38 | AD9: =AC9+0.3 -> 38.3 | AE9: =AD9+0.2 -> 38.5 | AF9: =AE9+0.3 -> 38.8 | AG9: =AF9+0.2 -> 39 | AH9: =AG9+0.3 -> 39.3 | AI9: =AH9+0.2 -> 39.5 | AJ9: =AI9+0.3 -> 39.8 | AK9: =AJ9+0.2 -> 40 | AL9: =AK9+0.3 -> 40.3 | AM9: =AL9+0.2 -> 40.5 | AN9: =AM9+0.3 -> 40.8 | AO9: =AN9+0.2 -> 41 | AP9: =AO9+0.3 -> 41.3 | AQ9: =AP9+0.2 -> 41.5 | AR9: =AQ9+0.3 -> 41.8 | AS9: =AR9+0.2 -> 42 | AT9: =AS9+0.3 -> 42.3 | AU9: =AT9+0.2 -> 42.5 | AV9: =AU9+0.3 -> 42.8 | AW9: =AV9+0.2 -> 43 | AX9: =AW9+0.3 -> 43.3 | AY9: =AX9+0.2 -> 43.5 | AZ9: =AY9+0.3 -> 43.8 | BA9: =AZ9+0.2 -> 44 | BB9: =BA9+0.3 -> 44.3 | BC9: =BB9+0.2 -> 44.5 | BD9: =BC9+0.3 -> 44.8 | BE9: =BD9+0.2 -> 45 | BF9: =BE9+0.3 -> 45.3 | BG9: =BF9+0.2 -> 45.5 | BH9: =BG9+0.3 -> 45.8 | BI9: =BH9+0.2 -> 46
A10: Net Migration by age and gender group (percentages are based on June-end years between 2001/02 and 2022/23, where net migration was at least 10,000)
A11: Age Group (years) | B11: 0 to 4 | C11: 5 to 9 | D11: 10 to 14 | E11: 15 to 19 | F11: 20 to 24 | G11: 25 to 29 | H11: 30 to 34 | I11: 35 to 39 | J11: 40 to 44 | K11: 45 to 49 | L11: 50 to 54 | M11: 55 to 59 | N11: 60 to 64 | O11: 65 to 69 | P11: 70 to 74 | Q11: 75 to 79 | R11: 80 to 84 | S11: 85 to 89 | T11: 90 & over | U11: TOTAL
A12: Female | B12: 0.026425591 | C12: 0.041234733 | D12: 0.04015632 | E12: 0.055410759 | F12: -0.0070268329 | G12: 0.099773874 | H12: 0.10249018 | I12: 0.064931741 | J12: 0.036680817 | K12: 0.0096258135 | L12: 0.0025606803 | M12: 0.01051327 | N12: 0.0153957 | O12: 0.0078155333 | P12: 0.0031598032 | Q12: 0.0017419225 | R12: 0.00095729348 | S12: 0.00031786944 | T12: 0.0003014299 | U12: =SUM($B$12:$T$12) -> 0.5124665
A13: Male | B13: 0.030037309 | C13: 0.044282169 | D13: 0.042377857 | E13: 0.068621463 | F13: -0.010238044 | G13: 0.04588582 | H13: 0.093818368 | I13: 0.07100718 | J13: 0.046829162 | K13: 0.018292934 | L13: 0.0041365914 | M13: 0.0045830699 | N13: 0.012758722 | O13: 0.0088155106 | P13: 0.0035659477 | Q13: 0.0016009593 | R13: 0.00048177268 | S13: 0.00038055896 | T13: 0.0002994967 | U13: =SUM($B$13:$T$13) -> 0.48753685
A14: FEMALE POPULATION
A15: 0 | B15: ='Statistics NZ'!B$15*('Economic Forecasts'!D$10-'Economic Forecasts'!D$9)*1000000/SUM('Statistics NZ'!B$15:B$29,'Statistics NZ'!B$115:B$129) -> 30650.829 | C15: ='Statistics NZ'!C$15*('Economic Forecasts'!E$10-'Economic Forecasts'!E$9)*1000000/SUM('Statistics NZ'!C$15:C$29,'Statistics NZ'!C$115:C$129) -> 31861.396 | D15: ='Statistics NZ'!D$15*('Economic Forecasts'!F$10-'Economic Forecasts'!F$9)*1000000/SUM('Statistics NZ'!D$15:D$29,'Statistics NZ'!D$115:D$129) -> 33068.584 | E15: ='Statistics NZ'!E$15*('Economic Forecasts'!G$10-'Economic Forecasts'!G$9)*1000000/SUM('Statistics NZ'!E$15:E$29,'Statistics NZ'!E$115:E$129) -> 32524.836 | F15: ='Statistics NZ'!F$15*('Economic Forecasts'!H$10-'Economic Forecasts'!H$9)*1000000/SUM('Statistics NZ'!F$15:F$29,'Statistics NZ'!F$115:F$129) -> 33302.462 | G15: ='Statistics NZ'!G$15*('Economic Forecasts'!I$10-'Economic Forecasts'!I$9)*1000000/SUM('Statistics NZ'!G$15:G$29,'Statistics NZ'!G$115:G$129) -> 32471.384 | H15: ='Statistics NZ'!H$15*('Economic Forecasts'!J$10-'Economic Forecasts'!J$9)*1000000/SUM('Statistics NZ'!H$15:H$29,'Statistics NZ'!H$115:H$129) -> 31676.13 | I15: ='Statistics NZ'!I$15*('Economic Forecasts'!K$10-'Economic Forecasts'!K$9)*1000000/SUM('Statistics NZ'!I$15:I$29,'Statistics NZ'!I$115:I$129) -> 31218.895 | ... T15: ='Statistics NZ'!T$15*('Economic Forecasts'!V$10-'Economic Forecasts'!V$9)*1000000/SUM('Statistics NZ'!T$15:T$29,'Statistics NZ'!T$115:T$129) -> 29554.175 | U15: =SUM('Statistics NZ'!U$15,$B$12/5*(U$8-U$9)*1000)*('Economic Forecasts'!W$10-'Economic Forecasts'!W$9)*1000000/SUM('Statistics NZ'!U$15:U$29,'Statistics NZ'!U$115:U$129,SUM($B$12:$D$13)*(U$8-U$9)*1000) -> 30145.243 | V15: =SUM('Statistics NZ'!V$15,$B$12/5*(V$8-V$9)*1000)*('Economic Forecasts'!X$10-'Economic Forecasts'!X$9)*1000000/SUM('Statistics NZ'!V$15:V$29,'Statistics NZ'!V$115:V$129,SUM($B$12:$D$13)*(V$8-V$9)*1000) -> 30501.17 | W15: =SUM('Statistics NZ'!W$15,$B$12/5*(W$8-W$9)*1000)*('Economic Forecasts'!Y$10-'Economic Forecasts'!Y$9)*1000000/SUM('Statistics NZ'!W$15:W$29,'Statistics NZ'!W$115:W$129,SUM($B$12:$D$13)*(W$8-W$9)*1000) -> 30881.159 | X15: =SUM('Statistics NZ'!X$15,$B$12/5*(X$8-X$9)*1000)*('Economic Forecasts'!Z$10-'Economic Forecasts'!Z$9)*1000000/SUM('Statistics NZ'!X$15:X$29,'Statistics NZ'!X$115:X$129,SUM($B$12:$D$13)*(X$8-X$9)*1000) -> 31254.297 | Y15: =SUM('Statistics NZ'!Y$15,$B$12/5*(Y$8-Y$9)*1000)*('Economic Forecasts'!AA$10-'Economic Forecasts'!AA$9)*1000000/SUM('Statistics NZ'!Y$15:Y$29,'Statistics NZ'!Y$115:Y$129,SUM($B$12:$D$13)*(Y$8-Y$9)*1000) -> 31579.403 | Z15: =SUM(Y$15,'Statistics NZ'!Z$15-'Statistics NZ'!Y$15,$B$12/5*(Z$8-Z$9)*1000) -> 31582.616 | AA15: =SUM(Z$15,'Statistics NZ'!AA$15-'Statistics NZ'!Z$15,$B$12/5*(AA$8-AA$9)*1000) -> 31600.544 | AB15: =SUM(AA$15,'Statistics NZ'!AB$15-'Statistics NZ'!AA$15,$B$12/5*(AB$8-AB$9)*1000) -> 31624.243 | AC15: =SUM(AB$15,'Statistics NZ'!AC$15-'Statistics NZ'!AB$15,$B$12/5*(AC$8-AC$9)*1000) -> 31674.243 | AD15: =SUM(AC$15,'Statistics NZ'!AD$15-'Statistics NZ'!AC$15,$B$12/5*(AD$8-AD$9)*1000) -> 31754.243 | AE15: =SUM(AD$15,'Statistics NZ'!AE$15-'Statistics NZ'!AD$15,$B$12/5*(AE$8-AE$9)*1000) -> 31874.243 | AF15: =SUM(AE$15,'Statistics NZ'!AF$15-'Statistics NZ'!AE$15,$B$12/5*(AF$8-AF$9)*1000) -> 32034.243 | AG15: =SUM(AF$15,'Statistics NZ'!AG$15-'Statistics NZ'!AF$15,$B$12/5*(AG$8-AG$9)*1000) -> 32214.243 | ... BI15: =SUM(BH$15,'Statistics NZ'!BI$15-'Statistics NZ'!BH$15,$B$12/5*(BI$8-BI$9)*1000) -> 33714.243
A16: 1 | B16: ='Statistics NZ'!B$16*('Economic Forecasts'!D$10-'Economic Forecasts'!D$9)*1000000/SUM('Statistics NZ'!B$15:B$29,'Statistics NZ'!B$115:B$129) -> 29675.431 | C16: ='Statistics NZ'!C$16*('Economic Forecasts'!E$10-'Economic Forecasts'!E$9)*1000000/SUM('Statistics NZ'!C$15:C$29,'Statistics NZ'!C$115:C$129) -> 30406.922 | D16: ='Statistics NZ'!D$16*('Economic Forecasts'!F$10-'Economic Forecasts'!F$9)*1000000/SUM('Statistics NZ'!D$15:D$29,'Statistics NZ'!D$115:D$129) -> 31750.481 | E16: ='Statistics NZ'!E$16*('Economic Forecasts'!G$10-'Economic Forecasts'!G$9)*1000000/SUM('Statistics NZ'!E$15:E$29,'Statistics NZ'!E$115:E$129) -> 32978.474 | F16: ='Statistics NZ'!F$16*('Economic Forecasts'!H$10-'Economic Forecasts'!H$9)*1000000/SUM('Statistics NZ'!F$15:F$29,'Statistics NZ'!F$115:F$129) -> 32573.211 | G16: ='Statistics NZ'!G$16*('Economic Forecasts'!I$10-'Economic Forecasts'!I$9)*1000000/SUM('Statistics NZ'!G$15:G$29,'Statistics NZ'!G$115:G$129) -> 33307.784 | H16: ='Statistics NZ'!H$16*('Economic Forecasts'!J$10-'Economic Forecasts'!J$9)*1000000/SUM('Statistics NZ'!H$15:H$29,'Statistics NZ'!H$115:H$129) -> 32481.815 | I16: ='Statistics NZ'!I$16*('Economic Forecasts'!K$10-'Economic Forecasts'!K$9)*1000000/SUM('Statistics NZ'!I$15:I$29,'Statistics NZ'!I$115:I$129) -> 31835.408 | ... T16: ='Statistics NZ'!T$16*('Economic Forecasts'!V$10-'Economic Forecasts'!V$9)*1000000/SUM('Statistics NZ'!T$15:T$29,'Statistics NZ'!T$115:T$129) -> 29437.318 | U16: =SUM('Statistics NZ'!U$16,$B$12/5*(U$8-U$9)*1000)*('Economic Forecasts'!W$10-'Economic Forecasts'!W$9)*1000000/SUM('Statistics NZ'!U$15:U$29,'Statistics NZ'!U$115:U$129,SUM($B$12:$D$13)*(U$8-U$9)*1000) -> 29623.695 | V16: =SUM('Statistics NZ'!V$16,$B$12/5*(V$8-V$9)*1000)*('Economic Forecasts'!X$10-'Economic Forecasts'!X$9)*1000000/SUM('Statistics NZ'!V$15:V$29,'Statistics NZ'!V$115:V$129,SUM($B$12:$D$13)*(V$8-V$9)*1000) -> 30490.404 | W16: =SUM('Statistics NZ'!W$16,$B$12/5*(W$8-W$9)*1000)*('Economic Forecasts'!Y$10-'Economic Forecasts'!Y$9)*1000000/SUM('Statistics NZ'!W$15:W$29,'Statistics NZ'!W$115:W$129,SUM($B$12:$D$13)*(W$8-W$9)*1000) -> 30902.97 | X16: =SUM('Statistics NZ'!X$16,$B$12/5*(X$8-X$9)*1000)*('Economic Forecasts'!Z$10-'Economic Forecasts'!Z$9)*1000000/SUM('Statistics NZ'!X$15:X$29,'Statistics NZ'!X$115:X$129,SUM($B$12:$D$13)*(X$8-X$9)*1000) -> 31298.475 | Y16: =SUM('Statistics NZ'!Y$16,$B$12/5*(Y$8-Y$9)*1000)*('Economic Forecasts'!AA$10-'Economic Forecasts'!AA$9)*1000000/SUM('Statistics NZ'!Y$15:Y$29,'Statistics NZ'!Y$115:Y$129,SUM($B$12:$D$13)*(Y$8-Y$9)*1000) -> 31635.254 | Z16: =SUM(Y$16,'Statistics NZ'!Z$16-'Statistics NZ'!Y$16,$B$12/5*(Z$8-Z$9)*1000) -> 31638.467 | AA16: =SUM(Z$16,'Statistics NZ'!AA$16-'Statistics NZ'!Z$16,$B$12/5*(AA$8-AA$9)*1000) -> 31646.395 | AB16: =SUM(AA$16,'Statistics NZ'!AB$16-'Statistics NZ'!AA$16,$B$12/5*(AB$8-AB$9)*1000) -> 31650.094 | AC16: =SUM(AB$16,'Statistics NZ'!AC$16-'Statistics NZ'!AB$16,$B$12/5*(AC$8-AC$9)*1000) -> 31680.094 | AD16: =SUM(AC$16,'Statistics NZ'!AD$16-'Statistics NZ'!AC$16,$B$12/5*(AD$8-AD$9)*1000) -> 31730.094 | AE16: =SUM(AD$16,'Statistics NZ'!AE$16-'Statistics NZ'!AD$16,$B$12/5*(AE$8-AE$9)*1000) -> 31810.094 | AF16: =SUM(AE$16,'Statistics NZ'!AF$16-'Statistics NZ'!AE$16,$B$12/5*(AF$8-AF$9)*1000) -> 31930.094 | AG16: =SUM(AF$16,'Statistics NZ'!AG$16-'Statistics NZ'!AF$16,$B$12/5*(AG$8-AG$9)*1000) -> 32090.094 | ... BI16: =SUM(BH$16,'Statistics NZ'!BI$16-'Statistics NZ'!BH$16,$B$12/5*(BI$8-BI$9)*1000) -> 33710.094
A17: 2 | B17: ='Statistics NZ'!B$17*('Economic Forecasts'!D$10-'Economic Forecasts'!D$9)*1000000/SUM('Statistics NZ'!B$15:B$29,'Statistics NZ'!B$115:B$129) -> 29876.872 | C17: ='Statistics NZ'!C$17*('Economic Forecasts'!E$10-'Economic Forecasts'!E$9)*1000000/SUM('Statistics NZ'!C$15:C$29,'Statistics NZ'!C$115:C$129) -> 29616.448 | D17: ='Statistics NZ'!D$17*('Economic Forecasts'!F$10-'Economic Forecasts'!F$9)*1000000/SUM('Statistics NZ'!D$15:D$29,'Statistics NZ'!D$115:D$129) -> 30442.922 | E17: ='Statistics NZ'!E$17*('Economic Forecasts'!G$10-'Economic Forecasts'!G$9)*1000000/SUM('Statistics NZ'!E$15:E$29,'Statistics NZ'!E$115:E$129) -> 31881.302 | F17: ='Statistics NZ'!F$17*('Economic Forecasts'!H$10-'Economic Forecasts'!H$9)*1000000/SUM('Statistics NZ'!F$15:F$29,'Statistics NZ'!F$115:F$129) -> 33122.792 | G17: ='Statistics NZ'!G$17*('Economic Forecasts'!I$10-'Economic Forecasts'!I$9)*1000000/SUM('Statistics NZ'!G$15:G$29,'Statistics NZ'!G$115:G$129) -> 32577.257 | H17: ='Statistics NZ'!H$17*('Economic Forecasts'!J$10-'Economic Forecasts'!J$9)*1000000/SUM('Statistics NZ'!H$15:H$29,'Statistics NZ'!H$115:H$129) -> 33192.09 | I17: ='Statistics NZ'!I$17*('Economic Forecasts'!K$10-'Economic Forecasts'!K$9)*1000000/SUM('Statistics NZ'!I$15:I$29,'Statistics NZ'!I$115:I$129) -> 32505.067 | ... T17: ='Statistics NZ'!T$17*('Economic Forecasts'!V$10-'Economic Forecasts'!V$9)*1000000/SUM('Statistics NZ'!T$15:T$29,'Statistics NZ'!T$115:T$129) -> 32348.118 | U17: =SUM('Statistics NZ'!U$17,$B$12/5*(U$8-U$9)*1000)*('Economic Forecasts'!W$10-'Economic Forecasts'!W$9)*1000000/SUM('Statistics NZ'!U$15:U$29,'Statistics NZ'!U$115:U$129,SUM($B$12:$D$13)*(U$8-U$9)*1000) -> 29613.051 | V17: =SUM('Statistics NZ'!V$17,$B$12/5*(V$8-V$9)*1000)*('Economic Forecasts'!X$10-'Economic Forecasts'!X$9)*1000000/SUM('Statistics NZ'!V$15:V$29,'Statistics NZ'!V$115:V$129,SUM($B$12:$D$13)*(V$8-V$9)*1000) -> 30070.565 | W17: =SUM('Statistics NZ'!W$17,$B$12/5*(W$8-W$9)*1000)*('Economic Forecasts'!Y$10-'Economic Forecasts'!Y$9)*1000000/SUM('Statistics NZ'!W$15:W$29,'Statistics NZ'!W$115:W$129,SUM($B$12:$D$13)*(W$8-W$9)*1000) -> 31001.119 | X17: =SUM('Statistics NZ'!X$17,$B$12/5*(X$8-X$9)*1000)*('Economic Forecasts'!Z$10-'Economic Forecasts'!Z$9)*1000000/SUM('Statistics NZ'!X$15:X$29,'Statistics NZ'!X$115:X$129,SUM($B$12:$D$13)*(X$8-X$9)*1000) -> 31431.009 | Y17: =SUM('Statistics NZ'!Y$17,$B$12/5*(Y$8-Y$9)*1000)*('Economic Forecasts'!AA$10-'Economic Forecasts'!AA$9)*1000000/SUM('Statistics NZ'!Y$15:Y$29,'Statistics NZ'!Y$115:Y$129,SUM($B$12:$D$13)*(Y$8-Y$9)*1000) -> 31791.637 | Z17: =SUM(Y$17,'Statistics NZ'!Z$17-'Statistics NZ'!Y$17,$B$12/5*(Z$8-Z$9)*1000) -> 31804.85 | AA17: =SUM(Z$17,'Statistics NZ'!AA$17-'Statistics NZ'!Z$17,$B$12/5*(AA$8-AA$9)*1000) -> 31812.777 | AB17: =SUM(AA$17,'Statistics NZ'!AB$17-'Statistics NZ'!AA$17,$B$12/5*(AB$8-AB$9)*1000) -> 31806.477 | AC17: =SUM(AB$17,'Statistics NZ'!AC$17-'Statistics NZ'!AB$17,$B$12/5*(AC$8-AC$9)*1000) -> 31816.477 | AD17: =SUM(AC$17,'Statistics NZ'!AD$17-'Statistics NZ'!AC$17,$B$12/5*(AD$8-AD$9)*1000) -> 31846.477 | AE17: =SUM(AD$17,'Statistics NZ'!AE$17-'Statistics NZ'!AD$17,$B$12/5*(AE$8-AE$9)*1000) -> 31896.477 | AF17: =SUM(AE$17,'Statistics NZ'!AF$17-'Statistics NZ'!AE$17,$B$12/5*(AF$8-AF$9)*1000) -> 31986.477 | AG17: =SUM(AF$17,'Statistics NZ'!AG$17-'Statistics NZ'!AF$17,$B$12/5*(AG$8-AG$9)*1000) -> 32106.477 | ... BI17: =SUM(BH$17,'Statistics NZ'!BI$17-'Statistics NZ'!BH$17,$B$12/5*(BI$8-BI$9)*1000) -> 33836.477
A18: 3 | B18: ='Statistics NZ'!B$18*('Economic Forecasts'!D$10-'Economic Forecasts'!D$9)*1000000/SUM('Statistics NZ'!B$15:B$29,'Statistics NZ'!B$115:B$129) -> 28954.484 | C18: ='Statistics NZ'!C$18*('Economic Forecasts'!E$10-'Economic Forecasts'!E$9)*1000000/SUM('Statistics NZ'!C$15:C$29,'Statistics NZ'!C$115:C$129) -> 29785.082 | D18: ='Statistics NZ'!D$18*('Economic Forecasts'!F$10-'Economic Forecasts'!F$9)*1000000/SUM('Statistics NZ'!D$15:D$29,'Statistics NZ'!D$115:D$129) -> 29620.425 | E18: ='Statistics NZ'!E$18*('Economic Forecasts'!G$10-'Economic Forecasts'!G$9)*1000000/SUM('Statistics NZ'!E$15:E$29,'Statistics NZ'!E$115:E$129) -> 30499.286 | F18: ='Statistics NZ'!F$18*('Economic Forecasts'!H$10-'Economic Forecasts'!H$9)*1000000/SUM('Statistics NZ'!F$15:F$29,'Statistics NZ'!F$115:F$129) -> 32002.493 | G18: ='Statistics NZ'!G$18*('Economic Forecasts'!I$10-'Economic Forecasts'!I$9)*1000000/SUM('Statistics NZ'!G$15:G$29,'Statistics NZ'!G$115:G$129) -> 33127.799 | H18: ='Statistics NZ'!H$18*('Economic Forecasts'!J$10-'Economic Forecasts'!J$9)*1000000/SUM('Statistics NZ'!H$15:H$29,'Statistics NZ'!H$115:H$129) -> 32513.618 | I18: ='Statistics NZ'!I$18*('Economic Forecasts'!K$10-'Economic Forecasts'!K$9)*1000000/SUM('Statistics NZ'!I$15:I$29,'Statistics NZ'!I$115:I$129) -> 33291.652 | ... T18: ='Statistics NZ'!T$18*('Economic Forecasts'!V$10-'Economic Forecasts'!V$9)*1000000/SUM('Statistics NZ'!T$15:T$29,'Statistics NZ'!T$115:T$129) -> 32231.261 | U18: =SUM('Statistics NZ'!U$18,$B$12/5*(U$8-U$9)*1000)*('Economic Forecasts'!W$10-'Economic Forecasts'!W$9)*1000000/SUM('Statistics NZ'!U$15:U$29,'Statistics NZ'!U$115:U$129,SUM($B$12:$D$13)*(U$8-U$9)*1000) -> 32582.684 | V18: =SUM('Statistics NZ'!V$18,$B$12/5*(V$8-V$9)*1000)*('Economic Forecasts'!X$10-'Economic Forecasts'!X$9)*1000000/SUM('Statistics NZ'!V$15:V$29,'Statistics NZ'!V$115:V$129,SUM($B$12:$D$13)*(V$8-V$9)*1000) -> 30113.625 | W18: =SUM('Statistics NZ'!W$18,$B$12/5*(W$8-W$9)*1000)*('Economic Forecasts'!Y$10-'Economic Forecasts'!Y$9)*1000000/SUM('Statistics NZ'!W$15:W$29,'Statistics NZ'!W$115:W$129,SUM($B$12:$D$13)*(W$8-W$9)*1000) -> 30641.237 | X18: =SUM('Statistics NZ'!X$18,$B$12/5*(X$8-X$9)*1000)*('Economic Forecasts'!Z$10-'Economic Forecasts'!Z$9)*1000000/SUM('Statistics NZ'!X$15:X$29,'Statistics NZ'!X$115:X$129,SUM($B$12:$D$13)*(X$8-X$9)*1000) -> 31596.676 | Y18: =SUM('Statistics NZ'!Y$18,$B$12/5*(Y$8-Y$9)*1000)*('Economic Forecasts'!AA$10-'Economic Forecasts'!AA$9)*1000000/SUM('Statistics NZ'!Y$15:Y$29,'Statistics NZ'!Y$115:Y$129,SUM($B$12:$D$13)*(Y$8-Y$9)*1000) -> 31992.7 | Z18: =SUM(Y$18,'Statistics NZ'!Z$18-'Statistics NZ'!Y$18,$B$12/5*(Z$8-Z$9)*1000) -> 32025.913 | AA18: =SUM(Z$18,'Statistics NZ'!AA$18-'Statistics NZ'!Z$18,$B$12/5*(AA$8-AA$9)*1000) -> 32043.841 | AB18: =SUM(AA$18,'Statistics NZ'!AB$18-'Statistics NZ'!AA$18,$B$12/5*(AB$8-AB$9)*1000) -> 32037.54 | AC18: =SUM(AB$18,'Statistics NZ'!AC$18-'Statistics NZ'!AB$18,$B$12/5*(AC$8-AC$9)*1000) -> 32037.54 | AD18: =SUM(AC$18,'Statistics NZ'!AD$18-'Statistics NZ'!AC$18,$B$12/5*(AD$8-AD$9)*1000) -> 32047.54 | AE18: =SUM(AD$18,'Statistics NZ'!AE$18-'Statistics NZ'!AD$18,$B$12/5*(AE$8-AE$9)*1000) -> 32077.54 | AF18: =SUM(AE$18,'Statistics NZ'!AF$18-'Statistics NZ'!AE$18,$B$12/5*(AF$8-AF$9)*1000) -> 32127.54 | AG18: =SUM(AF$18,'Statistics NZ'!AG$18-'Statistics NZ'!AF$18,$B$12/5*(AG$8-AG$9)*1000) -> 32217.54 | ... BI18: =SUM(BH$18,'Statistics NZ'!BI$18-'Statistics NZ'!BH$18,$B$12/5*(BI$8-BI$9)*1000) -> 34037.54
A19: 4 | B19: ='Statistics NZ'!B$19*('Economic Forecasts'!D$10-'Economic Forecasts'!D$9)*1000000/SUM('Statistics NZ'!B$15:B$29,'Statistics NZ'!B$115:B$129) -> 29049.904 | C19: ='Statistics NZ'!C$19*('Economic Forecasts'!E$10-'Economic Forecasts'!E$9)*1000000/SUM('Statistics NZ'!C$15:C$29,'Statistics NZ'!C$115:C$129) -> 28941.91 | D19: ='Statistics NZ'!D$19*('Economic Forecasts'!F$10-'Economic Forecasts'!F$9)*1000000/SUM('Statistics NZ'!D$15:D$29,'Statistics NZ'!D$115:D$129) -> 29852.411 | E19: ='Statistics NZ'!E$19*('Economic Forecasts'!G$10-'Economic Forecasts'!G$9)*1000000/SUM('Statistics NZ'!E$15:E$29,'Statistics NZ'!E$115:E$129) -> 29739.705 | F19: ='Statistics NZ'!F$19*('Economic Forecasts'!H$10-'Economic Forecasts'!H$9)*1000000/SUM('Statistics NZ'!F$15:F$29,'Statistics NZ'!F$115:F$129) -> 30681.386 | G19: ='Statistics NZ'!G$19*('Economic Forecasts'!I$10-'Economic Forecasts'!I$9)*1000000/SUM('Statistics NZ'!G$15:G$29,'Statistics NZ'!G$115:G$129) -> 32026.715 | H19: ='Statistics NZ'!H$19*('Economic Forecasts'!J$10-'Economic Forecasts'!J$9)*1000000/SUM('Statistics NZ'!H$15:H$29,'Statistics NZ'!H$115:H$129) -> 33011.871 | I19: ='Statistics NZ'!I$19*('Economic Forecasts'!K$10-'Economic Forecasts'!K$9)*1000000/SUM('Statistics NZ'!I$15:I$29,'Statistics NZ'!I$115:I$129) -> 32473.179 | ... T19: ='Statistics NZ'!T$19*('Economic Forecasts'!V$10-'Economic Forecasts'!V$9)*1000000/SUM('Statistics NZ'!T$15:T$29,'Statistics NZ'!T$115:T$129) -> 32326.871 | U19: =SUM('Statistics NZ'!U$19,$B$12/5*(U$8-U$9)*1000)*('Economic Forecasts'!W$10-'Economic Forecasts'!W$9)*1000000/SUM('Statistics NZ'!U$15:U$29,'Statistics NZ'!U$115:U$129,SUM($B$12:$D$13)*(U$8-U$9)*1000) -> 32508.177 | V19: =SUM('Statistics NZ'!V$19,$B$12/5*(V$8-V$9)*1000)*('Economic Forecasts'!X$10-'Economic Forecasts'!X$9)*1000000/SUM('Statistics NZ'!V$15:V$29,'Statistics NZ'!V$115:V$129,SUM($B$12:$D$13)*(V$8-V$9)*1000) -> 33170.919 | W19: =SUM('Statistics NZ'!W$19,$B$12/5*(W$8-W$9)*1000)*('Economic Forecasts'!Y$10-'Economic Forecasts'!Y$9)*1000000/SUM('Statistics NZ'!W$15:W$29,'Statistics NZ'!W$115:W$129,SUM($B$12:$D$13)*(W$8-W$9)*1000) -> 30739.387 | X19: =SUM('Statistics NZ'!X$19,$B$12/5*(X$8-X$9)*1000)*('Economic Forecasts'!Z$10-'Economic Forecasts'!Z$9)*1000000/SUM('Statistics NZ'!X$15:X$29,'Statistics NZ'!X$115:X$129,SUM($B$12:$D$13)*(X$8-X$9)*1000) -> 31276.386 | Y19: =SUM('Statistics NZ'!Y$19,$B$12/5*(Y$8-Y$9)*1000)*('Economic Forecasts'!AA$10-'Economic Forecasts'!AA$9)*1000000/SUM('Statistics NZ'!Y$15:Y$29,'Statistics NZ'!Y$115:Y$129,SUM($B$12:$D$13)*(Y$8-Y$9)*1000) -> 32216.104 | Z19: =SUM(Y$19,'Statistics NZ'!Z$19-'Statistics NZ'!Y$19,$B$12/5*(Z$8-Z$9)*1000) -> 32279.317 | AA19: =SUM(Z$19,'Statistics NZ'!AA$19-'Statistics NZ'!Z$19,$B$12/5*(AA$8-AA$9)*1000) -> 32317.245 | AB19: =SUM(AA$19,'Statistics NZ'!AB$19-'Statistics NZ'!AA$19,$B$12/5*(AB$8-AB$9)*1000) -> 32330.944 | AC19: =SUM(AB$19,'Statistics NZ'!AC$19-'Statistics NZ'!AB$19,$B$12/5*(AC$8-AC$9)*1000) -> 32320.944 | AD19: =SUM(AC$19,'Statistics NZ'!AD$19-'Statistics NZ'!AC$19,$B$12/5*(AD$8-AD$9)*1000) -> 32320.944 | AE19: =SUM(AD$19,'Statistics NZ'!AE$19-'Statistics NZ'!AD$19,$B$12/5*(AE$8-AE$9)*1000) -> 32330.944 | AF19: =SUM(AE$19,'Statistics NZ'!AF$19-'Statistics NZ'!AE$19,$B$12/5*(AF$8-AF$9)*1000) -> 32360.944 | AG19: =SUM(AF$19,'Statistics NZ'!AG$19-'Statistics NZ'!AF$19,$B$12/5*(AG$8-AG$9)*1000) -> 32420.944 | ... BI19: =SUM(BH$19,'Statistics NZ'!BI$19-'Statistics NZ'!BH$19,$B$12/5*(BI$8-BI$9)*1000) -> 34310.944
A20: 5 | B20: ='Statistics NZ'!B$20*('Economic Forecasts'!D$10-'Economic Forecasts'!D$9)*1000000/SUM('Statistics NZ'!B$15:B$29,'Statistics NZ'!B$115:B$129) -> 30078.313 | C20: ='Statistics NZ'!C$20*('Economic Forecasts'!E$10-'Economic Forecasts'!E$9)*1000000/SUM('Statistics NZ'!C$15:C$29,'Statistics NZ'!C$115:C$129) -> 29142.163 | D20: ='Statistics NZ'!D$20*('Economic Forecasts'!F$10-'Economic Forecasts'!F$9)*1000000/SUM('Statistics NZ'!D$15:D$29,'Statistics NZ'!D$115:D$129) -> 29114.273 | E20: ='Statistics NZ'!E$20*('Economic Forecasts'!G$10-'Economic Forecasts'!G$9)*1000000/SUM('Statistics NZ'!E$15:E$29,'Statistics NZ'!E$115:E$129) -> 29971.8 | F20: ='Statistics NZ'!F$20*('Economic Forecasts'!H$10-'Economic Forecasts'!H$9)*1000000/SUM('Statistics NZ'!F$15:F$29,'Statistics NZ'!F$115:F$129) -> 29930.997 | G20: ='Statistics NZ'!G$20*('Economic Forecasts'!I$10-'Economic Forecasts'!I$9)*1000000/SUM('Statistics NZ'!G$15:G$29,'Statistics NZ'!G$115:G$129) -> 30756.234 | H20: ='Statistics NZ'!H$20*('Economic Forecasts'!J$10-'Economic Forecasts'!J$9)*1000000/SUM('Statistics NZ'!H$15:H$29,'Statistics NZ'!H$115:H$129) -> 31930.557 | I20: ='Statistics NZ'!I$20*('Economic Forecasts'!K$10-'Economic Forecasts'!K$9)*1000000/SUM('Statistics NZ'!I$15:I$29,'Statistics NZ'!I$115:I$129) -> 33047.173 | ... T20: ='Statistics NZ'!T$20*('Economic Forecasts'!V$10-'Economic Forecasts'!V$9)*1000000/SUM('Statistics NZ'!T$15:T$29,'Statistics NZ'!T$115:T$129) -> 32943.026 | U20: =SUM('Statistics NZ'!U$20,$C$12/5*(U$8-U$9)*1000)*('Economic Forecasts'!W$10-'Economic Forecasts'!W$9)*1000000/SUM('Statistics NZ'!U$15:U$29,'Statistics NZ'!U$115:U$129,SUM($B$12:$D$13)*(U$8-U$9)*1000) -> 32650.165 | V20: =SUM('Statistics NZ'!V$20,$C$12/5*(V$8-V$9)*1000)*('Economic Forecasts'!X$10-'Economic Forecasts'!X$9)*1000000/SUM('Statistics NZ'!V$15:V$29,'Statistics NZ'!V$115:V$129,SUM($B$12:$D$13)*(V$8-V$9)*1000) -> 33143.238 | W20: =SUM('Statistics NZ'!W$20,$C$12/5*(W$8-W$9)*1000)*('Economic Forecasts'!Y$10-'Economic Forecasts'!Y$9)*1000000/SUM('Statistics NZ'!W$15:W$29,'Statistics NZ'!W$115:W$129,SUM($B$12:$D$13)*(W$8-W$9)*1000) -> 33870.07 | X20: =SUM('Statistics NZ'!X$20,$C$12/5*(X$8-X$9)*1000)*('Economic Forecasts'!Z$10-'Economic Forecasts'!Z$9)*1000000/SUM('Statistics NZ'!X$15:X$29,'Statistics NZ'!X$115:X$129,SUM($B$12:$D$13)*(X$8-X$9)*1000) -> 31415.54 | Y20: =SUM('Statistics NZ'!Y$20,$C$12/5*(Y$8-Y$9)*1000)*('Economic Forecasts'!AA$10-'Economic Forecasts'!AA$9)*1000000/SUM('Statistics NZ'!Y$15:Y$29,'Statistics NZ'!Y$115:Y$129,SUM($B$12:$D$13)*(Y$8-Y$9)*1000) -> 31938.913 | Z20: =SUM(Y$20,'Statistics NZ'!Z$20-'Statistics NZ'!Y$20,$C$12/5*(Z$8-Z$9)*1000) -> 32489.53 | AA20: =SUM(Z$20,'Statistics NZ'!AA$20-'Statistics NZ'!Z$20,$C$12/5*(AA$8-AA$9)*1000) -> 32561.901 | AB20: =SUM(AA$20,'Statistics NZ'!AB$20-'Statistics NZ'!AA$20,$C$12/5*(AB$8-AB$9)*1000) -> 32597.673 | AC20: =SUM(AB$20,'Statistics NZ'!AC$20-'Statistics NZ'!AB$20,$C$12/5*(AC$8-AC$9)*1000) -> 32597.673 | AD20: =SUM(AC$20,'Statistics NZ'!AD$20-'Statistics NZ'!AC$20,$C$12/5*(AD$8-AD$9)*1000) -> 32597.673 | AE20: =SUM(AD$20,'Statistics NZ'!AE$20-'Statistics NZ'!AD$20,$C$12/5*(AE$8-AE$9)*1000) -> 32597.673 | AF20: =SUM(AE$20,'Statistics NZ'!AF$20-'Statistics NZ'!AE$20,$C$12/5*(AF$8-AF$9)*1000) -> 32617.673 | AG20: =SUM(AF$20,'Statistics NZ'!AG$20-'Statistics NZ'!AF$20,$C$12/5*(AG$8-AG$9)*1000) -> 32647.673 | ... BI20: =SUM(BH$20,'Statistics NZ'!BI$20-'Statistics NZ'!BH$20,$C$12/5*(BI$8-BI$9)*1000) -> 34597.673
A21: 6 | B21: ='Statistics NZ'!B$21*('Economic Forecasts'!D$10-'Economic Forecasts'!D$9)*1000000/SUM('Statistics NZ'!B$15:B$29,'Statistics NZ'!B$115:B$129) -> 30650.829 | C21: ='Statistics NZ'!C$21*('Economic Forecasts'!E$10-'Economic Forecasts'!E$9)*1000000/SUM('Statistics NZ'!C$15:C$29,'Statistics NZ'!C$115:C$129) -> 30164.51 | D21: ='Statistics NZ'!D$21*('Economic Forecasts'!F$10-'Economic Forecasts'!F$9)*1000000/SUM('Statistics NZ'!D$15:D$29,'Statistics NZ'!D$115:D$129) -> 29377.894 | E21: ='Statistics NZ'!E$21*('Economic Forecasts'!G$10-'Economic Forecasts'!G$9)*1000000/SUM('Statistics NZ'!E$15:E$29,'Statistics NZ'!E$115:E$129) -> 29296.617 | F21: ='Statistics NZ'!F$21*('Economic Forecasts'!H$10-'Economic Forecasts'!H$9)*1000000/SUM('Statistics NZ'!F$15:F$29,'Statistics NZ'!F$115:F$129) -> 30174.081 | G21: ='Statistics NZ'!G$21*('Economic Forecasts'!I$10-'Economic Forecasts'!I$9)*1000000/SUM('Statistics NZ'!G$15:G$29,'Statistics NZ'!G$115:G$129) -> 29951.596 | H21: ='Statistics NZ'!H$21*('Economic Forecasts'!J$10-'Economic Forecasts'!J$9)*1000000/SUM('Statistics NZ'!H$15:H$29,'Statistics NZ'!H$115:H$129) -> 30637.221 | I21: ='Statistics NZ'!I$21*('Economic Forecasts'!K$10-'Economic Forecasts'!K$9)*1000000/SUM('Statistics NZ'!I$15:I$29,'Statistics NZ'!I$115:I$129) -> 31941.703 | ... T21: ='Statistics NZ'!T$21*('Economic Forecasts'!V$10-'Economic Forecasts'!V$9)*1000000/SUM('Statistics NZ'!T$15:T$29,'Statistics NZ'!T$115:T$129) -> 33187.363 | U21: =SUM('Statistics NZ'!U$21,$C$12/5*(U$8-U$9)*1000)*('Economic Forecasts'!W$10-'Economic Forecasts'!W$9)*1000000/SUM('Statistics NZ'!U$15:U$29,'Statistics NZ'!U$115:U$129,SUM($B$12:$D$13)*(U$8-U$9)*1000) -> 33278.152 | V21: =SUM('Statistics NZ'!V$21,$C$12/5*(V$8-V$9)*1000)*('Economic Forecasts'!X$10-'Economic Forecasts'!X$9)*1000000/SUM('Statistics NZ'!V$15:V$29,'Statistics NZ'!V$115:V$129,SUM($B$12:$D$13)*(V$8-V$9)*1000) -> 33272.42 | W21: =SUM('Statistics NZ'!W$21,$C$12/5*(W$8-W$9)*1000)*('Economic Forecasts'!Y$10-'Economic Forecasts'!Y$9)*1000000/SUM('Statistics NZ'!W$15:W$29,'Statistics NZ'!W$115:W$129,SUM($B$12:$D$13)*(W$8-W$9)*1000) -> 33837.354 | X21: =SUM('Statistics NZ'!X$21,$C$12/5*(X$8-X$9)*1000)*('Economic Forecasts'!Z$10-'Economic Forecasts'!Z$9)*1000000/SUM('Statistics NZ'!X$15:X$29,'Statistics NZ'!X$115:X$129,SUM($B$12:$D$13)*(X$8-X$9)*1000) -> 34585.309 | Y21: =SUM('Statistics NZ'!Y$21,$C$12/5*(Y$8-Y$9)*1000)*('Economic Forecasts'!AA$10-'Economic Forecasts'!AA$9)*1000000/SUM('Statistics NZ'!Y$15:Y$29,'Statistics NZ'!Y$115:Y$129,SUM($B$12:$D$13)*(Y$8-Y$9)*1000) -> 32072.955 | Z21: =SUM(Y$21,'Statistics NZ'!Z$21-'Statistics NZ'!Y$21,$C$12/5*(Z$8-Z$9)*1000) -> 32253.572 | AA21: =SUM(Z$21,'Statistics NZ'!AA$21-'Statistics NZ'!Z$21,$C$12/5*(AA$8-AA$9)*1000) -> 32805.943 | AB21: =SUM(AA$21,'Statistics NZ'!AB$21-'Statistics NZ'!AA$21,$C$12/5*(AB$8-AB$9)*1000) -> 32871.716 | AC21: =SUM(AB$21,'Statistics NZ'!AC$21-'Statistics NZ'!AB$21,$C$12/5*(AC$8-AC$9)*1000) -> 32901.716 | AD21: =SUM(AC$21,'Statistics NZ'!AD$21-'Statistics NZ'!AC$21,$C$12/5*(AD$8-AD$9)*1000) -> 32911.716 | AE21: =SUM(AD$21,'Statistics NZ'!AE$21-'Statistics NZ'!AD$21,$C$12/5*(AE$8-AE$9)*1000) -> 32911.716 | AF21: =SUM(AE$21,'Statistics NZ'!AF$21-'Statistics NZ'!AE$21,$C$12/5*(AF$8-AF$9)*1000) -> 32921.716 | AG21: =SUM(AF$21,'Statistics NZ'!AG$21-'Statistics NZ'!AF$21,$C$12/5*(AG$8-AG$9)*1000) -> 32931.716 | ... BI21: =SUM(BH$21,'Statistics NZ'!BI$21-'Statistics NZ'!BH$21,$C$12/5*(BI$8-BI$9)*1000) -> 34941.716
A22: 7 | B22: ='Statistics NZ'!B$22*('Economic Forecasts'!D$10-'Economic Forecasts'!D$9)*1000000/SUM('Statistics NZ'!B$15:B$29,'Statistics NZ'!B$115:B$129) -> 29664.829 | C22: ='Statistics NZ'!C$22*('Economic Forecasts'!E$10-'Economic Forecasts'!E$9)*1000000/SUM('Statistics NZ'!C$15:C$29,'Statistics NZ'!C$115:C$129) -> 30733.652 | D22: ='Statistics NZ'!D$22*('Economic Forecasts'!F$10-'Economic Forecasts'!F$9)*1000000/SUM('Statistics NZ'!D$15:D$29,'Statistics NZ'!D$115:D$129) -> 30326.929 | E22: ='Statistics NZ'!E$22*('Economic Forecasts'!G$10-'Economic Forecasts'!G$9)*1000000/SUM('Statistics NZ'!E$15:E$29,'Statistics NZ'!E$115:E$129) -> 29528.711 | F22: ='Statistics NZ'!F$22*('Economic Forecasts'!H$10-'Economic Forecasts'!H$9)*1000000/SUM('Statistics NZ'!F$15:F$29,'Statistics NZ'!F$115:F$129) -> 29434.261 | G22: ='Statistics NZ'!G$22*('Economic Forecasts'!I$10-'Economic Forecasts'!I$9)*1000000/SUM('Statistics NZ'!G$15:G$29,'Statistics NZ'!G$115:G$129) -> 30279.804 | H22: ='Statistics NZ'!H$22*('Economic Forecasts'!J$10-'Economic Forecasts'!J$9)*1000000/SUM('Statistics NZ'!H$15:H$29,'Statistics NZ'!H$115:H$129) -> 29895.143 | I22: ='Statistics NZ'!I$22*('Economic Forecasts'!K$10-'Economic Forecasts'!K$9)*1000000/SUM('Statistics NZ'!I$15:I$29,'Statistics NZ'!I$115:I$129) -> 30602.383 | ... T22: ='Statistics NZ'!T$22*('Economic Forecasts'!V$10-'Economic Forecasts'!V$9)*1000000/SUM('Statistics NZ'!T$15:T$29,'Statistics NZ'!T$115:T$129) -> 34122.218 | U22: =SUM('Statistics NZ'!U$22,$C$12/5*(U$8-U$9)*1000)*('Economic Forecasts'!W$10-'Economic Forecasts'!W$9)*1000000/SUM('Statistics NZ'!U$15:U$29,'Statistics NZ'!U$115:U$129,SUM($B$12:$D$13)*(U$8-U$9)*1000) -> 33533.604 | V22: =SUM('Statistics NZ'!V$22,$C$12/5*(V$8-V$9)*1000)*('Economic Forecasts'!X$10-'Economic Forecasts'!X$9)*1000000/SUM('Statistics NZ'!V$15:V$29,'Statistics NZ'!V$115:V$129,SUM($B$12:$D$13)*(V$8-V$9)*1000) -> 33918.327 | W22: =SUM('Statistics NZ'!W$22,$C$12/5*(W$8-W$9)*1000)*('Economic Forecasts'!Y$10-'Economic Forecasts'!Y$9)*1000000/SUM('Statistics NZ'!W$15:W$29,'Statistics NZ'!W$115:W$129,SUM($B$12:$D$13)*(W$8-W$9)*1000) -> 33979.126 | X22: =SUM('Statistics NZ'!X$22,$C$12/5*(X$8-X$9)*1000)*('Economic Forecasts'!Z$10-'Economic Forecasts'!Z$9)*1000000/SUM('Statistics NZ'!X$15:X$29,'Statistics NZ'!X$115:X$129,SUM($B$12:$D$13)*(X$8-X$9)*1000) -> 34563.22 | Y22: =SUM('Statistics NZ'!Y$22,$C$12/5*(Y$8-Y$9)*1000)*('Economic Forecasts'!AA$10-'Economic Forecasts'!AA$9)*1000000/SUM('Statistics NZ'!Y$15:Y$29,'Statistics NZ'!Y$115:Y$129,SUM($B$12:$D$13)*(Y$8-Y$9)*1000) -> 35289.97 | Z22: =SUM(Y$22,'Statistics NZ'!Z$22-'Statistics NZ'!Y$22,$C$12/5*(Z$8-Z$9)*1000) -> 32730.587 | AA22: =SUM(Z$22,'Statistics NZ'!AA$22-'Statistics NZ'!Z$22,$C$12/5*(AA$8-AA$9)*1000) -> 32902.958 | AB22: =SUM(AA$22,'Statistics NZ'!AB$22-'Statistics NZ'!AA$22,$C$12/5*(AB$8-AB$9)*1000) -> 33458.731 | AC22: =SUM(AB$22,'Statistics NZ'!AC$22-'Statistics NZ'!AB$22,$C$12/5*(AC$8-AC$9)*1000) -> 33518.731 | AD22: =SUM(AC$22,'Statistics NZ'!AD$22-'Statistics NZ'!AC$22,$C$12/5*(AD$8-AD$9)*1000) -> 33548.731 | AE22: =SUM(AD$22,'Statistics NZ'!AE$22-'Statistics NZ'!AD$22,$C$12/5*(AE$8-AE$9)*1000) -> 33558.731 | AF22: =SUM(AE$22,'Statistics NZ'!AF$22-'Statistics NZ'!AE$22,$C$12/5*(AF$8-AF$9)*1000) -> 33558.731 | AG22: =SUM(AF$22,'Statistics NZ'!AG$22-'Statistics NZ'!AF$22,$C$12/5*(AG$8-AG$9)*1000) -> 33568.731 | ... BI22: =SUM(BH$22,'Statistics NZ'!BI$22-'Statistics NZ'!BH$22,$C$12/5*(BI$8-BI$9)*1000) -> 35628.731
A23: 8 | B23: ='Statistics NZ'!B$23*('Economic Forecasts'!D$10-'Economic Forecasts'!D$9)*1000000/SUM('Statistics NZ'!B$15:B$29,'Statistics NZ'!B$115:B$129) -> 30343.367 | C23: ='Statistics NZ'!C$23*('Economic Forecasts'!E$10-'Economic Forecasts'!E$9)*1000000/SUM('Statistics NZ'!C$15:C$29,'Statistics NZ'!C$115:C$129) -> 29753.463 | D23: ='Statistics NZ'!D$23*('Economic Forecasts'!F$10-'Economic Forecasts'!F$9)*1000000/SUM('Statistics NZ'!D$15:D$29,'Statistics NZ'!D$115:D$129) -> 30938.529 | E23: ='Statistics NZ'!E$23*('Economic Forecasts'!G$10-'Economic Forecasts'!G$9)*1000000/SUM('Statistics NZ'!E$15:E$29,'Statistics NZ'!E$115:E$129) -> 30541.485 | F23: ='Statistics NZ'!F$23*('Economic Forecasts'!H$10-'Economic Forecasts'!H$9)*1000000/SUM('Statistics NZ'!F$15:F$29,'Statistics NZ'!F$115:F$129) -> 29719.62 | G23: ='Statistics NZ'!G$23*('Economic Forecasts'!I$10-'Economic Forecasts'!I$9)*1000000/SUM('Statistics NZ'!G$15:G$29,'Statistics NZ'!G$115:G$129) -> 29549.277 | H23: ='Statistics NZ'!H$23*('Economic Forecasts'!J$10-'Economic Forecasts'!J$9)*1000000/SUM('Statistics NZ'!H$15:H$29,'Statistics NZ'!H$115:H$129) -> 30202.575 | I23: ='Statistics NZ'!I$23*('Economic Forecasts'!K$10-'Economic Forecasts'!K$9)*1000000/SUM('Statistics NZ'!I$15:I$29,'Statistics NZ'!I$115:I$129) -> 29911.465 | ... T23: ='Statistics NZ'!T$23*('Economic Forecasts'!V$10-'Economic Forecasts'!V$9)*1000000/SUM('Statistics NZ'!T$15:T$29,'Statistics NZ'!T$115:T$129) -> 33899.128 | U23: =SUM('Statistics NZ'!U$23,$C$12/5*(U$8-U$9)*1000)*('Economic Forecasts'!W$10-'Economic Forecasts'!W$9)*1000000/SUM('Statistics NZ'!U$15:U$29,'Statistics NZ'!U$115:U$129,SUM($B$12:$D$13)*(U$8-U$9)*1000) -> 34470.263 | V23: =SUM('Statistics NZ'!V$23,$C$12/5*(V$8-V$9)*1000)*('Economic Forecasts'!X$10-'Economic Forecasts'!X$9)*1000000/SUM('Statistics NZ'!V$15:V$29,'Statistics NZ'!V$115:V$129,SUM($B$12:$D$13)*(V$8-V$9)*1000) -> 34176.689 | W23: =SUM('Statistics NZ'!W$23,$C$12/5*(W$8-W$9)*1000)*('Economic Forecasts'!Y$10-'Economic Forecasts'!Y$9)*1000000/SUM('Statistics NZ'!W$15:W$29,'Statistics NZ'!W$115:W$129,SUM($B$12:$D$13)*(W$8-W$9)*1000) -> 34633.457 | X23: =SUM('Statistics NZ'!X$23,$C$12/5*(X$8-X$9)*1000)*('Economic Forecasts'!Z$10-'Economic Forecasts'!Z$9)*1000000/SUM('Statistics NZ'!X$15:X$29,'Statistics NZ'!X$115:X$129,SUM($B$12:$D$13)*(X$8-X$9)*1000) -> 34706.798 | Y23: =SUM('Statistics NZ'!Y$23,$C$12/5*(Y$8-Y$9)*1000)*('Economic Forecasts'!AA$10-'Economic Forecasts'!AA$9)*1000000/SUM('Statistics NZ'!Y$15:Y$29,'Statistics NZ'!Y$115:Y$129,SUM($B$12:$D$13)*(Y$8-Y$9)*1000) -> 35267.63 | Z23: =SUM(Y$23,'Statistics NZ'!Z$23-'Statistics NZ'!Y$23,$C$12/5*(Z$8-Z$9)*1000) -> 35608.247 | AA23: =SUM(Z$23,'Statistics NZ'!AA$23-'Statistics NZ'!Z$23,$C$12/5*(AA$8-AA$9)*1000) -> 33040.617 | AB23: =SUM(AA$23,'Statistics NZ'!AB$23-'Statistics NZ'!AA$23,$C$12/5*(AB$8-AB$9)*1000) -> 33216.39 | AC23: =SUM(AB$23,'Statistics NZ'!AC$23-'Statistics NZ'!AB$23,$C$12/5*(AC$8-AC$9)*1000) -> 33756.39 | AD23: =SUM(AC$23,'Statistics NZ'!AD$23-'Statistics NZ'!AC$23,$C$12/5*(AD$8-AD$9)*1000) -> 33816.39 | AE23: =SUM(AD$23,'Statistics NZ'!AE$23-'Statistics NZ'!AD$23,$C$12/5*(AE$8-AE$9)*1000) -> 33856.39 | AF23: =SUM(AE$23,'Statistics NZ'!AF$23-'Statistics NZ'!AE$23,$C$12/5*(AF$8-AF$9)*1000) -> 33866.39 | AG23: =SUM(AF$23,'Statistics NZ'!AG$23-'Statistics NZ'!AF$23,$C$12/5*(AG$8-AG$9)*1000) -> 33876.39 | ... BI23: =SUM(BH$23,'Statistics NZ'!BI$23-'Statistics NZ'!BH$23,$C$12/5*(BI$8-BI$9)*1000) -> 35996.39
A24: 9 | B24: ='Statistics NZ'!B$24*('Economic Forecasts'!D$10-'Economic Forecasts'!D$9)*1000000/SUM('Statistics NZ'!B$15:B$29,'Statistics NZ'!B$115:B$129) -> 30502.399 | C24: ='Statistics NZ'!C$24*('Economic Forecasts'!E$10-'Economic Forecasts'!E$9)*1000000/SUM('Statistics NZ'!C$15:C$29,'Statistics NZ'!C$115:C$129) -> 30470.16 | D24: ='Statistics NZ'!D$24*('Economic Forecasts'!F$10-'Economic Forecasts'!F$9)*1000000/SUM('Statistics NZ'!D$15:D$29,'Statistics NZ'!D$115:D$129) -> 29936.77 | E24: ='Statistics NZ'!E$24*('Economic Forecasts'!G$10-'Economic Forecasts'!G$9)*1000000/SUM('Statistics NZ'!E$15:E$29,'Statistics NZ'!E$115:E$129) -> 31174.47 | F24: ='Statistics NZ'!F$24*('Economic Forecasts'!H$10-'Economic Forecasts'!H$9)*1000000/SUM('Statistics NZ'!F$15:F$29,'Statistics NZ'!F$115:F$129) -> 30808.212 | G24: ='Statistics NZ'!G$24*('Economic Forecasts'!I$10-'Economic Forecasts'!I$9)*1000000/SUM('Statistics NZ'!G$15:G$29,'Statistics NZ'!G$115:G$129) -> 29866.897 | H24: ='Statistics NZ'!H$24*('Economic Forecasts'!J$10-'Economic Forecasts'!J$9)*1000000/SUM('Statistics NZ'!H$15:H$29,'Statistics NZ'!H$115:H$129) -> 29524.104 | I24: ='Statistics NZ'!I$24*('Economic Forecasts'!K$10-'Economic Forecasts'!K$9)*1000000/SUM('Statistics NZ'!I$15:I$29,'Statistics NZ'!I$115:I$129) -> 30219.721 | ... T24: ='Statistics NZ'!T$24*('Economic Forecasts'!V$10-'Economic Forecasts'!V$9)*1000000/SUM('Statistics NZ'!T$15:T$29,'Statistics NZ'!T$115:T$129) -> 34653.386 | U24: =SUM('Statistics NZ'!U$24,$C$12/5*(U$8-U$9)*1000)*('Economic Forecasts'!W$10-'Economic Forecasts'!W$9)*1000000/SUM('Statistics NZ'!U$15:U$29,'Statistics NZ'!U$115:U$129,SUM($B$12:$D$13)*(U$8-U$9)*1000) -> 34246.742 | V24: =SUM('Statistics NZ'!V$24,$C$12/5*(V$8-V$9)*1000)*('Economic Forecasts'!X$10-'Economic Forecasts'!X$9)*1000000/SUM('Statistics NZ'!V$15:V$29,'Statistics NZ'!V$115:V$129,SUM($B$12:$D$13)*(V$8-V$9)*1000) -> 35134.785 | W24: =SUM('Statistics NZ'!W$24,$C$12/5*(W$8-W$9)*1000)*('Economic Forecasts'!Y$10-'Economic Forecasts'!Y$9)*1000000/SUM('Statistics NZ'!W$15:W$29,'Statistics NZ'!W$115:W$129,SUM($B$12:$D$13)*(W$8-W$9)*1000) -> 34895.189 | X24: =SUM('Statistics NZ'!X$24,$C$12/5*(X$8-X$9)*1000)*('Economic Forecasts'!Z$10-'Economic Forecasts'!Z$9)*1000000/SUM('Statistics NZ'!X$15:X$29,'Statistics NZ'!X$115:X$129,SUM($B$12:$D$13)*(X$8-X$9)*1000) -> 35369.468 | Y24: =SUM('Statistics NZ'!Y$24,$C$12/5*(Y$8-Y$9)*1000)*('Economic Forecasts'!AA$10-'Economic Forecasts'!AA$9)*1000000/SUM('Statistics NZ'!Y$15:Y$29,'Statistics NZ'!Y$115:Y$129,SUM($B$12:$D$13)*(Y$8-Y$9)*1000) -> 35401.672 | Z24: =SUM(Y$24,'Statistics NZ'!Z$24-'Statistics NZ'!Y$24,$C$12/5*(Z$8-Z$9)*1000) -> 35592.289 | AA24: =SUM(Z$24,'Statistics NZ'!AA$24-'Statistics NZ'!Z$24,$C$12/5*(AA$8-AA$9)*1000) -> 35934.66 | AB24: =SUM(AA$24,'Statistics NZ'!AB$24-'Statistics NZ'!AA$24,$C$12/5*(AB$8-AB$9)*1000) -> 33360.433 | AC24: =SUM(AB$24,'Statistics NZ'!AC$24-'Statistics NZ'!AB$24,$C$12/5*(AC$8-AC$9)*1000) -> 33530.433 | AD24: =SUM(AC$24,'Statistics NZ'!AD$24-'Statistics NZ'!AC$24,$C$12/5*(AD$8-AD$9)*1000) -> 34080.433 | AE24: =SUM(AD$24,'Statistics NZ'!AE$24-'Statistics NZ'!AD$24,$C$12/5*(AE$8-AE$9)*1000) -> 34140.433 | AF24: =SUM(AE$24,'Statistics NZ'!AF$24-'Statistics NZ'!AE$24,$C$12/5*(AF$8-AF$9)*1000) -> 34180.433 | AG24: =SUM(AF$24,'Statistics NZ'!AG$24-'Statistics NZ'!AF$24,$C$12/5*(AG$8-AG$9)*1000) -> 34190.433 | ... BI24: =SUM(BH$24,'Statistics NZ'!BI$24-'Statistics NZ'!BH$24,$C$12/5*(BI$8-BI$9)*1000) -> 36390.433
A25: 10 | B25: ='Statistics NZ'!B$25*('Economic Forecasts'!D$10-'Economic Forecasts'!D$9)*1000000/SUM('Statistics NZ'!B$15:B$29,'Statistics NZ'!B$115:B$129) -> 31011.302 | C25: ='Statistics NZ'!C$25*('Economic Forecasts'!E$10-'Economic Forecasts'!E$9)*1000000/SUM('Statistics NZ'!C$15:C$29,'Statistics NZ'!C$115:C$129) -> 30554.478 | D25: ='Statistics NZ'!D$25*('Economic Forecasts'!F$10-'Economic Forecasts'!F$9)*1000000/SUM('Statistics NZ'!D$15:D$29,'Statistics NZ'!D$115:D$129) -> 30674.908 | E25: ='Statistics NZ'!E$25*('Economic Forecasts'!G$10-'Economic Forecasts'!G$9)*1000000/SUM('Statistics NZ'!E$15:E$29,'Statistics NZ'!E$115:E$129) -> 30119.496 | F25: ='Statistics NZ'!F$25*('Economic Forecasts'!H$10-'Economic Forecasts'!H$9)*1000000/SUM('Statistics NZ'!F$15:F$29,'Statistics NZ'!F$115:F$129) -> 31463.481 | G25: ='Statistics NZ'!G$25*('Economic Forecasts'!I$10-'Economic Forecasts'!I$9)*1000000/SUM('Statistics NZ'!G$15:G$29,'Statistics NZ'!G$115:G$129) -> 31031.505 | H25: ='Statistics NZ'!H$25*('Economic Forecasts'!J$10-'Economic Forecasts'!J$9)*1000000/SUM('Statistics NZ'!H$15:H$29,'Statistics NZ'!H$115:H$129) -> 29905.744 | I25: ='Statistics NZ'!I$25*('Economic Forecasts'!K$10-'Economic Forecasts'!K$9)*1000000/SUM('Statistics NZ'!I$15:I$29,'Statistics NZ'!I$115:I$129) -> 29656.356 | ... T25: ='Statistics NZ'!T$25*('Economic Forecasts'!V$10-'Economic Forecasts'!V$9)*1000000/SUM('Statistics NZ'!T$15:T$29,'Statistics NZ'!T$115:T$129) -> 34865.853 | U25: =SUM('Statistics NZ'!U$25,$D$12/5*(U$8-U$9)*1000)*('Economic Forecasts'!W$10-'Economic Forecasts'!W$9)*1000000/SUM('Statistics NZ'!U$15:U$29,'Statistics NZ'!U$115:U$129,SUM($B$12:$D$13)*(U$8-U$9)*1000) -> 35011.285 | V25: =SUM('Statistics NZ'!V$25,$D$12/5*(V$8-V$9)*1000)*('Economic Forecasts'!X$10-'Economic Forecasts'!X$9)*1000000/SUM('Statistics NZ'!V$15:V$29,'Statistics NZ'!V$115:V$129,SUM($B$12:$D$13)*(V$8-V$9)*1000) -> 34917.579 | W25: =SUM('Statistics NZ'!W$25,$D$12/5*(W$8-W$9)*1000)*('Economic Forecasts'!Y$10-'Economic Forecasts'!Y$9)*1000000/SUM('Statistics NZ'!W$15:W$29,'Statistics NZ'!W$115:W$129,SUM($B$12:$D$13)*(W$8-W$9)*1000) -> 35875.04 | X25: =SUM('Statistics NZ'!X$25,$D$12/5*(X$8-X$9)*1000)*('Economic Forecasts'!Z$10-'Economic Forecasts'!Z$9)*1000000/SUM('Statistics NZ'!X$15:X$29,'Statistics NZ'!X$115:X$129,SUM($B$12:$D$13)*(X$8-X$9)*1000) -> 35644.294 | Y25: =SUM('Statistics NZ'!Y$25,$D$12/5*(Y$8-Y$9)*1000)*('Economic Forecasts'!AA$10-'Economic Forecasts'!AA$9)*1000000/SUM('Statistics NZ'!Y$15:Y$29,'Statistics NZ'!Y$115:Y$129,SUM($B$12:$D$13)*(Y$8-Y$9)*1000) -> 36093.26 | Z25: =SUM(Y$25,'Statistics NZ'!Z$25-'Statistics NZ'!Y$25,$D$12/5*(Z$8-Z$9)*1000) -> 35803.338 | AA25: =SUM(Z$25,'Statistics NZ'!AA$25-'Statistics NZ'!Z$25,$D$12/5*(AA$8-AA$9)*1000) -> 35985.385 | AB25: =SUM(AA$25,'Statistics NZ'!AB$25-'Statistics NZ'!AA$25,$D$12/5*(AB$8-AB$9)*1000) -> 36321.007 | AC25: =SUM(AB$25,'Statistics NZ'!AC$25-'Statistics NZ'!AB$25,$D$12/5*(AC$8-AC$9)*1000) -> 33751.007 | AD25: =SUM(AC$25,'Statistics NZ'!AD$25-'Statistics NZ'!AC$25,$D$12/5*(AD$8-AD$9)*1000) -> 33921.007 | AE25: =SUM(AD$25,'Statistics NZ'!AE$25-'Statistics NZ'!AD$25,$D$12/5*(AE$8-AE$9)*1000) -> 34471.007 | AF25: =SUM(AE$25,'Statistics NZ'!AF$25-'Statistics NZ'!AE$25,$D$12/5*(AF$8-AF$9)*1000) -> 34531.007 | AG25: =SUM(AF$25,'Statistics NZ'!AG$25-'Statistics NZ'!AF$25,$D$12/5*(AG$8-AG$9)*1000) -> 34571.007 | ... BI25: =SUM(BH$25,'Statistics NZ'!BI$25-'Statistics NZ'!BH$25,$D$12/5*(BI$8-BI$9)*1000) -> 36861.007
A26: 11 | B26: ='Statistics NZ'!B$26*('Economic Forecasts'!D$10-'Economic Forecasts'!D$9)*1000000/SUM('Statistics NZ'!B$15:B$29,'Statistics NZ'!B$115:B$129) -> 31774.657 | C26: ='Statistics NZ'!C$26*('Economic Forecasts'!E$10-'Economic Forecasts'!E$9)*1000000/SUM('Statistics NZ'!C$15:C$29,'Statistics NZ'!C$115:C$129) -> 31018.223 | D26: ='Statistics NZ'!D$26*('Economic Forecasts'!F$10-'Economic Forecasts'!F$9)*1000000/SUM('Statistics NZ'!D$15:D$29,'Statistics NZ'!D$115:D$129) -> 30769.812 | E26: ='Statistics NZ'!E$26*('Economic Forecasts'!G$10-'Economic Forecasts'!G$9)*1000000/SUM('Statistics NZ'!E$15:E$29,'Statistics NZ'!E$115:E$129) -> 30879.077 | F26: ='Statistics NZ'!F$26*('Economic Forecasts'!H$10-'Economic Forecasts'!H$9)*1000000/SUM('Statistics NZ'!F$15:F$29,'Statistics NZ'!F$115:F$129) -> 30332.614 | G26: ='Statistics NZ'!G$26*('Economic Forecasts'!I$10-'Economic Forecasts'!I$9)*1000000/SUM('Statistics NZ'!G$15:G$29,'Statistics NZ'!G$115:G$129) -> 31634.984 | H26: ='Statistics NZ'!H$26*('Economic Forecasts'!J$10-'Economic Forecasts'!J$9)*1000000/SUM('Statistics NZ'!H$15:H$29,'Statistics NZ'!H$115:H$129) -> 31146.074 | I26: ='Statistics NZ'!I$26*('Economic Forecasts'!K$10-'Economic Forecasts'!K$9)*1000000/SUM('Statistics NZ'!I$15:I$29,'Statistics NZ'!I$115:I$129) -> 30060.278 | ... T26: ='Statistics NZ'!T$26*('Economic Forecasts'!V$10-'Economic Forecasts'!V$9)*1000000/SUM('Statistics NZ'!T$15:T$29,'Statistics NZ'!T$115:T$129) -> 36066.292 | U26: =SUM('Statistics NZ'!U$26,$D$12/5*(U$8-U$9)*1000)*('Economic Forecasts'!W$10-'Economic Forecasts'!W$9)*1000000/SUM('Statistics NZ'!U$15:U$29,'Statistics NZ'!U$115:U$129,SUM($B$12:$D$13)*(U$8-U$9)*1000) -> 35224.162 | V26: =SUM('Statistics NZ'!V$26,$D$12/5*(V$8-V$9)*1000)*('Economic Forecasts'!X$10-'Economic Forecasts'!X$9)*1000000/SUM('Statistics NZ'!V$15:V$29,'Statistics NZ'!V$115:V$129,SUM($B$12:$D$13)*(V$8-V$9)*1000) -> 35681.902 | W26: =SUM('Statistics NZ'!W$26,$D$12/5*(W$8-W$9)*1000)*('Economic Forecasts'!Y$10-'Economic Forecasts'!Y$9)*1000000/SUM('Statistics NZ'!W$15:W$29,'Statistics NZ'!W$115:W$129,SUM($B$12:$D$13)*(W$8-W$9)*1000) -> 35656.929 | X26: =SUM('Statistics NZ'!X$26,$D$12/5*(X$8-X$9)*1000)*('Economic Forecasts'!Z$10-'Economic Forecasts'!Z$9)*1000000/SUM('Statistics NZ'!X$15:X$29,'Statistics NZ'!X$115:X$129,SUM($B$12:$D$13)*(X$8-X$9)*1000) -> 36627.253 | Y26: =SUM('Statistics NZ'!Y$26,$D$12/5*(Y$8-Y$9)*1000)*('Economic Forecasts'!AA$10-'Economic Forecasts'!AA$9)*1000000/SUM('Statistics NZ'!Y$15:Y$29,'Statistics NZ'!Y$115:Y$129,SUM($B$12:$D$13)*(Y$8-Y$9)*1000) -> 36372.515 | Z26: =SUM(Y$26,'Statistics NZ'!Z$26-'Statistics NZ'!Y$26,$D$12/5*(Z$8-Z$9)*1000) -> 36442.593 | AA26: =SUM(Z$26,'Statistics NZ'!AA$26-'Statistics NZ'!Z$26,$D$12/5*(AA$8-AA$9)*1000) -> 36154.64 | AB26: =SUM(AA$26,'Statistics NZ'!AB$26-'Statistics NZ'!AA$26,$D$12/5*(AB$8-AB$9)*1000) -> 36340.262 | AC26: =SUM(AB$26,'Statistics NZ'!AC$26-'Statistics NZ'!AB$26,$D$12/5*(AC$8-AC$9)*1000) -> 36660.262 | AD26: =SUM(AC$26,'Statistics NZ'!AD$26-'Statistics NZ'!AC$26,$D$12/5*(AD$8-AD$9)*1000) -> 34090.262 | AE26: =SUM(AD$26,'Statistics NZ'!AE$26-'Statistics NZ'!AD$26,$D$12/5*(AE$8-AE$9)*1000) -> 34270.262 | AF26: =SUM(AE$26,'Statistics NZ'!AF$26-'Statistics NZ'!AE$26,$D$12/5*(AF$8-AF$9)*1000) -> 34820.262 | AG26: =SUM(AF$26,'Statistics NZ'!AG$26-'Statistics NZ'!AF$26,$D$12/5*(AG$8-AG$9)*1000) -> 34880.262 | ... BI26: =SUM(BH$26,'Statistics NZ'!BI$26-'Statistics NZ'!BH$26,$D$12/5*(BI$8-BI$9)*1000) -> 37310.262
A27: 12 | B27: ='Statistics NZ'!B$27*('Economic Forecasts'!D$10-'Economic Forecasts'!D$9)*1000000/SUM('Statistics NZ'!B$15:B$29,'Statistics NZ'!B$115:B$129) -> 31795.862 | C27: ='Statistics NZ'!C$27*('Economic Forecasts'!E$10-'Economic Forecasts'!E$9)*1000000/SUM('Statistics NZ'!C$15:C$29,'Statistics NZ'!C$115:C$129) -> 31713.84 | D27: ='Statistics NZ'!D$27*('Economic Forecasts'!F$10-'Economic Forecasts'!F$9)*1000000/SUM('Statistics NZ'!D$15:D$29,'Statistics NZ'!D$115:D$129) -> 31117.791 | E27: ='Statistics NZ'!E$27*('Economic Forecasts'!G$10-'Economic Forecasts'!G$9)*1000000/SUM('Statistics NZ'!E$15:E$29,'Statistics NZ'!E$115:E$129) -> 30984.574 | F27: ='Statistics NZ'!F$27*('Economic Forecasts'!H$10-'Economic Forecasts'!H$9)*1000000/SUM('Statistics NZ'!F$15:F$29,'Statistics NZ'!F$115:F$129) -> 31199.26 | G27: ='Statistics NZ'!G$27*('Economic Forecasts'!I$10-'Economic Forecasts'!I$9)*1000000/SUM('Statistics NZ'!G$15:G$29,'Statistics NZ'!G$115:G$129) -> 30565.662 | H27: ='Statistics NZ'!H$27*('Economic Forecasts'!J$10-'Economic Forecasts'!J$9)*1000000/SUM('Statistics NZ'!H$15:H$29,'Statistics NZ'!H$115:H$129) -> 31707.934 | I27: ='Statistics NZ'!I$27*('Economic Forecasts'!K$10-'Economic Forecasts'!K$9)*1000000/SUM('Statistics NZ'!I$15:I$29,'Statistics NZ'!I$115:I$129) -> 31335.82 | ... T27: ='Statistics NZ'!T$27*('Economic Forecasts'!V$10-'Economic Forecasts'!V$9)*1000000/SUM('Statistics NZ'!T$15:T$29,'Statistics NZ'!T$115:T$129) -> 36353.123 | U27: =SUM('Statistics NZ'!U$27,$D$12/5*(U$8-U$9)*1000)*('Economic Forecasts'!W$10-'Economic Forecasts'!W$9)*1000000/SUM('Statistics NZ'!U$15:U$29,'Statistics NZ'!U$115:U$129,SUM($B$12:$D$13)*(U$8-U$9)*1000) -> 36437.561 | V27: =SUM('Statistics NZ'!V$27,$D$12/5*(V$8-V$9)*1000)*('Economic Forecasts'!X$10-'Economic Forecasts'!X$9)*1000000/SUM('Statistics NZ'!V$15:V$29,'Statistics NZ'!V$115:V$129,SUM($B$12:$D$13)*(V$8-V$9)*1000) -> 35907.969 | W27: =SUM('Statistics NZ'!W$27,$D$12/5*(W$8-W$9)*1000)*('Economic Forecasts'!Y$10-'Economic Forecasts'!Y$9)*1000000/SUM('Statistics NZ'!W$15:W$29,'Statistics NZ'!W$115:W$129,SUM($B$12:$D$13)*(W$8-W$9)*1000) -> 36442.127 | X27: =SUM('Statistics NZ'!X$27,$D$12/5*(X$8-X$9)*1000)*('Economic Forecasts'!Z$10-'Economic Forecasts'!Z$9)*1000000/SUM('Statistics NZ'!X$15:X$29,'Statistics NZ'!X$115:X$129,SUM($B$12:$D$13)*(X$8-X$9)*1000) -> 36417.408 | Y27: =SUM('Statistics NZ'!Y$27,$D$12/5*(Y$8-Y$9)*1000)*('Economic Forecasts'!AA$10-'Economic Forecasts'!AA$9)*1000000/SUM('Statistics NZ'!Y$15:Y$29,'Statistics NZ'!Y$115:Y$129,SUM($B$12:$D$13)*(Y$8-Y$9)*1000) -> 37377.832 | Z27: =SUM(Y$27,'Statistics NZ'!Z$27-'Statistics NZ'!Y$27,$D$12/5*(Z$8-Z$9)*1000) -> 36807.91 | AA27: =SUM(Z$27,'Statistics NZ'!AA$27-'Statistics NZ'!Z$27,$D$12/5*(AA$8-AA$9)*1000) -> 36869.957 | AB27: =SUM(AA$27,'Statistics NZ'!AB$27-'Statistics NZ'!AA$27,$D$12/5*(AB$8-AB$9)*1000) -> 36575.579 | AC27: =SUM(AB$27,'Statistics NZ'!AC$27-'Statistics NZ'!AB$27,$D$12/5*(AC$8-AC$9)*1000) -> 36755.579 | AD27: =SUM(AC$27,'Statistics NZ'!AD$27-'Statistics NZ'!AC$27,$D$12/5*(AD$8-AD$9)*1000) -> 37085.579 | AE27: =SUM(AD$27,'Statistics NZ'!AE$27-'Statistics NZ'!AD$27,$D$12/5*(AE$8-AE$9)*1000) -> 34515.579 | AF27: =SUM(AE$27,'Statistics NZ'!AF$27-'Statistics NZ'!AE$27,$D$12/5*(AF$8-AF$9)*1000) -> 34695.579 | AG27: =SUM(AF$27,'Statistics NZ'!AG$27-'Statistics NZ'!AF$27,$D$12/5*(AG$8-AG$9)*1000) -> 35245.579 | ... BI27: =SUM(BH$27,'Statistics NZ'!BI$27-'Statistics NZ'!BH$27,$D$12/5*(BI$8-BI$9)*1000) -> 37825.579
A28: 13 | B28: ='Statistics NZ'!B$28*('Economic Forecasts'!D$10-'Economic Forecasts'!D$9)*1000000/SUM('Statistics NZ'!B$15:B$29,'Statistics NZ'!B$115:B$129) -> 32601.626 | C28: ='Statistics NZ'!C$28*('Economic Forecasts'!E$10-'Economic Forecasts'!E$9)*1000000/SUM('Statistics NZ'!C$15:C$29,'Statistics NZ'!C$115:C$129) -> 31713.84 | D28: ='Statistics NZ'!D$28*('Economic Forecasts'!F$10-'Economic Forecasts'!F$9)*1000000/SUM('Statistics NZ'!D$15:D$29,'Statistics NZ'!D$115:D$129) -> 31761.026 | E28: ='Statistics NZ'!E$28*('Economic Forecasts'!G$10-'Economic Forecasts'!G$9)*1000000/SUM('Statistics NZ'!E$15:E$29,'Statistics NZ'!E$115:E$129) -> 31258.867 | F28: ='Statistics NZ'!F$28*('Economic Forecasts'!H$10-'Economic Forecasts'!H$9)*1000000/SUM('Statistics NZ'!F$15:F$29,'Statistics NZ'!F$115:F$129) -> 31273.242 | G28: ='Statistics NZ'!G$28*('Economic Forecasts'!I$10-'Economic Forecasts'!I$9)*1000000/SUM('Statistics NZ'!G$15:G$29,'Statistics NZ'!G$115:G$129) -> 31370.3 | H28: ='Statistics NZ'!H$28*('Economic Forecasts'!J$10-'Economic Forecasts'!J$9)*1000000/SUM('Statistics NZ'!H$15:H$29,'Statistics NZ'!H$115:H$129) -> 30647.822 | I28: ='Statistics NZ'!I$28*('Economic Forecasts'!K$10-'Economic Forecasts'!K$9)*1000000/SUM('Statistics NZ'!I$15:I$29,'Statistics NZ'!I$115:I$129) -> 31814.148 | ... T28: ='Statistics NZ'!T$28*('Economic Forecasts'!V$10-'Economic Forecasts'!V$9)*1000000/SUM('Statistics NZ'!T$15:T$29,'Statistics NZ'!T$115:T$129) -> 36586.837 | U28: =SUM('Statistics NZ'!U$28,$D$12/5*(U$8-U$9)*1000)*('Economic Forecasts'!W$10-'Economic Forecasts'!W$9)*1000000/SUM('Statistics NZ'!U$15:U$29,'Statistics NZ'!U$115:U$129,SUM($B$12:$D$13)*(U$8-U$9)*1000) -> 36756.876 | V28: =SUM('Statistics NZ'!V$28,$D$12/5*(V$8-V$9)*1000)*('Economic Forecasts'!X$10-'Economic Forecasts'!X$9)*1000000/SUM('Statistics NZ'!V$15:V$29,'Statistics NZ'!V$115:V$129,SUM($B$12:$D$13)*(V$8-V$9)*1000) -> 37156.723 | W28: =SUM('Statistics NZ'!W$28,$D$12/5*(W$8-W$9)*1000)*('Economic Forecasts'!Y$10-'Economic Forecasts'!Y$9)*1000000/SUM('Statistics NZ'!W$15:W$29,'Statistics NZ'!W$115:W$129,SUM($B$12:$D$13)*(W$8-W$9)*1000) -> 36692.954 | X28: =SUM('Statistics NZ'!X$28,$D$12/5*(X$8-X$9)*1000)*('Economic Forecasts'!Z$10-'Economic Forecasts'!Z$9)*1000000/SUM('Statistics NZ'!X$15:X$29,'Statistics NZ'!X$115:X$129,SUM($B$12:$D$13)*(X$8-X$9)*1000) -> 37234.7 | Y28: =SUM('Statistics NZ'!Y$28,$D$12/5*(Y$8-Y$9)*1000)*('Economic Forecasts'!AA$10-'Economic Forecasts'!AA$9)*1000000/SUM('Statistics NZ'!Y$15:Y$29,'Statistics NZ'!Y$115:Y$129,SUM($B$12:$D$13)*(Y$8-Y$9)*1000) -> 37176.769 | Z28: =SUM(Y$28,'Statistics NZ'!Z$28-'Statistics NZ'!Y$28,$D$12/5*(Z$8-Z$9)*1000) -> 37706.847 | AA28: =SUM(Z$28,'Statistics NZ'!AA$28-'Statistics NZ'!Z$28,$D$12/5*(AA$8-AA$9)*1000) -> 37128.894 | AB28: =SUM(AA$28,'Statistics NZ'!AB$28-'Statistics NZ'!AA$28,$D$12/5*(AB$8-AB$9)*1000) -> 37194.515 | AC28: =SUM(AB$28,'Statistics NZ'!AC$28-'Statistics NZ'!AB$28,$D$12/5*(AC$8-AC$9)*1000) -> 36904.515 | AD28: =SUM(AC$28,'Statistics NZ'!AD$28-'Statistics NZ'!AC$28,$D$12/5*(AD$8-AD$9)*1000) -> 37074.515 | AE28: =SUM(AD$28,'Statistics NZ'!AE$28-'Statistics NZ'!AD$28,$D$12/5*(AE$8-AE$9)*1000) -> 37404.515 | AF28: =SUM(AE$28,'Statistics NZ'!AF$28-'Statistics NZ'!AE$28,$D$12/5*(AF$8-AF$9)*1000) -> 34844.515 | AG28: =SUM(AF$28,'Statistics NZ'!AG$28-'Statistics NZ'!AF$28,$D$12/5*(AG$8-AG$9)*1000) -> 35024.515 | ... BI28: =SUM(BH$28,'Statistics NZ'!BI$28-'Statistics NZ'!BH$28,$D$12/5*(BI$8-BI$9)*1000) -> 38254.515
A29: 14 | B29: ='Statistics NZ'!B$29*('Economic Forecasts'!D$10-'Economic Forecasts'!D$9)*1000000/SUM('Statistics NZ'!B$15:B$29,'Statistics NZ'!B$115:B$129) -> 32824.271 | C29: ='Statistics NZ'!C$29*('Economic Forecasts'!E$10-'Economic Forecasts'!E$9)*1000000/SUM('Statistics NZ'!C$15:C$29,'Statistics NZ'!C$115:C$129) -> 32441.077 | D29: ='Statistics NZ'!D$29*('Economic Forecasts'!F$10-'Economic Forecasts'!F$9)*1000000/SUM('Statistics NZ'!D$15:D$29,'Statistics NZ'!D$115:D$129) -> 31750.481 | E29: ='Statistics NZ'!E$29*('Economic Forecasts'!G$10-'Economic Forecasts'!G$9)*1000000/SUM('Statistics NZ'!E$15:E$29,'Statistics NZ'!E$115:E$129) -> 31828.553 | F29: ='Statistics NZ'!F$29*('Economic Forecasts'!H$10-'Economic Forecasts'!H$9)*1000000/SUM('Statistics NZ'!F$15:F$29,'Statistics NZ'!F$115:F$129) -> 31526.895 | G29: ='Statistics NZ'!G$29*('Economic Forecasts'!I$10-'Economic Forecasts'!I$9)*1000000/SUM('Statistics NZ'!G$15:G$29,'Statistics NZ'!G$115:G$129) -> 31539.698 | H29: ='Statistics NZ'!H$29*('Economic Forecasts'!J$10-'Economic Forecasts'!J$9)*1000000/SUM('Statistics NZ'!H$15:H$29,'Statistics NZ'!H$115:H$129) -> 31485.31 | I29: ='Statistics NZ'!I$29*('Economic Forecasts'!K$10-'Economic Forecasts'!K$9)*1000000/SUM('Statistics NZ'!I$15:I$29,'Statistics NZ'!I$115:I$129) -> 30825.603 | ... T29: ='Statistics NZ'!T$29*('Economic Forecasts'!V$10-'Economic Forecasts'!V$9)*1000000/SUM('Statistics NZ'!T$15:T$29,'Statistics NZ'!T$115:T$129) -> 36905.537 | U29: =SUM('Statistics NZ'!U$29,$D$12/5*(U$8-U$9)*1000)*('Economic Forecasts'!W$10-'Economic Forecasts'!W$9)*1000000/SUM('Statistics NZ'!U$15:U$29,'Statistics NZ'!U$115:U$129,SUM($B$12:$D$13)*(U$8-U$9)*1000) -> 37012.329 | V29: =SUM('Statistics NZ'!V$29,$D$12/5*(V$8-V$9)*1000)*('Economic Forecasts'!X$10-'Economic Forecasts'!X$9)*1000000/SUM('Statistics NZ'!V$15:V$29,'Statistics NZ'!V$115:V$129,SUM($B$12:$D$13)*(V$8-V$9)*1000) -> 37511.972 | W29: =SUM('Statistics NZ'!W$29,$D$12/5*(W$8-W$9)*1000)*('Economic Forecasts'!Y$10-'Economic Forecasts'!Y$9)*1000000/SUM('Statistics NZ'!W$15:W$29,'Statistics NZ'!W$115:W$129,SUM($B$12:$D$13)*(W$8-W$9)*1000) -> 37979.805 | X29: =SUM('Statistics NZ'!X$29,$D$12/5*(X$8-X$9)*1000)*('Economic Forecasts'!Z$10-'Economic Forecasts'!Z$9)*1000000/SUM('Statistics NZ'!X$15:X$29,'Statistics NZ'!X$115:X$129,SUM($B$12:$D$13)*(X$8-X$9)*1000) -> 37521.857 | Y29: =SUM('Statistics NZ'!Y$29,$D$12/5*(Y$8-Y$9)*1000)*('Economic Forecasts'!AA$10-'Economic Forecasts'!AA$9)*1000000/SUM('Statistics NZ'!Y$15:Y$29,'Statistics NZ'!Y$115:Y$129,SUM($B$12:$D$13)*(Y$8-Y$9)*1000) -> 38048.043 | Z29: =SUM(Y$29,'Statistics NZ'!Z$29-'Statistics NZ'!Y$29,$D$12/5*(Z$8-Z$9)*1000) -> 37648.122 | AA29: =SUM(Z$29,'Statistics NZ'!AA$29-'Statistics NZ'!Z$29,$D$12/5*(AA$8-AA$9)*1000) -> 38170.168 | AB29: =SUM(AA$29,'Statistics NZ'!AB$29-'Statistics NZ'!AA$29,$D$12/5*(AB$8-AB$9)*1000) -> 37595.79 | AC29: =SUM(AB$29,'Statistics NZ'!AC$29-'Statistics NZ'!AB$29,$D$12/5*(AC$8-AC$9)*1000) -> 37655.79 | AD29: =SUM(AC$29,'Statistics NZ'!AD$29-'Statistics NZ'!AC$29,$D$12/5*(AD$8-AD$9)*1000) -> 37365.79 | AE29: =SUM(AD$29,'Statistics NZ'!AE$29-'Statistics NZ'!AD$29,$D$12/5*(AE$8-AE$9)*1000) -> 37545.79 | AF29: =SUM(AE$29,'Statistics NZ'!AF$29-'Statistics NZ'!AE$29,$D$12/5*(AF$8-AF$9)*1000) -> 37875.79 | AG29: =SUM(AF$29,'Statistics NZ'!AG$29-'Statistics NZ'!AF$29,$D$12/5*(AG$8-AG$9)*1000) -> 35315.79 | ... BI29: =SUM(BH$29,'Statistics NZ'!BI$29-'Statistics NZ'!BH$29,$D$12/5*(BI$8-BI$9)*1000) -> 38815.79
A30: 15 | B30: ='Statistics NZ'!B$30*'Economic Forecasts'!D$9*1000000/SUM('Statistics NZ'!B$30:B$110,'Statistics NZ'!B$130:B$210) -> 31337.963 | C30: ='Statistics NZ'!C$30*'Economic Forecasts'!E$9*1000000/SUM('Statistics NZ'!C$30:C$110,'Statistics NZ'!C$130:C$210) -> 30540.443 | D30: ='Statistics NZ'!D$30*'Economic Forecasts'!F$9*1000000/SUM('Statistics NZ'!D$30:D$110,'Statistics NZ'!D$130:D$210) -> 30322.748 | E30: ='Statistics NZ'!E$30*'Economic Forecasts'!G$9*1000000/SUM('Statistics NZ'!E$30:E$110,'Statistics NZ'!E$130:E$210) -> 29646.63 | F30: ='Statistics NZ'!F$30*'Economic Forecasts'!H$9*1000000/SUM('Statistics NZ'!F$30:F$110,'Statistics NZ'!F$130:F$210) -> 29828.656 | G30: ='Statistics NZ'!G$30*'Economic Forecasts'!I$9*1000000/SUM('Statistics NZ'!G$30:G$110,'Statistics NZ'!G$130:G$210) -> 29408.482 | H30: ='Statistics NZ'!H$30*'Economic Forecasts'!J$9*1000000/SUM('Statistics NZ'!H$30:H$110,'Statistics NZ'!H$130:H$210) -> 29495.062 | I30: ='Statistics NZ'!I$30*'Economic Forecasts'!K$9*1000000/SUM('Statistics NZ'!I$30:I$110,'Statistics NZ'!I$130:I$210) -> 29342.041 | ... T30: ='Statistics NZ'!T$30*'Economic Forecasts'!V$9*1000000/SUM('Statistics NZ'!T$30:T$110,'Statistics NZ'!T$130:T$210) -> 33798.391 | U30: =SUM('Statistics NZ'!U$30,$E$12/5*(U$8-U$9)*1000)*'Economic Forecasts'!W$9*1000000/SUM('Statistics NZ'!U$30:U$110,'Statistics NZ'!U$130:U$210,SUM($E$12:$T$13)*(U$8-U$9)*1000) -> 34813.465 | V30: =SUM('Statistics NZ'!V$30,$E$12/5*(V$8-V$9)*1000)*'Economic Forecasts'!X$9*1000000/SUM('Statistics NZ'!V$30:V$110,'Statistics NZ'!V$130:V$210,SUM($E$12:$T$13)*(V$8-V$9)*1000) -> 34802.24 | W30: =SUM('Statistics NZ'!W$30,$E$12/5*(W$8-W$9)*1000)*'Economic Forecasts'!Y$9*1000000/SUM('Statistics NZ'!W$30:W$110,'Statistics NZ'!W$130:W$210,SUM($E$12:$T$13)*(W$8-W$9)*1000) -> 34885.852 | X30: =SUM('Statistics NZ'!X$30,$E$12/5*(X$8-X$9)*1000)*'Economic Forecasts'!Z$9*1000000/SUM('Statistics NZ'!X$30:X$110,'Statistics NZ'!X$130:X$210,SUM($E$12:$T$13)*(X$8-X$9)*1000) -> 34886.175 | Y30: =SUM('Statistics NZ'!Y$30,$E$12/5*(Y$8-Y$9)*1000)*'Economic Forecasts'!AA$9*1000000/SUM('Statistics NZ'!Y$30:Y$110,'Statistics NZ'!Y$130:Y$210,SUM($E$12:$T$13)*(Y$8-Y$9)*1000) -> 34061.181 | Z30: =SUM(Y$30,'Statistics NZ'!Z$30-'Statistics NZ'!Y$30,$E$12/5*(Z$8-Z$9)*1000) -> 34188.886 | AA30: =SUM(Z$30,'Statistics NZ'!AA$30-'Statistics NZ'!Z$30,$E$12/5*(AA$8-AA$9)*1000) -> 33795.509 | AB30: =SUM(AA$30,'Statistics NZ'!AB$30-'Statistics NZ'!AA$30,$E$12/5*(AB$8-AB$9)*1000) -> 34313.267 | AC30: =SUM(AB$30,'Statistics NZ'!AC$30-'Statistics NZ'!AB$30,$E$12/5*(AC$8-AC$9)*1000) -> 33733.267 | AD30: =SUM(AC$30,'Statistics NZ'!AD$30-'Statistics NZ'!AC$30,$E$12/5*(AD$8-AD$9)*1000) -> 33793.267 | AE30: =SUM(AD$30,'Statistics NZ'!AE$30-'Statistics NZ'!AD$30,$E$12/5*(AE$8-AE$9)*1000) -> 33503.267 | AF30: =SUM(AE$30,'Statistics NZ'!AF$30-'Statistics NZ'!AE$30,$E$12/5*(AF$8-AF$9)*1000) -> 33683.267 | AG30: =SUM(AF$30,'Statistics NZ'!AG$30-'Statistics NZ'!AF$30,$E$12/5*(AG$8-AG$9)*1000) -> 34023.267 | ... BI30: =SUM(BH$30,'Statistics NZ'!BI$30-'Statistics NZ'!BH$30,$E$12/5*(BI$8-BI$9)*1000) -> 35043.267
A31: 16 | B31: ='Statistics NZ'!B$31*'Economic Forecasts'!D$9*1000000/SUM('Statistics NZ'!B$30:B$110,'Statistics NZ'!B$130:B$210) -> 31298.827 | C31: ='Statistics NZ'!C$31*'Economic Forecasts'!E$9*1000000/SUM('Statistics NZ'!C$30:C$110,'Statistics NZ'!C$130:C$210) -> 31591.192 | D31: ='Statistics NZ'!D$31*'Economic Forecasts'!F$9*1000000/SUM('Statistics NZ'!D$30:D$110,'Statistics NZ'!D$130:D$210) -> 30597.784 | E31: ='Statistics NZ'!E$31*'Economic Forecasts'!G$9*1000000/SUM('Statistics NZ'!E$30:E$110,'Statistics NZ'!E$130:E$210) -> 30480.227 | F31: ='Statistics NZ'!F$31*'Economic Forecasts'!H$9*1000000/SUM('Statistics NZ'!F$30:F$110,'Statistics NZ'!F$130:F$210) -> 29965.98 | G31: ='Statistics NZ'!G$31*'Economic Forecasts'!I$9*1000000/SUM('Statistics NZ'!G$30:G$110,'Statistics NZ'!G$130:G$210) -> 30184.457 | H31: ='Statistics NZ'!H$31*'Economic Forecasts'!J$9*1000000/SUM('Statistics NZ'!H$30:H$110,'Statistics NZ'!H$130:H$210) -> 29632.614 | I31: ='Statistics NZ'!I$31*'Economic Forecasts'!K$9*1000000/SUM('Statistics NZ'!I$30:I$110,'Statistics NZ'!I$130:I$210) -> 29753.79 | ... T31: ='Statistics NZ'!T$31*'Economic Forecasts'!V$9*1000000/SUM('Statistics NZ'!T$30:T$110,'Statistics NZ'!T$130:T$210) -> 34759.812 | U31: =SUM('Statistics NZ'!U$31,$E$12/5*(U$8-U$9)*1000)*'Economic Forecasts'!W$9*1000000/SUM('Statistics NZ'!U$30:U$110,'Statistics NZ'!U$130:U$210,SUM($E$12:$T$13)*(U$8-U$9)*1000) -> 34189.454 | V31: =SUM('Statistics NZ'!V$31,$E$12/5*(V$8-V$9)*1000)*'Economic Forecasts'!X$9*1000000/SUM('Statistics NZ'!V$30:V$110,'Statistics NZ'!V$130:V$210,SUM($E$12:$T$13)*(V$8-V$9)*1000) -> 35148.769 | W31: =SUM('Statistics NZ'!W$31,$E$12/5*(W$8-W$9)*1000)*'Economic Forecasts'!Y$9*1000000/SUM('Statistics NZ'!W$30:W$110,'Statistics NZ'!W$130:W$210,SUM($E$12:$T$13)*(W$8-W$9)*1000) -> 35163.136 | X31: =SUM('Statistics NZ'!X$31,$E$12/5*(X$8-X$9)*1000)*'Economic Forecasts'!Z$9*1000000/SUM('Statistics NZ'!X$30:X$110,'Statistics NZ'!X$130:X$210,SUM($E$12:$T$13)*(X$8-X$9)*1000) -> 35252.669 | Y31: =SUM('Statistics NZ'!Y$31,$E$12/5*(Y$8-Y$9)*1000)*'Economic Forecasts'!AA$9*1000000/SUM('Statistics NZ'!Y$30:Y$110,'Statistics NZ'!Y$130:Y$210,SUM($E$12:$T$13)*(Y$8-Y$9)*1000) -> 35270.067 | Z31: =SUM(Y$31,'Statistics NZ'!Z$31-'Statistics NZ'!Y$31,$E$12/5*(Z$8-Z$9)*1000) -> 34467.772 | AA31: =SUM(Z$31,'Statistics NZ'!AA$31-'Statistics NZ'!Z$31,$E$12/5*(AA$8-AA$9)*1000) -> 34594.395 | AB31: =SUM(AA$31,'Statistics NZ'!AB$31-'Statistics NZ'!AA$31,$E$12/5*(AB$8-AB$9)*1000) -> 34192.153 | AC31: =SUM(AB$31,'Statistics NZ'!AC$31-'Statistics NZ'!AB$31,$E$12/5*(AC$8-AC$9)*1000) -> 34702.153 | AD31: =SUM(AC$31,'Statistics NZ'!AD$31-'Statistics NZ'!AC$31,$E$12/5*(AD$8-AD$9)*1000) -> 34122.153 | AE31: =SUM(AD$31,'Statistics NZ'!AE$31-'Statistics NZ'!AD$31,$E$12/5*(AE$8-AE$9)*1000) -> 34192.153 | AF31: =SUM(AE$31,'Statistics NZ'!AF$31-'Statistics NZ'!AE$31,$E$12/5*(AF$8-AF$9)*1000) -> 33902.153 | AG31: =SUM(AF$31,'Statistics NZ'!AG$31-'Statistics NZ'!AF$31,$E$12/5*(AG$8-AG$9)*1000) -> 34082.153 | ... BI31: =SUM(BH$31,'Statistics NZ'!BI$31-'Statistics NZ'!BH$31,$E$12/5*(BI$8-BI$9)*1000) -> 35492.153
A32: 17 | B32: ='Statistics NZ'!B$32*'Economic Forecasts'!D$9*1000000/SUM('Statistics NZ'!B$30:B$110,'Statistics NZ'!B$130:B$210) -> 30212.809 | C32: ='Statistics NZ'!C$32*'Economic Forecasts'!E$9*1000000/SUM('Statistics NZ'!C$30:C$110,'Statistics NZ'!C$130:C$210) -> 31502.811 | D32: ='Statistics NZ'!D$32*'Economic Forecasts'!F$9*1000000/SUM('Statistics NZ'!D$30:D$110,'Statistics NZ'!D$130:D$210) -> 31756.866 | E32: ='Statistics NZ'!E$32*'Economic Forecasts'!G$9*1000000/SUM('Statistics NZ'!E$30:E$110,'Statistics NZ'!E$130:E$210) -> 30823.473 | F32: ='Statistics NZ'!F$32*'Economic Forecasts'!H$9*1000000/SUM('Statistics NZ'!F$30:F$110,'Statistics NZ'!F$130:F$210) -> 30819.348 | G32: ='Statistics NZ'!G$32*'Economic Forecasts'!I$9*1000000/SUM('Statistics NZ'!G$30:G$110,'Statistics NZ'!G$130:G$210) -> 30282.682 | H32: ='Statistics NZ'!H$32*'Economic Forecasts'!J$9*1000000/SUM('Statistics NZ'!H$30:H$110,'Statistics NZ'!H$130:H$210) -> 30349.849 | I32: ='Statistics NZ'!I$32*'Economic Forecasts'!K$9*1000000/SUM('Statistics NZ'!I$30:I$110,'Statistics NZ'!I$130:I$210) -> 29842.022 | ... T32: ='Statistics NZ'!T$32*'Economic Forecasts'!V$9*1000000/SUM('Statistics NZ'!T$30:T$110,'Statistics NZ'!T$130:T$210) -> 33996.622 | U32: =SUM('Statistics NZ'!U$32,$E$12/5*(U$8-U$9)*1000)*'Economic Forecasts'!W$9*1000000/SUM('Statistics NZ'!U$30:U$110,'Statistics NZ'!U$130:U$210,SUM($E$12:$T$13)*(U$8-U$9)*1000) -> 35080.899 | V32: =SUM('Statistics NZ'!V$32,$E$12/5*(V$8-V$9)*1000)*'Economic Forecasts'!X$9*1000000/SUM('Statistics NZ'!V$30:V$110,'Statistics NZ'!V$130:V$210,SUM($E$12:$T$13)*(V$8-V$9)*1000) -> 34465.613 | W32: =SUM('Statistics NZ'!W$32,$E$12/5*(W$8-W$9)*1000)*'Economic Forecasts'!Y$9*1000000/SUM('Statistics NZ'!W$30:W$110,'Statistics NZ'!W$130:W$210,SUM($E$12:$T$13)*(W$8-W$9)*1000) -> 35450.323 | X32: =SUM('Statistics NZ'!X$32,$E$12/5*(X$8-X$9)*1000)*'Economic Forecasts'!Z$9*1000000/SUM('Statistics NZ'!X$30:X$110,'Statistics NZ'!X$130:X$210,SUM($E$12:$T$13)*(X$8-X$9)*1000) -> 35470.585 | Y32: =SUM('Statistics NZ'!Y$32,$E$12/5*(Y$8-Y$9)*1000)*'Economic Forecasts'!AA$9*1000000/SUM('Statistics NZ'!Y$30:Y$110,'Statistics NZ'!Y$130:Y$210,SUM($E$12:$T$13)*(Y$8-Y$9)*1000) -> 35577.242 | Z32: =SUM(Y$32,'Statistics NZ'!Z$32-'Statistics NZ'!Y$32,$E$12/5*(Z$8-Z$9)*1000) -> 35634.948 | AA32: =SUM(Z$32,'Statistics NZ'!AA$32-'Statistics NZ'!Z$32,$E$12/5*(AA$8-AA$9)*1000) -> 34831.571 | AB32: =SUM(AA$32,'Statistics NZ'!AB$32-'Statistics NZ'!AA$32,$E$12/5*(AB$8-AB$9)*1000) -> 34939.329 | AC32: =SUM(AB$32,'Statistics NZ'!AC$32-'Statistics NZ'!AB$32,$E$12/5*(AC$8-AC$9)*1000) -> 34539.329 | AD32: =SUM(AC$32,'Statistics NZ'!AD$32-'Statistics NZ'!AC$32,$E$12/5*(AD$8-AD$9)*1000) -> 35049.329 | AE32: =SUM(AD$32,'Statistics NZ'!AE$32-'Statistics NZ'!AD$32,$E$12/5*(AE$8-AE$9)*1000) -> 34469.329 | AF32: =SUM(AE$32,'Statistics NZ'!AF$32-'Statistics NZ'!AE$32,$E$12/5*(AF$8-AF$9)*1000) -> 34539.329 | AG32: =SUM(AF$32,'Statistics NZ'!AG$32-'Statistics NZ'!AF$32,$E$12/5*(AG$8-AG$9)*1000) -> 34249.329 | ... BI32: =SUM(BH$32,'Statistics NZ'!BI$32-'Statistics NZ'!BH$32,$E$12/5*(BI$8-BI$9)*1000) -> 35879.329
A33: 18 | B33: ='Statistics NZ'!B$33*'Economic Forecasts'!D$9*1000000/SUM('Statistics NZ'!B$30:B$110,'Statistics NZ'!B$130:B$210) -> 29527.934 | C33: ='Statistics NZ'!C$33*'Economic Forecasts'!E$9*1000000/SUM('Statistics NZ'!C$30:C$110,'Statistics NZ'!C$130:C$210) -> 30019.979 | D33: ='Statistics NZ'!D$33*'Economic Forecasts'!F$9*1000000/SUM('Statistics NZ'!D$30:D$110,'Statistics NZ'!D$130:D$210) -> 31177.325 | E33: ='Statistics NZ'!E$33*'Economic Forecasts'!G$9*1000000/SUM('Statistics NZ'!E$30:E$110,'Statistics NZ'!E$130:E$210) -> 31559 | F33: ='Statistics NZ'!F$33*'Economic Forecasts'!H$9*1000000/SUM('Statistics NZ'!F$30:F$110,'Statistics NZ'!F$130:F$210) -> 30789.922 | G33: ='Statistics NZ'!G$33*'Economic Forecasts'!I$9*1000000/SUM('Statistics NZ'!G$30:G$110,'Statistics NZ'!G$130:G$210) -> 30695.226 | H33: ='Statistics NZ'!H$33*'Economic Forecasts'!J$9*1000000/SUM('Statistics NZ'!H$30:H$110,'Statistics NZ'!H$130:H$210) -> 30055.095 | I33: ='Statistics NZ'!I$33*'Economic Forecasts'!K$9*1000000/SUM('Statistics NZ'!I$30:I$110,'Statistics NZ'!I$130:I$210) -> 30165.54 | ... T33: ='Statistics NZ'!T$33*'Economic Forecasts'!V$9*1000000/SUM('Statistics NZ'!T$30:T$110,'Statistics NZ'!T$130:T$210) -> 32113.427 | U33: =SUM('Statistics NZ'!U$33,$E$12/5*(U$8-U$9)*1000)*'Economic Forecasts'!W$9*1000000/SUM('Statistics NZ'!U$30:U$110,'Statistics NZ'!U$130:U$210,SUM($E$12:$T$13)*(U$8-U$9)*1000) -> 34219.168 | V33: =SUM('Statistics NZ'!V$33,$E$12/5*(V$8-V$9)*1000)*'Economic Forecasts'!X$9*1000000/SUM('Statistics NZ'!V$30:V$110,'Statistics NZ'!V$130:V$210,SUM($E$12:$T$13)*(V$8-V$9)*1000) -> 35267.579 | W33: =SUM('Statistics NZ'!W$33,$E$12/5*(W$8-W$9)*1000)*'Economic Forecasts'!Y$9*1000000/SUM('Statistics NZ'!W$30:W$110,'Statistics NZ'!W$130:W$210,SUM($E$12:$T$13)*(W$8-W$9)*1000) -> 34667.986 | X33: =SUM('Statistics NZ'!X$33,$E$12/5*(X$8-X$9)*1000)*'Economic Forecasts'!Z$9*1000000/SUM('Statistics NZ'!X$30:X$110,'Statistics NZ'!X$130:X$210,SUM($E$12:$T$13)*(X$8-X$9)*1000) -> 35658.785 | Y33: =SUM('Statistics NZ'!Y$33,$E$12/5*(Y$8-Y$9)*1000)*'Economic Forecasts'!AA$9*1000000/SUM('Statistics NZ'!Y$30:Y$110,'Statistics NZ'!Y$130:Y$210,SUM($E$12:$T$13)*(Y$8-Y$9)*1000) -> 35696.149 | Z33: =SUM(Y$33,'Statistics NZ'!Z$33-'Statistics NZ'!Y$33,$E$12/5*(Z$8-Z$9)*1000) -> 35843.855 | AA33: =SUM(Z$33,'Statistics NZ'!AA$33-'Statistics NZ'!Z$33,$E$12/5*(AA$8-AA$9)*1000) -> 35890.478 | AB33: =SUM(AA$33,'Statistics NZ'!AB$33-'Statistics NZ'!AA$33,$E$12/5*(AB$8-AB$9)*1000) -> 35078.235 | AC33: =SUM(AB$33,'Statistics NZ'!AC$33-'Statistics NZ'!AB$33,$E$12/5*(AC$8-AC$9)*1000) -> 35188.235 | AD33: =SUM(AC$33,'Statistics NZ'!AD$33-'Statistics NZ'!AC$33,$E$12/5*(AD$8-AD$9)*1000) -> 34778.235 | AE33: =SUM(AD$33,'Statistics NZ'!AE$33-'Statistics NZ'!AD$33,$E$12/5*(AE$8-AE$9)*1000) -> 35298.235 | AF33: =SUM(AE$33,'Statistics NZ'!AF$33-'Statistics NZ'!AE$33,$E$12/5*(AF$8-AF$9)*1000) -> 34718.235 | AG33: =SUM(AF$33,'Statistics NZ'!AG$33-'Statistics NZ'!AF$33,$E$12/5*(AG$8-AG$9)*1000) -> 34788.235 | ... BI33: =SUM(BH$33,'Statistics NZ'!BI$33-'Statistics NZ'!BH$33,$E$12/5*(BI$8-BI$9)*1000) -> 36148.235
A34: 19 | B34: ='Statistics NZ'!B$34*'Economic Forecasts'!D$9*1000000/SUM('Statistics NZ'!B$30:B$110,'Statistics NZ'!B$130:B$210) -> 28441.916 | C34: ='Statistics NZ'!C$34*'Economic Forecasts'!E$9*1000000/SUM('Statistics NZ'!C$30:C$110,'Statistics NZ'!C$130:C$210) -> 29509.335 | D34: ='Statistics NZ'!D$34*'Economic Forecasts'!F$9*1000000/SUM('Statistics NZ'!D$30:D$110,'Statistics NZ'!D$130:D$210) -> 29900.371 | E34: ='Statistics NZ'!E$34*'Economic Forecasts'!G$9*1000000/SUM('Statistics NZ'!E$30:E$110,'Statistics NZ'!E$130:E$210) -> 31186.333 | F34: ='Statistics NZ'!F$34*'Economic Forecasts'!H$9*1000000/SUM('Statistics NZ'!F$30:F$110,'Statistics NZ'!F$130:F$210) -> 31868.893 | G34: ='Statistics NZ'!G$34*'Economic Forecasts'!I$9*1000000/SUM('Statistics NZ'!G$30:G$110,'Statistics NZ'!G$130:G$210) -> 30911.32 | H34: ='Statistics NZ'!H$34*'Economic Forecasts'!J$9*1000000/SUM('Statistics NZ'!H$30:H$110,'Statistics NZ'!H$130:H$210) -> 30791.98 | I34: ='Statistics NZ'!I$34*'Economic Forecasts'!K$9*1000000/SUM('Statistics NZ'!I$30:I$110,'Statistics NZ'!I$130:I$210) -> 30234.165 | ... T34: ='Statistics NZ'!T$34*'Economic Forecasts'!V$9*1000000/SUM('Statistics NZ'!T$30:T$110,'Statistics NZ'!T$130:T$210) -> 31647.584 | U34: =SUM('Statistics NZ'!U$34,$E$12/5*(U$8-U$9)*1000)*'Economic Forecasts'!W$9*1000000/SUM('Statistics NZ'!U$30:U$110,'Statistics NZ'!U$130:U$210,SUM($E$12:$T$13)*(U$8-U$9)*1000) -> 32307.513 | V34: =SUM('Statistics NZ'!V$34,$E$12/5*(V$8-V$9)*1000)*'Economic Forecasts'!X$9*1000000/SUM('Statistics NZ'!V$30:V$110,'Statistics NZ'!V$130:V$210,SUM($E$12:$T$13)*(V$8-V$9)*1000) -> 34366.604 | W34: =SUM('Statistics NZ'!W$34,$E$12/5*(W$8-W$9)*1000)*'Economic Forecasts'!Y$9*1000000/SUM('Statistics NZ'!W$30:W$110,'Statistics NZ'!W$130:W$210,SUM($E$12:$T$13)*(W$8-W$9)*1000) -> 35430.517 | X34: =SUM('Statistics NZ'!X$34,$E$12/5*(X$8-X$9)*1000)*'Economic Forecasts'!Z$9*1000000/SUM('Statistics NZ'!X$30:X$110,'Statistics NZ'!X$130:X$210,SUM($E$12:$T$13)*(X$8-X$9)*1000) -> 34836.648 | Y34: =SUM('Statistics NZ'!Y$34,$E$12/5*(Y$8-Y$9)*1000)*'Economic Forecasts'!AA$9*1000000/SUM('Statistics NZ'!Y$30:Y$110,'Statistics NZ'!Y$130:Y$210,SUM($E$12:$T$13)*(Y$8-Y$9)*1000) -> 35844.783 | Z34: =SUM(Y$34,'Statistics NZ'!Z$34-'Statistics NZ'!Y$34,$E$12/5*(Z$8-Z$9)*1000) -> 35922.488 | AA34: =SUM(Z$34,'Statistics NZ'!AA$34-'Statistics NZ'!Z$34,$E$12/5*(AA$8-AA$9)*1000) -> 36059.111 | AB34: =SUM(AA$34,'Statistics NZ'!AB$34-'Statistics NZ'!AA$34,$E$12/5*(AB$8-AB$9)*1000) -> 36096.869 | AC34: =SUM(AB$34,'Statistics NZ'!AC$34-'Statistics NZ'!AB$34,$E$12/5*(AC$8-AC$9)*1000) -> 35276.869 | AD34: =SUM(AC$34,'Statistics NZ'!AD$34-'Statistics NZ'!AC$34,$E$12/5*(AD$8-AD$9)*1000) -> 35386.869 | AE34: =SUM(AD$34,'Statistics NZ'!AE$34-'Statistics NZ'!AD$34,$E$12/5*(AE$8-AE$9)*1000) -> 34986.869 | AF34: =SUM(AE$34,'Statistics NZ'!AF$34-'Statistics NZ'!AE$34,$E$12/5*(AF$8-AF$9)*1000) -> 35506.869 | AG34: =SUM(AF$34,'Statistics NZ'!AG$34-'Statistics NZ'!AF$34,$E$12/5*(AG$8-AG$9)*1000) -> 34926.869 | ... BI34: =SUM(BH$34,'Statistics NZ'!BI$34-'Statistics NZ'!BH$34,$E$12/5*(BI$8-BI$9)*1000) -> 36336.869
A35: 20 | B35: ='Statistics NZ'!B$35*'Economic Forecasts'!D$9*1000000/SUM('Statistics NZ'!B$30:B$110,'Statistics NZ'!B$130:B$210) -> 29077.872 | C35: ='Statistics NZ'!C$35*'Economic Forecasts'!E$9*1000000/SUM('Statistics NZ'!C$30:C$110,'Statistics NZ'!C$130:C$210) -> 28507.687 | D35: ='Statistics NZ'!D$35*'Economic Forecasts'!F$9*1000000/SUM('Statistics NZ'!D$30:D$110,'Statistics NZ'!D$130:D$210) -> 29536.93 | E35: ='Statistics NZ'!E$35*'Economic Forecasts'!G$9*1000000/SUM('Statistics NZ'!E$30:E$110,'Statistics NZ'!E$130:E$210) -> 29960.455 | F35: ='Statistics NZ'!F$35*'Economic Forecasts'!H$9*1000000/SUM('Statistics NZ'!F$30:F$110,'Statistics NZ'!F$130:F$210) -> 31584.437 | G35: ='Statistics NZ'!G$35*'Economic Forecasts'!I$9*1000000/SUM('Statistics NZ'!G$30:G$110,'Statistics NZ'!G$130:G$210) -> 32198.064 | H35: ='Statistics NZ'!H$35*'Economic Forecasts'!J$9*1000000/SUM('Statistics NZ'!H$30:H$110,'Statistics NZ'!H$130:H$210) -> 31027.783 | I35: ='Statistics NZ'!I$35*'Economic Forecasts'!K$9*1000000/SUM('Statistics NZ'!I$30:I$110,'Statistics NZ'!I$130:I$210) -> 30969.431 | ... T35: ='Statistics NZ'!T$35*'Economic Forecasts'!V$9*1000000/SUM('Statistics NZ'!T$30:T$110,'Statistics NZ'!T$130:T$210) -> 31776.434 | U35: =SUM('Statistics NZ'!U$35,$F$12/5*(U$8-U$9)*1000)*'Economic Forecasts'!W$9*1000000/SUM('Statistics NZ'!U$30:U$110,'Statistics NZ'!U$130:U$210,SUM($E$12:$T$13)*(U$8-U$9)*1000) -> 31704.647 | V35: =SUM('Statistics NZ'!V$35,$F$12/5*(V$8-V$9)*1000)*'Economic Forecasts'!X$9*1000000/SUM('Statistics NZ'!V$30:V$110,'Statistics NZ'!V$130:V$210,SUM($E$12:$T$13)*(V$8-V$9)*1000) -> 32324.662 | W35: =SUM('Statistics NZ'!W$35,$F$12/5*(W$8-W$9)*1000)*'Economic Forecasts'!Y$9*1000000/SUM('Statistics NZ'!W$30:W$110,'Statistics NZ'!W$130:W$210,SUM($E$12:$T$13)*(W$8-W$9)*1000) -> 34422.974 | X35: =SUM('Statistics NZ'!X$35,$F$12/5*(X$8-X$9)*1000)*'Economic Forecasts'!Z$9*1000000/SUM('Statistics NZ'!X$30:X$110,'Statistics NZ'!X$130:X$210,SUM($E$12:$T$13)*(X$8-X$9)*1000) -> 35512.749 | Y35: =SUM('Statistics NZ'!Y$35,$F$12/5*(Y$8-Y$9)*1000)*'Economic Forecasts'!AA$9*1000000/SUM('Statistics NZ'!Y$30:Y$110,'Statistics NZ'!Y$130:Y$210,SUM($E$12:$T$13)*(Y$8-Y$9)*1000) -> 34962.94 | Z35: =SUM(Y$35,'Statistics NZ'!Z$35-'Statistics NZ'!Y$35,$F$12/5*(Z$8-Z$9)*1000) -> 35979.427 | AA35: =SUM(Z$35,'Statistics NZ'!AA$35-'Statistics NZ'!Z$35,$F$12/5*(AA$8-AA$9)*1000) -> 36037.319 | AB35: =SUM(AA$35,'Statistics NZ'!AB$35-'Statistics NZ'!AA$35,$F$12/5*(AB$8-AB$9)*1000) -> 36156.335 | AC35: =SUM(AB$35,'Statistics NZ'!AC$35-'Statistics NZ'!AB$35,$F$12/5*(AC$8-AC$9)*1000) -> 36186.335 | AD35: =SUM(AC$35,'Statistics NZ'!AD$35-'Statistics NZ'!AC$35,$F$12/5*(AD$8-AD$9)*1000) -> 35366.335 | AE35: =SUM(AD$35,'Statistics NZ'!AE$35-'Statistics NZ'!AD$35,$F$12/5*(AE$8-AE$9)*1000) -> 35476.335 | AF35: =SUM(AE$35,'Statistics NZ'!AF$35-'Statistics NZ'!AE$35,$F$12/5*(AF$8-AF$9)*1000) -> 35086.335 | AG35: =SUM(AF$35,'Statistics NZ'!AG$35-'Statistics NZ'!AF$35,$F$12/5*(AG$8-AG$9)*1000) -> 35596.335 | ... BI35: =SUM(BH$35,'Statistics NZ'!BI$35-'Statistics NZ'!BH$35,$F$12/5*(BI$8-BI$9)*1000) -> 36396.335
A36: 21 | B36: ='Statistics NZ'!B$36*'Economic Forecasts'!D$9*1000000/SUM('Statistics NZ'!B$30:B$110,'Statistics NZ'!B$130:B$210) -> 29009.385 | C36: ='Statistics NZ'!C$36*'Economic Forecasts'!E$9*1000000/SUM('Statistics NZ'!C$30:C$110,'Statistics NZ'!C$130:C$210) -> 28831.75 | D36: ='Statistics NZ'!D$36*'Economic Forecasts'!F$9*1000000/SUM('Statistics NZ'!D$30:D$110,'Statistics NZ'!D$130:D$210) -> 28250.153 | E36: ='Statistics NZ'!E$36*'Economic Forecasts'!G$9*1000000/SUM('Statistics NZ'!E$30:E$110,'Statistics NZ'!E$130:E$210) -> 29411.262 | F36: ='Statistics NZ'!F$36*'Economic Forecasts'!H$9*1000000/SUM('Statistics NZ'!F$30:F$110,'Statistics NZ'!F$130:F$210) -> 30054.259 | G36: ='Statistics NZ'!G$36*'Economic Forecasts'!I$9*1000000/SUM('Statistics NZ'!G$30:G$110,'Statistics NZ'!G$130:G$210) -> 31539.958 | H36: ='Statistics NZ'!H$36*'Economic Forecasts'!J$9*1000000/SUM('Statistics NZ'!H$30:H$110,'Statistics NZ'!H$130:H$210) -> 31882.57 | I36: ='Statistics NZ'!I$36*'Economic Forecasts'!K$9*1000000/SUM('Statistics NZ'!I$30:I$110,'Statistics NZ'!I$130:I$210) -> 30812.574 | ... T36: ='Statistics NZ'!T$36*'Economic Forecasts'!V$9*1000000/SUM('Statistics NZ'!T$30:T$110,'Statistics NZ'!T$130:T$210) -> 30953.776 | U36: =SUM('Statistics NZ'!U$36,$F$12/5*(U$8-U$9)*1000)*'Economic Forecasts'!W$9*1000000/SUM('Statistics NZ'!U$30:U$110,'Statistics NZ'!U$130:U$210,SUM($E$12:$T$13)*(U$8-U$9)*1000) -> 31674.933 | V36: =SUM('Statistics NZ'!V$36,$F$12/5*(V$8-V$9)*1000)*'Economic Forecasts'!X$9*1000000/SUM('Statistics NZ'!V$30:V$110,'Statistics NZ'!V$130:V$210,SUM($E$12:$T$13)*(V$8-V$9)*1000) -> 31671.208 | W36: =SUM('Statistics NZ'!W$36,$F$12/5*(W$8-W$9)*1000)*'Economic Forecasts'!Y$9*1000000/SUM('Statistics NZ'!W$30:W$110,'Statistics NZ'!W$130:W$210,SUM($E$12:$T$13)*(W$8-W$9)*1000) -> 32323.539 | X36: =SUM('Statistics NZ'!X$36,$F$12/5*(X$8-X$9)*1000)*'Economic Forecasts'!Z$9*1000000/SUM('Statistics NZ'!X$30:X$110,'Statistics NZ'!X$130:X$210,SUM($E$12:$T$13)*(X$8-X$9)*1000) -> 34442.981 | Y36: =SUM('Statistics NZ'!Y$36,$F$12/5*(Y$8-Y$9)*1000)*'Economic Forecasts'!AA$9*1000000/SUM('Statistics NZ'!Y$30:Y$110,'Statistics NZ'!Y$130:Y$210,SUM($E$12:$T$13)*(Y$8-Y$9)*1000) -> 35557.474 | Z36: =SUM(Y$36,'Statistics NZ'!Z$36-'Statistics NZ'!Y$36,$F$12/5*(Z$8-Z$9)*1000) -> 34983.961 | AA36: =SUM(Z$36,'Statistics NZ'!AA$36-'Statistics NZ'!Z$36,$F$12/5*(AA$8-AA$9)*1000) -> 36011.853 | AB36: =SUM(AA$36,'Statistics NZ'!AB$36-'Statistics NZ'!AA$36,$F$12/5*(AB$8-AB$9)*1000) -> 36070.869 | AC36: =SUM(AB$36,'Statistics NZ'!AC$36-'Statistics NZ'!AB$36,$F$12/5*(AC$8-AC$9)*1000) -> 36190.869 | AD36: =SUM(AC$36,'Statistics NZ'!AD$36-'Statistics NZ'!AC$36,$F$12/5*(AD$8-AD$9)*1000) -> 36230.869 | AE36: =SUM(AD$36,'Statistics NZ'!AE$36-'Statistics NZ'!AD$36,$F$12/5*(AE$8-AE$9)*1000) -> 35410.869 | AF36: =SUM(AE$36,'Statistics NZ'!AF$36-'Statistics NZ'!AE$36,$F$12/5*(AF$8-AF$9)*1000) -> 35530.869 | AG36: =SUM(AF$36,'Statistics NZ'!AG$36-'Statistics NZ'!AF$36,$F$12/5*(AG$8-AG$9)*1000) -> 35130.869 | ... BI36: =SUM(BH$36,'Statistics NZ'!BI$36-'Statistics NZ'!BH$36,$F$12/5*(BI$8-BI$9)*1000) -> 36370.869
A37: 22 | B37: ='Statistics NZ'!B$37*'Economic Forecasts'!D$9*1000000/SUM('Statistics NZ'!B$30:B$110,'Statistics NZ'!B$130:B$210) -> 28608.243 | C37: ='Statistics NZ'!C$37*'Economic Forecasts'!E$9*1000000/SUM('Statistics NZ'!C$30:C$110,'Statistics NZ'!C$130:C$210) -> 28537.147 | D37: ='Statistics NZ'!D$37*'Economic Forecasts'!F$9*1000000/SUM('Statistics NZ'!D$30:D$110,'Statistics NZ'!D$130:D$210) -> 28250.153 | E37: ='Statistics NZ'!E$37*'Economic Forecasts'!G$9*1000000/SUM('Statistics NZ'!E$30:E$110,'Statistics NZ'!E$130:E$210) -> 27950.015 | F37: ='Statistics NZ'!F$37*'Economic Forecasts'!H$9*1000000/SUM('Statistics NZ'!F$30:F$110,'Statistics NZ'!F$130:F$210) -> 29259.744 | G37: ='Statistics NZ'!G$37*'Economic Forecasts'!I$9*1000000/SUM('Statistics NZ'!G$30:G$110,'Statistics NZ'!G$130:G$210) -> 29683.511 | H37: ='Statistics NZ'!H$37*'Economic Forecasts'!J$9*1000000/SUM('Statistics NZ'!H$30:H$110,'Statistics NZ'!H$130:H$210) -> 30850.931 | I37: ='Statistics NZ'!I$37*'Economic Forecasts'!K$9*1000000/SUM('Statistics NZ'!I$30:I$110,'Statistics NZ'!I$130:I$210) -> 31440.002 | ... T37: ='Statistics NZ'!T$37*'Economic Forecasts'!V$9*1000000/SUM('Statistics NZ'!T$30:T$110,'Statistics NZ'!T$130:T$210) -> 31072.714 | U37: =SUM('Statistics NZ'!U$37,$F$12/5*(U$8-U$9)*1000)*'Economic Forecasts'!W$9*1000000/SUM('Statistics NZ'!U$30:U$110,'Statistics NZ'!U$130:U$210,SUM($E$12:$T$13)*(U$8-U$9)*1000) -> 30833.012 | V37: =SUM('Statistics NZ'!V$37,$F$12/5*(V$8-V$9)*1000)*'Economic Forecasts'!X$9*1000000/SUM('Statistics NZ'!V$30:V$110,'Statistics NZ'!V$130:V$210,SUM($E$12:$T$13)*(V$8-V$9)*1000) -> 31621.704 | W37: =SUM('Statistics NZ'!W$37,$F$12/5*(W$8-W$9)*1000)*'Economic Forecasts'!Y$9*1000000/SUM('Statistics NZ'!W$30:W$110,'Statistics NZ'!W$130:W$210,SUM($E$12:$T$13)*(W$8-W$9)*1000) -> 31669.941 | X37: =SUM('Statistics NZ'!X$37,$F$12/5*(X$8-X$9)*1000)*'Economic Forecasts'!Z$9*1000000/SUM('Statistics NZ'!X$30:X$110,'Statistics NZ'!X$130:X$210,SUM($E$12:$T$13)*(X$8-X$9)*1000) -> 32352.971 | Y37: =SUM('Statistics NZ'!Y$37,$F$12/5*(Y$8-Y$9)*1000)*'Economic Forecasts'!AA$9*1000000/SUM('Statistics NZ'!Y$30:Y$110,'Statistics NZ'!Y$130:Y$210,SUM($E$12:$T$13)*(Y$8-Y$9)*1000) -> 34487.313 | Z37: =SUM(Y$37,'Statistics NZ'!Z$37-'Statistics NZ'!Y$37,$F$12/5*(Z$8-Z$9)*1000) -> 35603.799 | AA37: =SUM(Z$37,'Statistics NZ'!AA$37-'Statistics NZ'!Z$37,$F$12/5*(AA$8-AA$9)*1000) -> 35041.691 | AB37: =SUM(AA$37,'Statistics NZ'!AB$37-'Statistics NZ'!AA$37,$F$12/5*(AB$8-AB$9)*1000) -> 36070.708 | AC37: =SUM(AB$37,'Statistics NZ'!AC$37-'Statistics NZ'!AB$37,$F$12/5*(AC$8-AC$9)*1000) -> 36130.708 | AD37: =SUM(AC$37,'Statistics NZ'!AD$37-'Statistics NZ'!AC$37,$F$12/5*(AD$8-AD$9)*1000) -> 36250.708 | AE37: =SUM(AD$37,'Statistics NZ'!AE$37-'Statistics NZ'!AD$37,$F$12/5*(AE$8-AE$9)*1000) -> 36290.708 | AF37: =SUM(AE$37,'Statistics NZ'!AF$37-'Statistics NZ'!AE$37,$F$12/5*(AF$8-AF$9)*1000) -> 35480.708 | AG37: =SUM(AF$37,'Statistics NZ'!AG$37-'Statistics NZ'!AF$37,$F$12/5*(AG$8-AG$9)*1000) -> 35600.708 | ... BI37: =SUM(BH$37,'Statistics NZ'!BI$37-'Statistics NZ'!BH$37,$F$12/5*(BI$8-BI$9)*1000) -> 36350.708
A38: 23 | B38: ='Statistics NZ'!B$38*'Economic Forecasts'!D$9*1000000/SUM('Statistics NZ'!B$30:B$110,'Statistics NZ'!B$130:B$210) -> 28256.021 | C38: ='Statistics NZ'!C$38*'Economic Forecasts'!E$9*1000000/SUM('Statistics NZ'!C$30:C$110,'Statistics NZ'!C$130:C$210) -> 28134.524 | D38: ='Statistics NZ'!D$38*'Economic Forecasts'!F$9*1000000/SUM('Statistics NZ'!D$30:D$110,'Statistics NZ'!D$130:D$210) -> 28014.408 | E38: ='Statistics NZ'!E$38*'Economic Forecasts'!G$9*1000000/SUM('Statistics NZ'!E$30:E$110,'Statistics NZ'!E$130:E$210) -> 27832.331 | F38: ='Statistics NZ'!F$38*'Economic Forecasts'!H$9*1000000/SUM('Statistics NZ'!F$30:F$110,'Statistics NZ'!F$130:F$210) -> 27857.081 | G38: ='Statistics NZ'!G$38*'Economic Forecasts'!I$9*1000000/SUM('Statistics NZ'!G$30:G$110,'Statistics NZ'!G$130:G$210) -> 28917.358 | H38: ='Statistics NZ'!H$38*'Economic Forecasts'!J$9*1000000/SUM('Statistics NZ'!H$30:H$110,'Statistics NZ'!H$130:H$210) -> 29210.133 | I38: ='Statistics NZ'!I$38*'Economic Forecasts'!K$9*1000000/SUM('Statistics NZ'!I$30:I$110,'Statistics NZ'!I$130:I$210) -> 30420.432 | ... T38: ='Statistics NZ'!T$38*'Economic Forecasts'!V$9*1000000/SUM('Statistics NZ'!T$30:T$110,'Statistics NZ'!T$130:T$210) -> 31895.373 | U38: =SUM('Statistics NZ'!U$38,$F$12/5*(U$8-U$9)*1000)*'Economic Forecasts'!W$9*1000000/SUM('Statistics NZ'!U$30:U$110,'Statistics NZ'!U$130:U$210,SUM($E$12:$T$13)*(U$8-U$9)*1000) -> 31001.396 | V38: =SUM('Statistics NZ'!V$38,$F$12/5*(V$8-V$9)*1000)*'Economic Forecasts'!X$9*1000000/SUM('Statistics NZ'!V$30:V$110,'Statistics NZ'!V$130:V$210,SUM($E$12:$T$13)*(V$8-V$9)*1000) -> 30839.539 | W38: =SUM('Statistics NZ'!W$38,$F$12/5*(W$8-W$9)*1000)*'Economic Forecasts'!Y$9*1000000/SUM('Statistics NZ'!W$30:W$110,'Statistics NZ'!W$130:W$210,SUM($E$12:$T$13)*(W$8-W$9)*1000) -> 31679.844 | X38: =SUM('Statistics NZ'!X$38,$F$12/5*(X$8-X$9)*1000)*'Economic Forecasts'!Z$9*1000000/SUM('Statistics NZ'!X$30:X$110,'Statistics NZ'!X$130:X$210,SUM($E$12:$T$13)*(X$8-X$9)*1000) -> 31748.75 | Y38: =SUM('Statistics NZ'!Y$38,$F$12/5*(Y$8-Y$9)*1000)*'Economic Forecasts'!AA$9*1000000/SUM('Statistics NZ'!Y$30:Y$110,'Statistics NZ'!Y$130:Y$210,SUM($E$12:$T$13)*(Y$8-Y$9)*1000) -> 32455.988 | Z38: =SUM(Y$38,'Statistics NZ'!Z$38-'Statistics NZ'!Y$38,$F$12/5*(Z$8-Z$9)*1000) -> 34602.475 | AA38: =SUM(Z$38,'Statistics NZ'!AA$38-'Statistics NZ'!Z$38,$F$12/5*(AA$8-AA$9)*1000) -> 35730.367 | AB38: =SUM(AA$38,'Statistics NZ'!AB$38-'Statistics NZ'!AA$38,$F$12/5*(AB$8-AB$9)*1000) -> 35169.383 | AC38: =SUM(AB$38,'Statistics NZ'!AC$38-'Statistics NZ'!AB$38,$F$12/5*(AC$8-AC$9)*1000) -> 36209.383 | AD38: =SUM(AC$38,'Statistics NZ'!AD$38-'Statistics NZ'!AC$38,$F$12/5*(AD$8-AD$9)*1000) -> 36269.383 | AE38: =SUM(AD$38,'Statistics NZ'!AE$38-'Statistics NZ'!AD$38,$F$12/5*(AE$8-AE$9)*1000) -> 36399.383 | AF38: =SUM(AE$38,'Statistics NZ'!AF$38-'Statistics NZ'!AE$38,$F$12/5*(AF$8-AF$9)*1000) -> 36439.383 | AG38: =SUM(AF$38,'Statistics NZ'!AG$38-'Statistics NZ'!AF$38,$F$12/5*(AG$8-AG$9)*1000) -> 35629.383 | ... BI38: =SUM(BH$38,'Statistics NZ'!BI$38-'Statistics NZ'!BH$38,$F$12/5*(BI$8-BI$9)*1000) -> 36389.383
A39: 24 | B39: ='Statistics NZ'!B$39*'Economic Forecasts'!D$9*1000000/SUM('Statistics NZ'!B$30:B$110,'Statistics NZ'!B$130:B$210) -> 27258.059 | C39: ='Statistics NZ'!C$39*'Economic Forecasts'!E$9*1000000/SUM('Statistics NZ'!C$30:C$110,'Statistics NZ'!C$130:C$210) -> 27928.303 | D39: ='Statistics NZ'!D$39*'Economic Forecasts'!F$9*1000000/SUM('Statistics NZ'!D$30:D$110,'Statistics NZ'!D$130:D$210) -> 27749.194 | E39: ='Statistics NZ'!E$39*'Economic Forecasts'!G$9*1000000/SUM('Statistics NZ'!E$30:E$110,'Statistics NZ'!E$130:E$210) -> 27763.682 | F39: ='Statistics NZ'!F$39*'Economic Forecasts'!H$9*1000000/SUM('Statistics NZ'!F$30:F$110,'Statistics NZ'!F$130:F$210) -> 27709.949 | G39: ='Statistics NZ'!G$39*'Economic Forecasts'!I$9*1000000/SUM('Statistics NZ'!G$30:G$110,'Statistics NZ'!G$130:G$210) -> 27679.727 | H39: ='Statistics NZ'!H$39*'Economic Forecasts'!J$9*1000000/SUM('Statistics NZ'!H$30:H$110,'Statistics NZ'!H$130:H$210) -> 28630.45 | I39: ='Statistics NZ'!I$39*'Economic Forecasts'!K$9*1000000/SUM('Statistics NZ'!I$30:I$110,'Statistics NZ'!I$130:I$210) -> 29038.131 | ... T39: ='Statistics NZ'!T$39*'Economic Forecasts'!V$9*1000000/SUM('Statistics NZ'!T$30:T$110,'Statistics NZ'!T$130:T$210) -> 32519.801 | U39: =SUM('Statistics NZ'!U$39,$F$12/5*(U$8-U$9)*1000)*'Economic Forecasts'!W$9*1000000/SUM('Statistics NZ'!U$30:U$110,'Statistics NZ'!U$130:U$210,SUM($E$12:$T$13)*(U$8-U$9)*1000) -> 31972.081 | V39: =SUM('Statistics NZ'!V$39,$F$12/5*(V$8-V$9)*1000)*'Economic Forecasts'!X$9*1000000/SUM('Statistics NZ'!V$30:V$110,'Statistics NZ'!V$130:V$210,SUM($E$12:$T$13)*(V$8-V$9)*1000) -> 31166.266 | W39: =SUM('Statistics NZ'!W$39,$F$12/5*(W$8-W$9)*1000)*'Economic Forecasts'!Y$9*1000000/SUM('Statistics NZ'!W$30:W$110,'Statistics NZ'!W$130:W$210,SUM($E$12:$T$13)*(W$8-W$9)*1000) -> 31055.955 | X39: =SUM('Statistics NZ'!X$39,$F$12/5*(X$8-X$9)*1000)*'Economic Forecasts'!Z$9*1000000/SUM('Statistics NZ'!X$30:X$110,'Statistics NZ'!X$130:X$210,SUM($E$12:$T$13)*(X$8-X$9)*1000) -> 31927.045 | Y39: =SUM('Statistics NZ'!Y$39,$F$12/5*(Y$8-Y$9)*1000)*'Economic Forecasts'!AA$9*1000000/SUM('Statistics NZ'!Y$30:Y$110,'Statistics NZ'!Y$130:Y$210,SUM($E$12:$T$13)*(Y$8-Y$9)*1000) -> 32029.905 | Z39: =SUM(Y$39,'Statistics NZ'!Z$39-'Statistics NZ'!Y$39,$F$12/5*(Z$8-Z$9)*1000) -> 32736.392 | AA39: =SUM(Z$39,'Statistics NZ'!AA$39-'Statistics NZ'!Z$39,$F$12/5*(AA$8-AA$9)*1000) -> 34894.284 | AB39: =SUM(AA$39,'Statistics NZ'!AB$39-'Statistics NZ'!AA$39,$F$12/5*(AB$8-AB$9)*1000) -> 36013.3 | AC39: =SUM(AB$39,'Statistics NZ'!AC$39-'Statistics NZ'!AB$39,$F$12/5*(AC$8-AC$9)*1000) -> 35463.3 | AD39: =SUM(AC$39,'Statistics NZ'!AD$39-'Statistics NZ'!AC$39,$F$12/5*(AD$8-AD$9)*1000) -> 36503.3 | AE39: =SUM(AD$39,'Statistics NZ'!AE$39-'Statistics NZ'!AD$39,$F$12/5*(AE$8-AE$9)*1000) -> 36563.3 | AF39: =SUM(AE$39,'Statistics NZ'!AF$39-'Statistics NZ'!AE$39,$F$12/5*(AF$8-AF$9)*1000) -> 36703.3 | AG39: =SUM(AF$39,'Statistics NZ'!AG$39-'Statistics NZ'!AF$39,$F$12/5*(AG$8-AG$9)*1000) -> 36743.3 | ... BI39: =SUM(BH$39,'Statistics NZ'!BI$39-'Statistics NZ'!BH$39,$F$12/5*(BI$8-BI$9)*1000) -> 36563.3
A40: 25 | B40: ='Statistics NZ'!B$40*'Economic Forecasts'!D$9*1000000/SUM('Statistics NZ'!B$30:B$110,'Statistics NZ'!B$130:B$210) -> 26553.616 | C40: ='Statistics NZ'!C$40*'Economic Forecasts'!E$9*1000000/SUM('Statistics NZ'!C$30:C$110,'Statistics NZ'!C$130:C$210) -> 27162.336 | D40: ='Statistics NZ'!D$40*'Economic Forecasts'!F$9*1000000/SUM('Statistics NZ'!D$30:D$110,'Statistics NZ'!D$130:D$210) -> 27552.74 | E40: ='Statistics NZ'!E$40*'Economic Forecasts'!G$9*1000000/SUM('Statistics NZ'!E$30:E$110,'Statistics NZ'!E$130:E$210) -> 27626.384 | F40: ='Statistics NZ'!F$40*'Economic Forecasts'!H$9*1000000/SUM('Statistics NZ'!F$30:F$110,'Statistics NZ'!F$130:F$210) -> 27719.757 | G40: ='Statistics NZ'!G$40*'Economic Forecasts'!I$9*1000000/SUM('Statistics NZ'!G$30:G$110,'Statistics NZ'!G$130:G$210) -> 27620.792 | H40: ='Statistics NZ'!H$40*'Economic Forecasts'!J$9*1000000/SUM('Statistics NZ'!H$30:H$110,'Statistics NZ'!H$130:H$210) -> 27539.859 | I40: ='Statistics NZ'!I$40*'Economic Forecasts'!K$9*1000000/SUM('Statistics NZ'!I$30:I$110,'Statistics NZ'!I$130:I$210) -> 28665.596 | ... T40: ='Statistics NZ'!T$40*'Economic Forecasts'!V$9*1000000/SUM('Statistics NZ'!T$30:T$110,'Statistics NZ'!T$130:T$210) -> 31449.353 | U40: =SUM('Statistics NZ'!U$40,$G$12/5*(U$8-U$9)*1000)*'Economic Forecasts'!W$9*1000000/SUM('Statistics NZ'!U$30:U$110,'Statistics NZ'!U$130:U$210,SUM($E$12:$T$13)*(U$8-U$9)*1000) -> 32941.523 | V40: =SUM('Statistics NZ'!V$40,$G$12/5*(V$8-V$9)*1000)*'Economic Forecasts'!X$9*1000000/SUM('Statistics NZ'!V$30:V$110,'Statistics NZ'!V$130:V$210,SUM($E$12:$T$13)*(V$8-V$9)*1000) -> 32478.276 | W40: =SUM('Statistics NZ'!W$40,$G$12/5*(W$8-W$9)*1000)*'Economic Forecasts'!Y$9*1000000/SUM('Statistics NZ'!W$30:W$110,'Statistics NZ'!W$130:W$210,SUM($E$12:$T$13)*(W$8-W$9)*1000) -> 31709.079 | X40: =SUM('Statistics NZ'!X$40,$G$12/5*(X$8-X$9)*1000)*'Economic Forecasts'!Z$9*1000000/SUM('Statistics NZ'!X$30:X$110,'Statistics NZ'!X$130:X$210,SUM($E$12:$T$13)*(X$8-X$9)*1000) -> 31595.56 | Y40: =SUM('Statistics NZ'!Y$40,$G$12/5*(Y$8-Y$9)*1000)*'Economic Forecasts'!AA$9*1000000/SUM('Statistics NZ'!Y$30:Y$110,'Statistics NZ'!Y$130:Y$210,SUM($E$12:$T$13)*(Y$8-Y$9)*1000) -> 32461.379 | Z40: =SUM(Y$40,'Statistics NZ'!Z$40-'Statistics NZ'!Y$40,$G$12/5*(Z$8-Z$9)*1000) -> 32611.266 | AA40: =SUM(Z$40,'Statistics NZ'!AA$40-'Statistics NZ'!Z$40,$G$12/5*(AA$8-AA$9)*1000) -> 33361.198 | AB40: =SUM(AA$40,'Statistics NZ'!AB$40-'Statistics NZ'!AA$40,$G$12/5*(AB$8-AB$9)*1000) -> 35535.167 | AC40: =SUM(AB$40,'Statistics NZ'!AC$40-'Statistics NZ'!AB$40,$G$12/5*(AC$8-AC$9)*1000) -> 36665.167 | AD40: =SUM(AC$40,'Statistics NZ'!AD$40-'Statistics NZ'!AC$40,$G$12/5*(AD$8-AD$9)*1000) -> 36115.167 | AE40: =SUM(AD$40,'Statistics NZ'!AE$40-'Statistics NZ'!AD$40,$G$12/5*(AE$8-AE$9)*1000) -> 37165.167 | AF40: =SUM(AE$40,'Statistics NZ'!AF$40-'Statistics NZ'!AE$40,$G$12/5*(AF$8-AF$9)*1000) -> 37225.167 | AG40: =SUM(AF$40,'Statistics NZ'!AG$40-'Statistics NZ'!AF$40,$G$12/5*(AG$8-AG$9)*1000) -> 37365.167 | ... BI40: =SUM(BH$40,'Statistics NZ'!BI$40-'Statistics NZ'!BH$40,$G$12/5*(BI$8-BI$9)*1000) -> 37065.167
A41: 26 | B41: ='Statistics NZ'!B$41*'Economic Forecasts'!D$9*1000000/SUM('Statistics NZ'!B$30:B$110,'Statistics NZ'!B$130:B$210) -> 26230.745 | C41: ='Statistics NZ'!C$41*'Economic Forecasts'!E$9*1000000/SUM('Statistics NZ'!C$30:C$110,'Statistics NZ'!C$130:C$210) -> 26710.613 | D41: ='Statistics NZ'!D$41*'Economic Forecasts'!F$9*1000000/SUM('Statistics NZ'!D$30:D$110,'Statistics NZ'!D$130:D$210) -> 27022.313 | E41: ='Statistics NZ'!E$41*'Economic Forecasts'!G$9*1000000/SUM('Statistics NZ'!E$30:E$110,'Statistics NZ'!E$130:E$210) -> 27489.085 | F41: ='Statistics NZ'!F$41*'Economic Forecasts'!H$9*1000000/SUM('Statistics NZ'!F$30:F$110,'Statistics NZ'!F$130:F$210) -> 27749.184 | G41: ='Statistics NZ'!G$41*'Economic Forecasts'!I$9*1000000/SUM('Statistics NZ'!G$30:G$110,'Statistics NZ'!G$130:G$210) -> 27561.857 | H41: ='Statistics NZ'!H$41*'Economic Forecasts'!J$9*1000000/SUM('Statistics NZ'!H$30:H$110,'Statistics NZ'!H$130:H$210) -> 27490.734 | I41: ='Statistics NZ'!I$41*'Economic Forecasts'!K$9*1000000/SUM('Statistics NZ'!I$30:I$110,'Statistics NZ'!I$130:I$210) -> 27685.24 | ... T41: ='Statistics NZ'!T$41*'Economic Forecasts'!V$9*1000000/SUM('Statistics NZ'!T$30:T$110,'Statistics NZ'!T$130:T$210) -> 33104.582 | U41: =SUM('Statistics NZ'!U$41,$G$12/5*(U$8-U$9)*1000)*'Economic Forecasts'!W$9*1000000/SUM('Statistics NZ'!U$30:U$110,'Statistics NZ'!U$130:U$210,SUM($E$12:$T$13)*(U$8-U$9)*1000) -> 31990.648 | V41: =SUM('Statistics NZ'!V$41,$G$12/5*(V$8-V$9)*1000)*'Economic Forecasts'!X$9*1000000/SUM('Statistics NZ'!V$30:V$110,'Statistics NZ'!V$130:V$210,SUM($E$12:$T$13)*(V$8-V$9)*1000) -> 33408.953 | W41: =SUM('Statistics NZ'!W$41,$G$12/5*(W$8-W$9)*1000)*'Economic Forecasts'!Y$9*1000000/SUM('Statistics NZ'!W$30:W$110,'Statistics NZ'!W$130:W$210,SUM($E$12:$T$13)*(W$8-W$9)*1000) -> 32976.662 | X41: =SUM('Statistics NZ'!X$41,$G$12/5*(X$8-X$9)*1000)*'Economic Forecasts'!Z$9*1000000/SUM('Statistics NZ'!X$30:X$110,'Statistics NZ'!X$130:X$210,SUM($E$12:$T$13)*(X$8-X$9)*1000) -> 32219.591 | Y41: =SUM('Statistics NZ'!Y$41,$G$12/5*(Y$8-Y$9)*1000)*'Economic Forecasts'!AA$9*1000000/SUM('Statistics NZ'!Y$30:Y$110,'Statistics NZ'!Y$130:Y$210,SUM($E$12:$T$13)*(Y$8-Y$9)*1000) -> 32144.294 | Z41: =SUM(Y$41,'Statistics NZ'!Z$41-'Statistics NZ'!Y$41,$G$12/5*(Z$8-Z$9)*1000) -> 33104.181 | AA41: =SUM(Z$41,'Statistics NZ'!AA$41-'Statistics NZ'!Z$41,$G$12/5*(AA$8-AA$9)*1000) -> 33234.113 | AB41: =SUM(AA$41,'Statistics NZ'!AB$41-'Statistics NZ'!AA$41,$G$12/5*(AB$8-AB$9)*1000) -> 33968.082 | AC41: =SUM(AB$41,'Statistics NZ'!AC$41-'Statistics NZ'!AB$41,$G$12/5*(AC$8-AC$9)*1000) -> 36138.082 | AD41: =SUM(AC$41,'Statistics NZ'!AD$41-'Statistics NZ'!AC$41,$G$12/5*(AD$8-AD$9)*1000) -> 37268.082 | AE41: =SUM(AD$41,'Statistics NZ'!AE$41-'Statistics NZ'!AD$41,$G$12/5*(AE$8-AE$9)*1000) -> 36728.082 | AF41: =SUM(AE$41,'Statistics NZ'!AF$41-'Statistics NZ'!AE$41,$G$12/5*(AF$8-AF$9)*1000) -> 37778.082 | AG41: =SUM(AF$41,'Statistics NZ'!AG$41-'Statistics NZ'!AF$41,$G$12/5*(AG$8-AG$9)*1000) -> 37848.082 | ... BI41: =SUM(BH$41,'Statistics NZ'!BI$41-'Statistics NZ'!BH$41,$G$12/5*(BI$8-BI$9)*1000) -> 37508.082
A42: 27 | B42: ='Statistics NZ'!B$42*'Economic Forecasts'!D$9*1000000/SUM('Statistics NZ'!B$30:B$110,'Statistics NZ'!B$130:B$210) -> 26211.178 | C42: ='Statistics NZ'!C$42*'Economic Forecasts'!E$9*1000000/SUM('Statistics NZ'!C$30:C$110,'Statistics NZ'!C$130:C$210) -> 26484.751 | D42: ='Statistics NZ'!D$42*'Economic Forecasts'!F$9*1000000/SUM('Statistics NZ'!D$30:D$110,'Statistics NZ'!D$130:D$210) -> 26766.922 | E42: ='Statistics NZ'!E$42*'Economic Forecasts'!G$9*1000000/SUM('Statistics NZ'!E$30:E$110,'Statistics NZ'!E$130:E$210) -> 27175.26 | F42: ='Statistics NZ'!F$42*'Economic Forecasts'!H$9*1000000/SUM('Statistics NZ'!F$30:F$110,'Statistics NZ'!F$130:F$210) -> 27729.566 | G42: ='Statistics NZ'!G$42*'Economic Forecasts'!I$9*1000000/SUM('Statistics NZ'!G$30:G$110,'Statistics NZ'!G$130:G$210) -> 27630.614 | H42: ='Statistics NZ'!H$42*'Economic Forecasts'!J$9*1000000/SUM('Statistics NZ'!H$30:H$110,'Statistics NZ'!H$130:H$210) -> 27559.51 | I42: ='Statistics NZ'!I$42*'Economic Forecasts'!K$9*1000000/SUM('Statistics NZ'!I$30:I$110,'Statistics NZ'!I$130:I$210) -> 27528.383 | ... T42: ='Statistics NZ'!T$42*'Economic Forecasts'!V$9*1000000/SUM('Statistics NZ'!T$30:T$110,'Statistics NZ'!T$130:T$210) -> 34105.649 | U42: =SUM('Statistics NZ'!U$42,$G$12/5*(U$8-U$9)*1000)*'Economic Forecasts'!W$9*1000000/SUM('Statistics NZ'!U$30:U$110,'Statistics NZ'!U$130:U$210,SUM($E$12:$T$13)*(U$8-U$9)*1000) -> 33753.729 | V42: =SUM('Statistics NZ'!V$42,$G$12/5*(V$8-V$9)*1000)*'Economic Forecasts'!X$9*1000000/SUM('Statistics NZ'!V$30:V$110,'Statistics NZ'!V$130:V$210,SUM($E$12:$T$13)*(V$8-V$9)*1000) -> 32567.384 | W42: =SUM('Statistics NZ'!W$42,$G$12/5*(W$8-W$9)*1000)*'Economic Forecasts'!Y$9*1000000/SUM('Statistics NZ'!W$30:W$110,'Statistics NZ'!W$130:W$210,SUM($E$12:$T$13)*(W$8-W$9)*1000) -> 34016.477 | X42: =SUM('Statistics NZ'!X$42,$G$12/5*(X$8-X$9)*1000)*'Economic Forecasts'!Z$9*1000000/SUM('Statistics NZ'!X$30:X$110,'Statistics NZ'!X$130:X$210,SUM($E$12:$T$13)*(X$8-X$9)*1000) -> 33606.328 | Y42: =SUM('Statistics NZ'!Y$42,$G$12/5*(Y$8-Y$9)*1000)*'Economic Forecasts'!AA$9*1000000/SUM('Statistics NZ'!Y$30:Y$110,'Statistics NZ'!Y$130:Y$210,SUM($E$12:$T$13)*(Y$8-Y$9)*1000) -> 32877.553 | Z42: =SUM(Y$42,'Statistics NZ'!Z$42-'Statistics NZ'!Y$42,$G$12/5*(Z$8-Z$9)*1000) -> 32877.44 | AA42: =SUM(Z$42,'Statistics NZ'!AA$42-'Statistics NZ'!Z$42,$G$12/5*(AA$8-AA$9)*1000) -> 33817.372 | AB42: =SUM(AA$42,'Statistics NZ'!AB$42-'Statistics NZ'!AA$42,$G$12/5*(AB$8-AB$9)*1000) -> 33941.34 | AC42: =SUM(AB$42,'Statistics NZ'!AC$42-'Statistics NZ'!AB$42,$G$12/5*(AC$8-AC$9)*1000) -> 34671.34 | AD42: =SUM(AC$42,'Statistics NZ'!AD$42-'Statistics NZ'!AC$42,$G$12/5*(AD$8-AD$9)*1000) -> 36831.34 | AE42: =SUM(AD$42,'Statistics NZ'!AE$42-'Statistics NZ'!AD$42,$G$12/5*(AE$8-AE$9)*1000) -> 37971.34 | AF42: =SUM(AE$42,'Statistics NZ'!AF$42-'Statistics NZ'!AE$42,$G$12/5*(AF$8-AF$9)*1000) -> 37431.34 | AG42: =SUM(AF$42,'Statistics NZ'!AG$42-'Statistics NZ'!AF$42,$G$12/5*(AG$8-AG$9)*1000) -> 38481.34 | ... BI42: =SUM(BH$42,'Statistics NZ'!BI$42-'Statistics NZ'!BH$42,$G$12/5*(BI$8-BI$9)*1000) -> 38041.34
A43: 28 | B43: ='Statistics NZ'!B$43*'Economic Forecasts'!D$9*1000000/SUM('Statistics NZ'!B$30:B$110,'Statistics NZ'!B$130:B$210) -> 25487.166 | C43: ='Statistics NZ'!C$43*'Economic Forecasts'!E$9*1000000/SUM('Statistics NZ'!C$30:C$110,'Statistics NZ'!C$130:C$210) -> 26612.412 | D43: ='Statistics NZ'!D$43*'Economic Forecasts'!F$9*1000000/SUM('Statistics NZ'!D$30:D$110,'Statistics NZ'!D$130:D$210) -> 26698.163 | E43: ='Statistics NZ'!E$43*'Economic Forecasts'!G$9*1000000/SUM('Statistics NZ'!E$30:E$110,'Statistics NZ'!E$130:E$210) -> 27008.541 | F43: ='Statistics NZ'!F$43*'Economic Forecasts'!H$9*1000000/SUM('Statistics NZ'!F$30:F$110,'Statistics NZ'!F$130:F$210) -> 27386.257 | G43: ='Statistics NZ'!G$43*'Economic Forecasts'!I$9*1000000/SUM('Statistics NZ'!G$30:G$110,'Statistics NZ'!G$130:G$210) -> 27846.709 | H43: ='Statistics NZ'!H$43*'Economic Forecasts'!J$9*1000000/SUM('Statistics NZ'!H$30:H$110,'Statistics NZ'!H$130:H$210) -> 27638.111 | I43: ='Statistics NZ'!I$43*'Economic Forecasts'!K$9*1000000/SUM('Statistics NZ'!I$30:I$110,'Statistics NZ'!I$130:I$210) -> 27734.258 | ... T43: ='Statistics NZ'!T$43*'Economic Forecasts'!V$9*1000000/SUM('Statistics NZ'!T$30:T$110,'Statistics NZ'!T$130:T$210) -> 34977.866 | U43: =SUM('Statistics NZ'!U$43,$G$12/5*(U$8-U$9)*1000)*'Economic Forecasts'!W$9*1000000/SUM('Statistics NZ'!U$30:U$110,'Statistics NZ'!U$130:U$210,SUM($E$12:$T$13)*(U$8-U$9)*1000) -> 34793.748 | V43: =SUM('Statistics NZ'!V$43,$G$12/5*(V$8-V$9)*1000)*'Economic Forecasts'!X$9*1000000/SUM('Statistics NZ'!V$30:V$110,'Statistics NZ'!V$130:V$210,SUM($E$12:$T$13)*(V$8-V$9)*1000) -> 34369.333 | W43: =SUM('Statistics NZ'!W$43,$G$12/5*(W$8-W$9)*1000)*'Economic Forecasts'!Y$9*1000000/SUM('Statistics NZ'!W$30:W$110,'Statistics NZ'!W$130:W$210,SUM($E$12:$T$13)*(W$8-W$9)*1000) -> 33204.431 | X43: =SUM('Statistics NZ'!X$43,$G$12/5*(X$8-X$9)*1000)*'Economic Forecasts'!Z$9*1000000/SUM('Statistics NZ'!X$30:X$110,'Statistics NZ'!X$130:X$210,SUM($E$12:$T$13)*(X$8-X$9)*1000) -> 34666.191 | Y43: =SUM('Statistics NZ'!Y$43,$G$12/5*(Y$8-Y$9)*1000)*'Economic Forecasts'!AA$9*1000000/SUM('Statistics NZ'!Y$30:Y$110,'Statistics NZ'!Y$130:Y$210,SUM($E$12:$T$13)*(Y$8-Y$9)*1000) -> 34284.617 | Z43: =SUM(Y$43,'Statistics NZ'!Z$43-'Statistics NZ'!Y$43,$G$12/5*(Z$8-Z$9)*1000) -> 33634.504 | AA43: =SUM(Z$43,'Statistics NZ'!AA$43-'Statistics NZ'!Z$43,$G$12/5*(AA$8-AA$9)*1000) -> 33624.436 | AB43: =SUM(AA$43,'Statistics NZ'!AB$43-'Statistics NZ'!AA$43,$G$12/5*(AB$8-AB$9)*1000) -> 34548.404 | AC43: =SUM(AB$43,'Statistics NZ'!AC$43-'Statistics NZ'!AB$43,$G$12/5*(AC$8-AC$9)*1000) -> 34658.404 | AD43: =SUM(AC$43,'Statistics NZ'!AD$43-'Statistics NZ'!AC$43,$G$12/5*(AD$8-AD$9)*1000) -> 35388.404 | AE43: =SUM(AD$43,'Statistics NZ'!AE$43-'Statistics NZ'!AD$43,$G$12/5*(AE$8-AE$9)*1000) -> 37558.404 | AF43: =SUM(AE$43,'Statistics NZ'!AF$43-'Statistics NZ'!AE$43,$G$12/5*(AF$8-AF$9)*1000) -> 38698.404 | AG43: =SUM(AF$43,'Statistics NZ'!AG$43-'Statistics NZ'!AF$43,$G$12/5*(AG$8-AG$9)*1000) -> 38168.404 | ... BI43: =SUM(BH$43,'Statistics NZ'!BI$43-'Statistics NZ'!BH$43,$G$12/5*(BI$8-BI$9)*1000) -> 38598.404
A44: 29 | B44: ='Statistics NZ'!B$44*'Economic Forecasts'!D$9*1000000/SUM('Statistics NZ'!B$30:B$110,'Statistics NZ'!B$130:B$210) -> 26230.745 | C44: ='Statistics NZ'!C$44*'Economic Forecasts'!E$9*1000000/SUM('Statistics NZ'!C$30:C$110,'Statistics NZ'!C$130:C$210) -> 26072.308 | D44: ='Statistics NZ'!D$44*'Economic Forecasts'!F$9*1000000/SUM('Statistics NZ'!D$30:D$110,'Statistics NZ'!D$130:D$210) -> 26953.554 | E44: ='Statistics NZ'!E$44*'Economic Forecasts'!G$9*1000000/SUM('Statistics NZ'!E$30:E$110,'Statistics NZ'!E$130:E$210) -> 27018.348 | F44: ='Statistics NZ'!F$44*'Economic Forecasts'!H$9*1000000/SUM('Statistics NZ'!F$30:F$110,'Statistics NZ'!F$130:F$210) -> 27278.36 | G44: ='Statistics NZ'!G$44*'Economic Forecasts'!I$9*1000000/SUM('Statistics NZ'!G$30:G$110,'Statistics NZ'!G$130:G$210) -> 27640.437 | H44: ='Statistics NZ'!H$44*'Economic Forecasts'!J$9*1000000/SUM('Statistics NZ'!H$30:H$110,'Statistics NZ'!H$130:H$210) -> 27873.914 | I44: ='Statistics NZ'!I$44*'Economic Forecasts'!K$9*1000000/SUM('Statistics NZ'!I$30:I$110,'Statistics NZ'!I$130:I$210) -> 27744.062 | ... T44: ='Statistics NZ'!T$44*'Economic Forecasts'!V$9*1000000/SUM('Statistics NZ'!T$30:T$110,'Statistics NZ'!T$130:T$210) -> 36732.21 | U44: =SUM('Statistics NZ'!U$44,$G$12/5*(U$8-U$9)*1000)*'Economic Forecasts'!W$9*1000000/SUM('Statistics NZ'!U$30:U$110,'Statistics NZ'!U$130:U$210,SUM($E$12:$T$13)*(U$8-U$9)*1000) -> 35675.289 | V44: =SUM('Statistics NZ'!V$44,$G$12/5*(V$8-V$9)*1000)*'Economic Forecasts'!X$9*1000000/SUM('Statistics NZ'!V$30:V$110,'Statistics NZ'!V$130:V$210,SUM($E$12:$T$13)*(V$8-V$9)*1000) -> 35408.919 | W44: =SUM('Statistics NZ'!W$44,$G$12/5*(W$8-W$9)*1000)*'Economic Forecasts'!Y$9*1000000/SUM('Statistics NZ'!W$30:W$110,'Statistics NZ'!W$130:W$210,SUM($E$12:$T$13)*(W$8-W$9)*1000) -> 34996.873 | X44: =SUM('Statistics NZ'!X$44,$G$12/5*(X$8-X$9)*1000)*'Economic Forecasts'!Z$9*1000000/SUM('Statistics NZ'!X$30:X$110,'Statistics NZ'!X$130:X$210,SUM($E$12:$T$13)*(X$8-X$9)*1000) -> 33853.96 | Y44: =SUM('Statistics NZ'!Y$44,$G$12/5*(Y$8-Y$9)*1000)*'Economic Forecasts'!AA$9*1000000/SUM('Statistics NZ'!Y$30:Y$110,'Statistics NZ'!Y$130:Y$210,SUM($E$12:$T$13)*(Y$8-Y$9)*1000) -> 35344.869 | Z44: =SUM(Y$44,'Statistics NZ'!Z$44-'Statistics NZ'!Y$44,$G$12/5*(Z$8-Z$9)*1000) -> 35034.756 | AA44: =SUM(Z$44,'Statistics NZ'!AA$44-'Statistics NZ'!Z$44,$G$12/5*(AA$8-AA$9)*1000) -> 34364.688 | AB44: =SUM(AA$44,'Statistics NZ'!AB$44-'Statistics NZ'!AA$44,$G$12/5*(AB$8-AB$9)*1000) -> 34348.657 | AC44: =SUM(AB$44,'Statistics NZ'!AC$44-'Statistics NZ'!AB$44,$G$12/5*(AC$8-AC$9)*1000) -> 35258.657 | AD44: =SUM(AC$44,'Statistics NZ'!AD$44-'Statistics NZ'!AC$44,$G$12/5*(AD$8-AD$9)*1000) -> 35378.657 | AE44: =SUM(AD$44,'Statistics NZ'!AE$44-'Statistics NZ'!AD$44,$G$12/5*(AE$8-AE$9)*1000) -> 36108.657 | AF44: =SUM(AE$44,'Statistics NZ'!AF$44-'Statistics NZ'!AE$44,$G$12/5*(AF$8-AF$9)*1000) -> 38278.657 | AG44: =SUM(AF$44,'Statistics NZ'!AG$44-'Statistics NZ'!AF$44,$G$12/5*(AG$8-AG$9)*1000) -> 39428.657 | ... BI44: =SUM(BH$44,'Statistics NZ'!BI$44-'Statistics NZ'!BH$44,$G$12/5*(BI$8-BI$9)*1000) -> 39168.657
